Workbook

Sheet INF
A23: NOMBRE | B23: RFC | C23: N. COMERCIAL | D23: CLAVE | E23: F. DE PAGO | F23: CLAVE | G23: USO DE LA FACTURA | H23: CORREO | I23: DIRECCION
A24: EFREN ABUNDEZ REYNA | B24: AURE7306187IA | D24: 01 | E24: EFECTIVO | F24: G01 | G24: ADQUISICION DE MERCANCIA | H24: EFRENABUNDEZREINA@GMAIL.COM | I24: FACTURAS DE MENOS DE $4,000
A25: LUIS ALEJANDRO HERNANDEZ REYNA | B25: HERL850705AL2 | C25: LOS CARACOLES | D25: 03 | E25: PAGO TRANSFERENCIA | F25: G01 | G25: ADQUISICION DE MERCANCIA | H25: alexhdzre@gmail.com
A26: ANA BEATRIZ ESTRADA ARGOTE | B26: EAAA860701UP2 | C26: MARISCOS MARLEY | D26: 03 | E26: PAGO TRANSFERENCIA | F26: G03 | G26: GASTO EN GENERAL
A27: SERGIO ROMERO DURAN | B27: RODS620908QAA | C27: YEYOS | D27: 01 | E27: EFECTIVO | F27: G01 | G27: ADQUISICION DE MERCANCIA | I27: FACTURAS DE MENOS DE $2,000
A28: MARIELA OLMOS GAONA | B28: OOGM010703NX1 | C28: MARISCOS MAR VELERO | D28: 01 | E28: PAGO TRANSFERENCIA | F28: G01 | G28: ADQUISICION DE MERCANCIA | H28: marveleroseafood@outlook.com | I28: David Galván Bermúdez 101 Col. Cristo Rey
A29: LUCIANO MIJAIL ORTEGA MUÑOZ | B29: OEML881105IK2 | D29: 01 | E29: PAGO TRANSFERENCIA | F29: G01 | G29: ADQUISICION DE MERCANCIA | H29: villaluna3107@gmail.com | I29: Brisas de San Simón 223 | J29: Colonia Brisas de San Nicolas | K29: Código Postal 37297
A30: GUSTAVO HUMBERTO VELASCO GALVEZ | B30: VEGG9211019T1 | C30: DELIMAR | E30: PAGO TRANSFERENCIA | F30: G01 | G30: ADQUISICION DE MERCANCIA
A31: JESUS AGUSTIN VELAZQUEZ FLORES | B31: VEFJ900303M65 | D31: 03 | E31: PAGO TRANSFERENCIA | F31: G01 | G31: ADQUISICION DE MERCANCIA
A32: KARLA ESTEFANIA SALAZAR FLORES | B32: SAFK9807277N1 | E32: EFECTIVO | G32: ADQUISICION DE MERCANCIA | J32: crisma-flores@hotmail.con
A33: ANGEL TERRAZAS MONROY | B33: TEMA7105035N4

Sheet P.F.A.E.
C4: PAGOS PROVISIONLAES REGIMEN DE PERSONAS FISICAS CON ACTIVIDADES EMPRESARIALES Y PROFESIONALES
C5: 1 | D5: 2 | E5: 3 | F5: 4 | G5: 5 | H5: 6 | I5: 7 | J5: 8 | K5: 9 | L5: 10 | M5: 11 | N5: 12
C6: ENERO | D6: FEBRERO | E6: MARZO | F6: ABRIL | G6: MAYO | H6: JUNIO | I6: JULIO | J6: AGOSTO | K6: SEPTIEMBRE | L6: OCTUBRE | M6: NOVIEMBRE | N6: DICIEMBRE | P6: DEL EJERCICIO | Q6: SALDO ANUAL
A7: INGRESOS DEL PERIODO | C7: =+'control p.y g.'!D3 -> 310579 | D7: =+'control p.y g.'!D4 -> 230572.03 | E7: =+'control p.y g.'!D5 -> 240808.89 | F7: =+'control p.y g.'!D6 -> 357091.76 | G7: =+'control p.y g.'!D7 -> 362431.69 | H7: =+'control p.y g.'!D8 -> 424706 | I7: =+'control p.y g.'!D9 -> 272396.1 | J7: =+'control p.y g.'!D10 -> 247594.93 | K7: =+'control p.y g.'!D11 -> 336307.21 | L7: =+'control p.y g.'!D12 -> 359882.55 | M7: =+'control p.y g.'!D13 -> 279550.69 | N7: =+'control p.y g.'!D14 -> 524795.93 | P7: =SUM(C7:O7) -> 3946716.8
A8: INGRESOS ACUMULABLES | C8: =C7+B8 -> 310579 | D8: =D7+C8 -> 541151.03 | E8: =E7+D8 -> 781959.92 | F8: =F7+E8 -> 1139051.7 | G8: =G7+F8 -> 1501483.4 | H8: =H7+G8 -> 1926189.4 | I8: =I7+H8 -> 2198585.5 | J8: =J7+I8 -> 2446180.4 | ... N8: =N7+M8 -> 3946716.8 | P8: =P7 -> 3946716.8 | Q8: =SUM(C7:N7) -> 3946716.8
A10: DEDUCCIONES PERSONALES | C10: 0 | D10: 0 | E10: 0 | F10: 0 | G10: 0 | H10: 0 | I10: 0 | J10: 0 | K10: 0 | L10: 0 | M10: 0 | N10: 0 | O10: 0 | P10: =SUM(C10:O10) -> 0
A11: SUELDOS Y SALARIOS | B11: 502 | C11: 0 | P11: =SUM(C11:N11) -> 0
A12: DEPRECIACIONES | B12: 560 | P12: =SUM(C12:N12) -> 0
A13: DEDUCCIONES DEL PERIODO | C13: =+'control p.y g.'!C3 -> 303686.29 | D13: =+'control p.y g.'!C4 -> 224265.94 | E13: =+'control p.y g.'!C5 -> 236808.89 | F13: =+'control p.y g.'!C6 -> 354090.89 | G13: =+'control p.y g.'!C7 -> 359428.77 | H13: =+'control p.y g.'!C8 -> 426702.99 | I13: =+'control p.y g.'!C9 -> 260003.44 | J13: =+'control p.y g.'!C10 -> 240167.35 | K13: =+'control p.y g.'!C11 -> 329447.37 | L13: =+'control p.y g.'!C12 -> 355882.93 | M13: =+'control p.y g.'!C13 -> 275458.4 | N13: =+'control p.y g.'!C14 -> 520718.05 | P13: =SUM(C13:O13) -> 3886661.3
A14: TOTAL DE DEDUCCIONES | C14: =C13+C11+C12 -> 303686.29 | D14: =D13+D12+C14+D11 -> 527952.23 | E14: =E13+E12+D14+E11 -> 764761.12 | F14: =F13+F12+E14+F11 -> 1118852 | G14: =G13+G12+F14+G11 -> 1478280.8 | H14: =H13+H12+G14+H11 -> 1904983.8 | I14: =I13+I12+H14+I11 -> 2164987.2 | J14: =J13+J12+I14+J11 -> 2405154.6 | K14: =K13+K12+J14+K11 -> 2734601.9 | ... N14: =N13+N12+M14+N11 -> 3886661.3 | P14: =SUM(P10:P13) -> 3886661.3 | Q14: =SUM(C13:N13) -> 3886661.3
A16: PERIDA FISCAL EJ. ANTES. | P16: =IF(P8-P14>0,N16,0) -> 0
A18: BASE GRAVABLE | C18: =IF((C8-C14-C16)>0,(C8-C14-C16),0) -> 6892.71 | D18: =IF((D8-D14-D16)>0,(D8-D14-D16),0) -> 13198.804 | E18: =IF((E8-E14-E16)>0,(E8-E14-E16),0) -> 17198.798 | F18: =IF((F8-F14-F16)>0,(F8-F14-F16),0) -> 20199.664 | G18: =IF((G8-G14-G16)>0,(G8-G14-G16),0) -> 23202.583 | H18: =IF((H8-H14-H16)>0,(H8-H14-H16),0) -> 21205.593 | I18: =IF((I8-I14-I16)>0,(I8-I14-I16),0) -> 33598.256 | J18: =IF((J8-J14-J16)>0,(J8-J14-J16),0) -> 41025.842 | ... N18: =IF((N8-N14-N16)>0,(N8-N14-N16),0) -> 60055.477 | P18: =IF((P8-P14-P16)>0,P8-P14-P16,0) -> 60055.477 | Q18: =Q8-Q14 -> 60055.477
A20: - LIMITE INFERIOR | C20: =IF(C18>0,VLOOKUP(C18,'T ISR'!A5:B15,1,1),0) -> 6332.06 | D20: =IF(D18>0,VLOOKUP(D18,'T ISR'!F5:G15,1,1),0) -> 12664.11 | E20: =IF(E18>0,VLOOKUP(E18,'T ISR'!A21:B30,1,1),0) -> 2238.13 | F20: =IF(F18>0,VLOOKUP(F18,'T ISR'!F21:G31,1,1),0) -> 2984.17 | G20: =IF(G18>0,VLOOKUP(G18,'T ISR'!A37:B47,1,1),0) -> 3730.21 | H20: =IF(H18>0,VLOOKUP(H18,'T ISR'!F37:G47,1,1),0) -> 4476.25 | I20: =IF(I18>0,VLOOKUP(I18,'T ISR'!A53:B63,1,1),0) -> 5222.29 | J20: =IF(J18>0,VLOOKUP(J18,'T ISR'!F53:G63,1,1),0) -> 5968.33 | K20: =IF(K18>0,VLOOKUP(K18,'T ISR'!A69:B79,1,1),0) -> 6714.37 | L20: =IF(L18>0,VLOOKUP(L18,'T ISR'!F69:G79,1,1),0) -> 7460.41 | M20: =IF(M18>0,VLOOKUP(M18,'T ISR'!A85:B95,1,1),0) -> 8206.45 | N20: =IF(N18>0,VLOOKUP(N18,'T ISR'!F85:G95,1,1),0) -> 8952.5
A22: = EXCEDENTE S/LIM INF. | C22: =C18-C20 -> 560.65 | D22: =D18-D20 -> 534.69448 | E22: =E18-E20 -> 14960.668 | F22: =F18-F20 -> 17215.494 | G22: =G18-G20 -> 19472.373 | H22: =H18-H20 -> 16729.343 | I22: =I18-I20 -> 28375.966 | J22: =J18-J20 -> 35057.512 | ... N22: =N18-N20 -> 51102.977
A24: x % DE TASA | C24: =IF(C18>0,VLOOKUP(C28,'T ISR'!C5:D15,2,0),0) -> 0.1088 | D24: =VLOOKUP(D18,'T ISR'!F5:I15,4,1) -> 0.1088 | E24: =VLOOKUP(E18,'T ISR'!A21:D31,4,1) -> 0.064 | F24: =VLOOKUP(F18,'T ISR'!F21:I31,4,1) -> 0.064 | G24: =VLOOKUP(G18,'T ISR'!A37:D47,4,1) -> 0.064 | H24: =VLOOKUP(H18,'T ISR'!F37:I47,4,1) -> 0.064 | I24: =VLOOKUP(I18,'T ISR'!A53:D63,4,1) -> 0.064 | J24: =VLOOKUP(J18,'T ISR'!F53:I63,4,1) -> 0.064 | K24: =VLOOKUP(K18,'T ISR'!A69:D79,4,1) -> 0.064 | L24: =VLOOKUP(L18,'T ISR'!F69:I79,4,1) -> 0.064 | M24: =VLOOKUP(M18,'T ISR'!A85:D95,4,1) -> 0.064 | N24: =VLOOKUP(N18,'T ISR'!F85:I95,4,1) -> 0.064
A26: = IMPUESTO MARGINAL | C26: =C22*C24 -> 60.99872 | D26: =D22*D24 -> 58.17476 | E26: =E22*E24 -> 957.48274 | F26: =F22*F24 -> 1101.7916 | G26: =G22*G24 -> 1246.2319 | H26: =H22*H24 -> 1070.6779 | I26: =I22*I24 -> 1816.0619 | J26: =J22*J24 -> 2243.6807 | ... N26: =N22*N24 -> 3270.5905
A28: + CUOTA FIJA | C28: =IF(C18>0,VLOOKUP(C18,'T ISR'!A5:C15,3,1),0) -> 371.83 | D28: =IF(D18>0,VLOOKUP(D18,'T ISR'!F5:H15,3,1),0) -> 743.66 | E28: =IF(E18>0,VLOOKUP(E18,'T ISR'!A21:C31,3,1),0) -> 42.96 | F28: =IF(F18>0,VLOOKUP(F18,'T ISR'!F21:H31,3,1),0) -> 57.28 | G28: =IF(G18>0,VLOOKUP(G18,'T ISR'!A37:C47,3,1),0) -> 71.6 | H28: =IF(H18>0,VLOOKUP(H18,'T ISR'!F37:H47,3,1),0) -> 85.92 | I28: =IF(I18>0,VLOOKUP(I18,'T ISR'!A53:C63,3,1),0) -> 100.24 | J28: =IF(J18>0,VLOOKUP(J18,'T ISR'!F53:H63,3,1),0) -> 114.56 | K28: =IF(K18>0,VLOOKUP(K18,'T ISR'!A69:C79,3,1),0) -> 128.88 | L28: =IF(L18>0,VLOOKUP(L18,'T ISR'!F69:H79,3,1),0) -> 143.2 | M28: =IF(M18>0,VLOOKUP(M18,'T ISR'!A85:C95,3,1),0) -> 157.52 | N28: =IF(N18>0,VLOOKUP(N18,'T ISR'!F85:H95,3,1),0) -> 171.88
A30: = IMPUESTO DETERMINADO | C30: =C26+C28 -> 432.82872 | D30: =D26+D28 -> 801.83476 | E30: =E26+E28 -> 1000.4427 | F30: =F26+F28 -> 1159.0716 | G30: =G26+G28 -> 1317.8319 | H30: =H26+H28 -> 1156.5979 | I30: =I26+I28 -> 1916.3019 | J30: =J26+J28 -> 2358.2407 | ... O30: =O26+O28 -> 0
A32: - PAGO PROVISIONAL | C32: 0 | D32: =IF(C36>0,C32+C33+C35+C36,C32+C33+C35) -> 432.82872 | E32: =IF(D36>0,D32+D33+D35+D36,D32+D33+D35) -> 801.83476 | F32: =IF(E36>0,E32+E33+E35+E36,E32+E33+E35) -> 1000.4427 | G32: =IF(F36>0,F32+F33+F35+F36,F32+F33+F35) -> 1159.0716 | H32: =IF(G36>0,G32+G33+G35+G36,G32+G33+G35) -> 1317.8319 | I32: =IF(H36>0,H32+H33+H35+H36,H32+H33+H35) -> 1317.8319 | J32: =IF(I36>0,I32+I33+I35+I36,I32+I33+I35) -> 1916.3019 | K32: =IF(J36>0,J32+J33+J35+J36,J32+J33+J35) -> 2358.2407 | ... N32: =IF(M36>0,M32+M33+M35+M36,M32+M33+M35) -> 3214.8732
A33: - SUBSIDIO PARA EL EMPLEO | C33: 0 | D33: 0 | E33: 0 | F33: 0 | G33: 0 | H33: 0 | I33: 0 | J33: 0 | K33: 0 | L33: 0 | M33: 0 | N33: 0
A34: - I.S.R. RETENIDO | C34: 0 | D34: 0 | E34: 0 | F34: 0 | G34: 0 | H34: 0 | I34: 0 | J34: 0 | K34: 0 | L34: 0 | M34: 0 | N34: 0 | Q34: =SUM(C34:N34) -> 0
A36: = ISR POR PAGAR | B36: 1 | C36: =IF((C30-C32-C33-C34)>0,C30-C32-C33-C34,0) -> 432.82872 | D36: =IF((D30-D32-D33-D34)>0,D30-D32-D33-D34,0) -> 369.00604 | E36: =IF((E30-E32-E33-E34)>0,E30-E32-E33-E34,0) -> 198.60798 | F36: =IF((F30-F32-F33-F34)>0,F30-F32-F33-F34,0) -> 158.62891 | G36: =IF((G30-G32-G33-G34)>0,G30-G32-G33-G34,0) -> 158.76022 | H36: =IF((H30-H32-H33-H34)>0,H30-H32-H33-H34,0) -> 0 | I36: =IF((I30-I32-I33-I34)>0,I30-I32-I33-I34,0) -> 598.46999 | J36: =IF((J30-J32-J33-J34)>0,J30-J32-J33-J34,0) -> 441.93888 | ... N36: =IF((N30-N32-N33-N34)>0,N30-N32-N33-N34,0) -> 227.59731 | Q36: =SUM(B36:P36) -> 3443.4705

Sheet IVA
A2: DETERMINACION DE IVA
A3: PERSONAS FISICAS CON ACTIVIDADES EMPRESARIALES
A5: Cta. Ing. X Vta | B5: Concepto | C5: Ene | D5: Feb | E5: Mar | F5: Abr | G5: May | H5: Jun | I5: Jul | J5: Ago | K5: Sep | L5: Oct | M5: Nov | N5: Dic | O5: TOTAL
C6: 1 | D6: 2 | E6: 3 | F6: 4 | G6: 5 | H6: 6 | I6: 7 | J6: 8 | K6: 9 | L6: 10 | M6: 11 | N6: 12
B8: IVA CAUSADO
A9: 12 | B9: Ingresos Gravados al 16% | C9: 0 | D9: =+ING!K17+ING!K23 -> 304.16552 | E9: 0 | F9: 137.24 | G9: 207.31 | H9: 0 | I9: 418.1 | J9: 0 | K9: 0 | L9: 0 | M9: 0 | N9: 0 | O9: =SUM(C9:N9) -> 1066.8155
A10: 13 | B10: Ingresos Gravados al 8% | C10: 0 | D10: 0 | E10: 0 | F10: 0 | G10: 0 | H10: 0 | I10: 0 | J10: 0 | K10: 0 | L10: 0 | M10: 0 | N10: 0 | O10: =SUM(C10:N10) -> 0
A11: 3 | B11: Ingresos Gravados al 0% | C11: =+'P.F.A.E.'!C9 -> 0 | D11: =+ING!J15+ING!J16+ING!J18+ING!J19+ING!J20+ING!J21+ING!J22+ING!J24+ING!J30 -> 228671 | E11: =+'P.F.A.E.'!E7 -> 240808.89 | F11: =+'P.F.A.E.'!F7 -> 357091.76 | G11: =+'P.F.A.E.'!G7 -> 362431.69 | H11: =+'P.F.A.E.'!H7 -> 424706 | I11: =+'P.F.A.E.'!I7 -> 272396.1 | J11: =+'P.F.A.E.'!J7 -> 247594.93 | K11: =+'P.F.A.E.'!K7 -> 336307.21 | L11: =+'P.F.A.E.'!L7 -> 359882.55 | ... N11: =+'P.F.A.E.'!N7 -> 524795.93 | O11: =SUM(C11:N11) -> 3634236.7
A12: 4 | B12: Ingresos Exentos | C12: 0 | D12: 0 | E12: 0 | F12: 0 | G12: 0 | H12: 0 | I12: 0 | J12: 0 | K12: 0 | L12: 0 | M12: 0 | N12: 0 | O12: =SUM(C12:N12) -> 0
A13: 1 | B13: Ingresos Gravados al 15% | C13: 0 | D13: 0 | E13: 0 | F13: 0 | G13: 0 | H13: 0 | I13: 0 | J13: 0 | K13: 0 | L13: 0 | M13: 0 | N13: 0 | O13: =SUM(C13:N13) -> 0
A14: 2 | B14: Ingresos Gravados al 10% | C14: 0 | D14: 0 | E14: 0 | F14: 0 | G14: 0 | H14: 0 | I14: 0 | J14: 0 | K14: 0 | L14: 0 | M14: 0 | N14: 0 | O14: =SUM(C14:N14) -> 0
A15: 5 | B15: Otras Bases | C15: 0 | D15: 0 | E15: 0 | F15: 0 | G15: 0 | H15: 0 | I15: 0 | J15: 0 | K15: 0 | L15: 0 | M15: 0 | N15: 0 | O15: =SUM(C15:N15) -> 0
B16: Total Ingresos | C16: =SUM(C9:C15) -> 0 | D16: =SUM(D9:D15) -> 228975.17 | E16: =SUM(E9:E15) -> 240808.89 | F16: =SUM(F9:F15) -> 357229 | G16: =SUM(G9:G15) -> 362639 | H16: =SUM(H9:H15) -> 424706 | I16: =SUM(I9:I15) -> 272814.2 | J16: =SUM(J9:J15) -> 247594.93 | ... N16: =SUM(N9:N15) -> 524795.93 | O16: =SUM(C16:N16) -> 3635303.6
A18: 12 | B18: IVA trasladado al 16% | C18: =C9*0.16 -> 0 | D18: =D9*0.16 -> 48.666483 | E18: =E9*0.16 -> 0 | F18: =F9*0.16 -> 21.9584 | G18: =G9*0.16 -> 33.1696 | H18: =H9*0.16 -> 0 | I18: =I9*0.16 -> 66.896 | J18: =J9*0.16 -> 0 | ... N18: =N9*0.16 -> 0 | O18: =SUM(C18:N18) -> 170.69048
A19: 13 | B19: IVA trasladado al 8% | C19: =C10*0.8% -> 0 | D19: =D10*0.8% -> 0 | E19: =E10*0.8% -> 0 | F19: =F10*0.8% -> 0 | G19: =G10*0.8% -> 0 | H19: =H10*0.8% -> 0 | I19: =I10*0.8% -> 0 | J19: =J10*0.8% -> 0 | ... N19: =N10*0.8% -> 0 | O19: =SUM(C19:N19) -> 0
A20: 8 | B20: IVA Retenido | C20: 0 | D20: 0 | E20: 0 | F20: 0 | G20: 0 | H20: 0 | I20: 0 | J20: 0 | K20: 0 | L20: 0 | M20: 0 | N20: 0 | O20: =SUM(C20:N20) -> 0
B21: Total IVA Trasladado | C21: =C18+C19-C20 -> 0 | D21: =D18+D19-D20 -> 48.666483 | E21: =E18+E19-E20 -> 0 | F21: =F18+F19-F20 -> 21.9584 | G21: =G18+G19-G20 -> 33.1696 | H21: =H18+H19-H20 -> 0 | I21: =I18+I19-I20 -> 66.896 | J21: =J18+J19-J20 -> 0 | ... O21: =O18+O19-O20 -> 170.69048
B23: IVA ACREDITABLE
A24: 12 | B24: Base gravable al 16% | C24: =+'control p.y g.'!I3 -> 303686.29 | D24: 36577 | E24: =+'control p.y g.'!I5 -> 12764.778 | F24: =+'control p.y g.'!I6 -> 7445.7775 | G24: =+'control p.y g.'!I7 -> 10422.32 | H24: =+'control p.y g.'!I8 -> 159173 | I24: =+'control p.y g.'!I9 -> 15790.578 | J24: =+'control p.y g.'!I10 -> 20983.1 | K24: =+'control p.y g.'!I11 -> 19558.553 | L24: =+'control p.y g.'!I12 -> 25572.574 | M24: =+'control p.y g.'!I13 -> 18207.446 | N24: =+'control p.y g.'!I14 -> 19375.174 | O24: =SUM(C24:N24) -> 649556.59
A25: 13 | B25: Base gravable al 8% | C25: 0 | D25: 0 | E25: 0 | F25: 0 | G25: 0 | H25: 0 | I25: 0 | J25: 0 | K25: 0 | L25: 0 | M25: 0 | N25: 0 | O25: =SUM(C25:N25) -> 0
A26: 3 | B26: Base gravable al 0% | C26: 0 | D26: 0 | E26: 0 | F26: 0 | G26: 0 | H26: 0 | I26: 0 | J26: 0 | K26: 0 | L26: 0 | M26: 0 | N26: 0 | O26: =SUM(C26:N26) -> 0
A27: 4 | B27: Base gravable exenta | C27: 0 | D27: 0 | E27: 0 | F27: 0 | G27: 0 | H27: 0 | I27: 0 | J27: 0 | K27: 0 | L27: 0 | M27: 0 | N27: 0 | O27: =SUM(C27:N27) -> 0
B28: Total Base IVA Acreditable | C28: =SUM(C24:C27) -> 303686.29 | D28: =SUM(D24:D27) -> 36577 | E28: =SUM(E24:E27) -> 12764.778 | F28: =SUM(F24:F27) -> 7445.7775 | G28: =SUM(G24:G27) -> 10422.32 | H28: =SUM(H24:H27) -> 159173 | I28: =SUM(I24:I27) -> 15790.578 | J28: =SUM(J24:J27) -> 20983.1 | ... N28: =SUM(N24:N27) -> 19375.174 | O28: =SUM(C28:N28) -> 649556.59
A30: 12 | B30: IVA Acreditable al 16% | C30: =C24*0.16 -> 48589.806 | D30: =D24*0.16 -> 5852.32 | E30: =E24*0.16 -> 2042.3644 | F30: =F24*0.16 -> 1191.3244 | G30: =G24*0.16 -> 1667.5712 | H30: =H24*0.16 -> 25467.68 | I30: 0 | J30: =J24*0.16 -> 3357.296 | K30: =K24*0.16 -> 3129.3684 | L30: =L24*0.16 -> 4091.6118 | M30: =M24*0.16 -> 2913.1914 | N30: =N24*0.16 -> 3100.0278 | O30: =SUM(C30:N30) -> 101402.56
A31: 13 | B31: IVA Acreditable al 8% | C31: =C25*8% -> 0 | D31: =D25*8% -> 0 | E31: =E25*8% -> 0 | F31: =F25*8% -> 0 | G31: =G25*8% -> 0 | H31: =H25*8% -> 0 | I31: =I25*8% -> 0 | J31: =J25*8% -> 0 | ... N31: =N25*8% -> 0 | O31: =SUM(C31:N31) -> 0
A32: 8 | B32: IVA Retenido | C32: 0 | D32: 0 | E32: 0 | F32: 0 | G32: 0 | H32: 0 | I32: 0 | J32: 0 | K32: 0 | L32: 0 | M32: 0 | N32: 0 | O32: =SUM(C32:N32) -> 0
A33: 8 | B33: IVA Retenido Meses Anteriores | C33: 0 | D33: =C32 -> 0 | E33: =D32 -> 0 | F33: =E32 -> 0 | G33: =F32 -> 0 | H33: =G32 -> 0 | I33: =H32 -> 0 | J33: =I32 -> 0 | K33: =J32 -> 0 | ... N33: =M32 -> 0 | O33: =SUM(C33:N33) -> 0
B34: Total IVA Acreditable | C34: =C30+C31-C32+C33 -> 48589.806 | D34: =D30+D31-D32+D33 -> 5852.32 | E34: =E30+E31-E32+E33 -> 2042.3644 | F34: =F30+F31-F32+F33 -> 1191.3244 | G34: =G30+G31-G32+G33 -> 1667.5712 | H34: =H30+H31-H32+H33 -> 25467.68 | I34: =I30+I31-I32+I33 -> 0 | J34: =J30+J31-J32+J33 -> 3357.296 | ... N34: =N30+N31-N32+N33 -> 3100.0278 | O34: =SUM(C34:N34) -> 101402.56
D35: =D37-D32 -> 0
B36: Determinación del IVA | D36: 1
B37: IVA a cargo del periodo | C37: =IF(C21>C34,C21-C34,0) -> 0 | D37: =IF(D21>D34,D21-D34,0) -> 0 | E37: =IF(E21>E34,E21-E34,0) -> 0 | F37: =IF(F21>F34,F21-F34,0) -> 0 | G37: =IF(G21>G34,G21-G34,0) -> 0 | H37: =IF(H21>H34,H21-H34,0) -> 0 | I37: =IF(I21>I34,I21-I34,0) -> 66.896 | J37: =IF(J21>J34,J21-J34,0) -> 0 | ... N37: =IF(N21>N34,N21-N34,0) -> 0 | O37: =SUM(C37:N37) -> 66.896
B38: IVA a favor del periodo | C38: =IF(C21<C34,C34-C21,0) -> 48589.806 | D38: =IF(D21<D34,D34-D21,0) -> 5803.6535 | E38: =IF(E21<E34,E34-E21,0) -> 2042.3644 | F38: =IF(F21<F34,F34-F21,0) -> 1169.366 | G38: =IF(G21<G34,G34-G21,0) -> 1634.4016 | H38: =IF(H21<H34,H34-H21,0) -> 25467.68 | I38: =IF(I21<I34,I34-I21,0) -> 0 | J38: =IF(J21<J34,J34-J21,0) -> 3357.296 | ... N38: =IF(N21<N34,N34-N21,0) -> 3100.0278 | O38: =SUM(C38:N38) -> 101298.77
B39: IVA pendiente por acreditar | C39: 0 | D39: =IF(C41<0,C41*-1,C41) -> 48589.806 | E39: =IF(D41<0,D41*-1,D41) -> 54393.46 | F39: =IF(E41<0,E41*-1,E41) -> 56435.824 | G39: =IF(F41<0,F41*-1,F41) -> 57605.19 | H39: =IF(G41<0,G41*-1,G41) -> 59239.592 | I39: =IF(H41<0,H41*-1,H41) -> 84707.272 | J39: =IF(I41<0,I41*-1,I41) -> 84640.376 | K39: =IF(J41<0,J41*-1,J41) -> 87997.672 | ... N39: =IF(M41<0,M41*-1,M41) -> 98131.844 | O39: =N41 -> 101231.87
B40: IVA a cargo | C40: =IF(C37>C39,C37-C39,0) -> 0 | D40: =IF(D37>D39,D37-D39,0) -> 0 | E40: =IF(E37>E39,E37-E39,0) -> 0 | F40: =IF(F37>F39,F37-F39,0) -> 0 | G40: =IF(G37>G39,G37-G39,0) -> 0 | H40: =IF(H37>H39,H37-H39,0) -> 0 | I40: =IF(I37>I39,I37-I39,0) -> 0 | J40: =IF(J37>J39,J37-J39,0) -> 0 | ... N40: =IF(N37>N39,N37-N39,0) -> 0 | O40: =SUM(C40:N40) -> 0
B41: IVA a favor | C41: =IF(C40=0,IF(C37=0,C38+C39,C39-C37),0) -> 48589.806 | D41: =IF(D40=0,IF(D37=0,D38+D39,D39-D37),0) -> 54393.46 | E41: =IF(E40=0,IF(E37=0,E38+E39,E39-E37),0) -> 56435.824 | F41: =IF(F40=0,IF(F37=0,F38+F39,F39-F37),0) -> 57605.19 | G41: =IF(G40=0,IF(G37=0,G38+G39,G39-G37),0) -> 59239.592 | H41: =IF(H40=0,IF(H37=0,H38+H39,H39-H37),0) -> 84707.272 | I41: =IF(I40=0,IF(I37=0,I38+I39,I39-I37),0) -> 84640.376 | J41: =IF(J40=0,IF(J37=0,J38+J39,J39-J37),0) -> 87997.672 | ... N41: =IF(N40=0,IF(N37=0,N38+N39,N39-N37),0) -> 101231.87

Sheet T ISR
A1: ENERO | F1: FEBRERO
A2: Límite inferior | B2: Límite superior | C2: Cuota fija | D2: Por ciento para aplicarse sobre | F2: Límite inferior | G2: Límite superior | H2: Cuota fija | I2: Por ciento para aplicarse sobre
D3: el excedente del límite inferior | I3: el excedente del límite inferior
A4: $ | B4: $ | C4: $ | D4: % | F4: $ | G4: $ | H4: $ | I4: %
A5: 0.01 | B5: 746.04 | C5: 0 | D5: 0.0192 | F5: 0.01 | G5: 1492.08 | H5: 0 | I5: 0.0192
A6: 746.05 | B6: 6332.05 | C6: 14.32 | D6: 0.064 | F6: 1492.09 | G6: 12664.1 | H6: 28.64 | I6: 0.064
A7: 6332.06 | B7: 11128.01 | C7: 371.83 | D7: 0.1088 | F7: 12664.11 | G7: 22256.02 | H7: 743.66 | I7: 0.1088
A8: 11128.02 | B8: 12935.82 | C8: 893.63 | D8: 0.16 | F8: 22256.03 | G8: 25871.64 | H8: 1787.26 | I8: 0.16
A9: 12935.83 | B9: 15487.71 | C9: 1182.88 | D9: 0.1792 | F9: 25871.65 | G9: 30975.42 | H9: 2365.76 | I9: 0.1792
A10: 15487.72 | B10: 31236.49 | C10: 1640.18 | D10: 0.2136 | F10: 30975.43 | G10: 62472.98 | H10: 3280.36 | I10: 0.2136
A11: 31236.5 | B11: 49233 | C11: 5004.12 | D11: 0.2352 | F11: 62472.99 | G11: 98466 | H11: 10008.24 | I11: 0.2352
A12: 49233.01 | B12: 93993.9 | C12: 9236.89 | D12: 0.3 | F12: 98466.01 | G12: 187987.8 | H12: 18473.78 | I12: 0.3
A13: 93993.91 | B13: 125325.2 | C13: 22665.17 | D13: 0.32 | F13: 187987.81 | G13: 250650.4 | H13: 45330.34 | I13: 0.32
A14: 125325.21 | B14: 375975.61 | C14: 32691.18 | D14: 0.34 | F14: 250650.41 | G14: 751951.22 | H14: 65382.36 | I14: 0.34
A15: 375975.62 | B15: En adelante | C15: 117912.32 | D15: 0.35 | F15: 751951.23 | G15: En adelante | H15: 235824.64 | I15: 0.35
A17: MARZO | F17: ABRIL
A18: Límite inferior | B18: Límite superior | C18: Cuota fija | D18: Por ciento para aplicarse sobre | F18: Límite inferior | G18: Límite superior | H18: Cuota fija | I18: Por ciento para aplicarse sobre
D19: el excedente del límite inferior | I19: el excedente del límite inferior
A20: $ | B20: $ | C20: $ | D20: % | F20: $ | G20: $ | H20: $ | I20: %
A21: 0.01 | B21: 2238.12 | C21: 0 | D21: 0.0192 | F21: 0.01 | G21: 2984.16 | H21: 0 | I21: 0.0192
A22: 2238.13 | B22: 18996.15 | C22: 42.96 | D22: 0.064 | F22: 2984.17 | G22: 25328.2 | H22: 57.28 | I22: 0.064
A23: 18996.16 | B23: 33384.03 | C23: 1115.49 | D23: 0.1088 | F23: 25328.21 | G23: 44512.04 | H23: 1487.32 | I23: 0.1088
A24: 33384.04 | B24: 38807.46 | C24: 2680.89 | D24: 0.16 | F24: 44512.05 | G24: 51743.28 | H24: 3574.52 | I24: 0.16
A25: 38807.47 | B25: 46463.13 | C25: 3548.64 | D25: 0.1792 | F25: 51743.29 | G25: 61950.84 | H25: 4731.52 | I25: 0.1792
A26: 46463.14 | B26: 93709.47 | C26: 4920.54 | D26: 0.2136 | F26: 61950.85 | G26: 124945.96 | H26: 6560.72 | I26: 0.2136
A27: 93709.48 | B27: 147699 | C27: 15012.36 | D27: 0.2352 | F27: 124945.97 | G27: 196932 | H27: 20016.48 | I27: 0.2352
A28: 147699.01 | B28: 281981.7 | C28: 27710.67 | D28: 0.3 | F28: 196932.01 | G28: 375975.6 | H28: 36947.56 | I28: 0.3
A29: 281981.71 | B29: 375975.6 | C29: 67995.51 | D29: 0.32 | F29: 375975.61 | G29: 501300.8 | H29: 90660.68 | I29: 0.32
A30: 375975.61 | B30: 1127926.8 | C30: 98073.54 | D30: 0.34 | F30: 501300.81 | G30: 1503902.4 | H30: 130764.72 | I30: 0.34
A31: 1127926.8 | B31: En adelante | C31: 353736.96 | D31: 0.35 | F31: 1503902.4 | G31: En adelante | H31: 471649.28 | I31: 0.35
A33: MAYO | F33: JUNIO
A34: Límite inferior | B34: Límite superior | C34: Cuota fija | D34: Por ciento para aplicarse sobre | F34: Límite inferior | G34: Límite superior | H34: Cuota fija | I34: Por ciento para aplicarse sobre
D35: el excedente del límite inferior | I35: el excedente del límite inferior
A36: $ | B36: $ | C36: $ | D36: % | F36: $ | G36: $ | H36: $ | I36: %
A37: 0.01 | B37: 3730.2 | C37: 0 | D37: 0.0192 | F37: 0.01 | G37: 4476.24 | H37: 0 | I37: 0.0192
A38: 3730.21 | B38: 31660.25 | C38: 71.6 | D38: 0.064 | F38: 4476.25 | G38: 37992.3 | H38: 85.92 | I38: 0.064
A39: 31660.26 | B39: 55640.05 | C39: 1859.15 | D39: 0.1088 | F39: 37992.31 | G39: 66768.06 | H39: 2230.98 | I39: 0.1088
A40: 55640.06 | B40: 64679.1 | C40: 4468.15 | D40: 0.16 | F40: 66768.07 | G40: 77614.92 | H40: 5361.78 | I40: 0.16
A41: 64679.11 | B41: 77438.55 | C41: 5914.4 | D41: 0.1792 | F41: 77614.93 | G41: 92926.26 | H41: 7097.28 | I41: 0.1792
A42: 77438.56 | B42: 156182.45 | C42: 8200.9 | D42: 0.2136 | F42: 92926.27 | G42: 187418.94 | H42: 9841.08 | I42: 0.2136
A43: 156182.46 | B43: 246165 | C43: 25020.6 | D43: 0.2352 | F43: 187418.95 | G43: 295398 | H43: 30024.72 | I43: 0.2352
A44: 246165.01 | B44: 469969.5 | C44: 46184.45 | D44: 0.3 | F44: 295398.01 | G44: 563963.4 | H44: 55421.34 | I44: 0.3
A45: 469969.51 | B45: 626626 | C45: 113325.85 | D45: 0.32 | F45: 563963.41 | G45: 751951.2 | H45: 135991.02 | I45: 0.32
A46: 626626.01 | B46: 1879878.1 | C46: 163455.9 | D46: 0.34 | F46: 751951.21 | G46: 2255853.7 | H46: 196147.08 | I46: 0.34
A47: 1879878.1 | B47: En adelante | C47: 589561.6 | D47: 0.35 | F47: 2255853.7 | G47: En adelante | H47: 707473.92 | I47: 0.35
A49: JULIO | F49: AGOSTO
A50: Límite inferior | B50: Límite superior | C50: Cuota fija | D50: Por ciento para aplicarse sobre | F50: Límite inferior | G50: Límite superior | H50: Cuota fija | I50: Por ciento para aplicarse sobre
D51: el excedente del límite inferior | I51: el excedente del límite inferior
A52: $ | B52: $ | C52: $ | D52: % | F52: $ | G52: $ | H52: $ | I52: %
A53: 0.01 | B53: 5222.28 | C53: 0 | D53: 0.0192 | F53: 0.01 | G53: 5968.32 | H53: 0 | I53: 0.0192
A54: 5222.29 | B54: 44324.35 | C54: 100.24 | D54: 0.064 | F54: 5968.33 | G54: 50656.4 | H54: 114.56 | I54: 0.064
A55: 44324.36 | B55: 77896.07 | C55: 2602.81 | D55: 0.1088 | F55: 50656.41 | G55: 89024.08 | H55: 2974.64 | I55: 0.1088
A56: 77896.08 | B56: 90550.74 | C56: 6255.41 | D56: 0.16 | F56: 89024.09 | G56: 103486.56 | H56: 7149.04 | I56: 0.16
A57: 90550.75 | B57: 108413.97 | C57: 8280.16 | D57: 0.1792 | F57: 103486.57 | G57: 123901.68 | H57: 9463.04 | I57: 0.1792
A58: 108413.98 | B58: 218655.43 | C58: 11481.26 | D58: 0.2136 | F58: 123901.69 | G58: 249891.92 | H58: 13121.44 | I58: 0.2136
A59: 218655.44 | B59: 344631 | C59: 35028.84 | D59: 0.2352 | F59: 249891.93 | G59: 393864 | H59: 40032.96 | I59: 0.2352
A60: 344631.01 | B60: 657957.3 | C60: 64658.23 | D60: 0.3 | F60: 393864.01 | G60: 751951.2 | H60: 73895.12 | I60: 0.3
A61: 657957.31 | B61: 877276.4 | C61: 158656.19 | D61: 0.32 | F61: 751951.21 | G61: 1002601.6 | H61: 181321.36 | I61: 0.32
A62: 877276.41 | B62: 2631829.3 | C62: 228838.26 | D62: 0.34 | F62: 1002601.6 | G62: 3007804.9 | H62: 261529.44 | I62: 0.34
A63: 2631829.3 | B63: En adelante | C63: 825386.24 | D63: 0.35 | F63: 3007804.9 | G63: En adelante | H63: 943298.56 | I63: 0.35
A65: Tarifa para el pago provisional del mes de septiembre de 2023, aplicable a los ingresos que perciban los contribuyentes a que se refiere el Capítulo II, Sección I, del Título IV de la Ley del Impuesto sobre la Renta. | F65: Tarifa para el pago provisional del mes de octubre de 2023, aplicable a los ingresos que perciban los contribuyentes a que se refiere el Capítulo II, Sección I, del Título IV de la Ley del Impuesto sobre la Renta.
A66: Límite inferior | B66: Límite superior | C66: Cuota fija | D66: Por ciento para aplicarse sobre | F66: Límite inferior | G66: Límite superior | H66: Cuota fija | I66: Por ciento para aplicarse sobre
D67: el excedente del límite inferior | I67: el excedente del límite inferior
A68: $ | B68: $ | C68: $ | D68: % | F68: $ | G68: $ | H68: $ | I68: %
A69: 0.01 | B69: 6714.36 | C69: 0 | D69: 0.0192 | F69: 0.01 | G69: 7460.4 | H69: 0 | I69: 0.0192
A70: 6714.37 | B70: 56988.45 | C70: 128.88 | D70: 0.064 | F70: 7460.41 | G70: 63320.5 | H70: 143.2 | I70: 0.064
A71: 56988.46 | B71: 100152.09 | C71: 3346.47 | D71: 0.1088 | F71: 63320.51 | G71: 111280.1 | H71: 3718.3 | I71: 0.1088
A72: 100152.1 | B72: 116422.38 | C72: 8042.67 | D72: 0.16 | F72: 111280.11 | G72: 129358.2 | H72: 8936.3 | I72: 0.16
A73: 116422.39 | B73: 139389.39 | C73: 10645.92 | D73: 0.1792 | F73: 129358.21 | G73: 154877.1 | H73: 11828.8 | I73: 0.1792
A74: 139389.4 | B74: 281128.41 | C74: 14761.62 | D74: 0.2136 | F74: 154877.11 | G74: 312364.9 | H74: 16401.8 | I74: 0.2136
A75: 281128.42 | B75: 443097 | C75: 45037.08 | D75: 0.2352 | F75: 312364.91 | G75: 492330 | H75: 50041.2 | I75: 0.2352
A76: 443097.01 | B76: 845945.1 | C76: 83132.01 | D76: 0.3 | F76: 492330.01 | G76: 939939 | H76: 92368.9 | I76: 0.3
A77: 845945.11 | B77: 1127926.8 | C77: 203986.53 | D77: 0.32 | F77: 939939.01 | G77: 1253252 | H77: 226651.7 | I77: 0.32
A78: 1127926.8 | B78: 3383780.5 | C78: 294220.62 | D78: 0.34 | F78: 1253252 | G78: 3759756.1 | H78: 326911.8 | I78: 0.34
A79: 3383780.5 | B79: En adelante | C79: 1061210.9 | D79: 0.35 | F79: 3759756.1 | G79: En adelante | H79: 1179123.2 | I79: 0.35
A81: Tarifa para el pago provisional del mes de noviembre de 2023, aplicable a los ingresos que perciban los contribuyentes a que se refiere el Capítulo II, Sección I, del Título IV de la Ley del Impuesto sobre la Renta. | F81: Tarifa para el pago provisional del mes de diciembre de 2023, aplicable a los ingresos que perciban los contribuyentes a que se refiere el Capítulo II, Sección I, del Título IV de la Ley del Impuesto sobre la Renta.
A82: Límite inferior | B82: Límite superior | C82: Cuota fija | D82: Por ciento para aplicarse sobre | F82: Límite inferior | G82: Límite superior | H82: Cuota fija | I82: Por ciento para aplicarse sobre
D83: el excedente del límite inferior | I83: el excedente del límite inferior
A84: $ | B84: $ | C84: $ | D84: % | F84: $ | G84: $ | H84: $ | I84: %
A85: 0.01 | B85: 8206.44 | C85: 0 | D85: 0.0192 | F85: 0.01 | G85: 8952.49 | H85: 0 | I85: 0.0192
A86: 8206.45 | B86: 69652.55 | C86: 157.52 | D86: 0.064 | F86: 8952.5 | G86: 75984.55 | H86: 171.88 | I86: 0.064
A87: 69652.56 | B87: 122408.11 | C87: 4090.13 | D87: 0.1088 | F87: 75984.56 | G87: 133536.07 | H87: 4461.94 | I87: 0.1088
A88: 122408.12 | B88: 142294.02 | C88: 9829.93 | D88: 0.16 | F88: 133536.08 | G88: 155229.8 | H88: 10723.55 | I88: 0.16
A89: 142294.03 | B89: 170364.81 | C89: 13011.68 | D89: 0.1792 | F89: 155229.81 | G89: 185852.57 | H89: 14194.54 | I89: 0.1792
A90: 170364.82 | B90: 343601.39 | C90: 18041.98 | D90: 0.2136 | F90: 185852.58 | G90: 374837.88 | H90: 19682.13 | I90: 0.2136
A91: 343601.4 | B91: 541563 | C91: 55045.32 | D91: 0.2352 | F91: 374837.89 | G91: 590795.99 | H91: 60049.4 | I91: 0.2352
A92: 541563.01 | B92: 1033932.9 | C92: 101605.79 | D92: 0.3 | F92: 590796 | G92: 1127926.8 | H92: 110842.74 | I92: 0.3
A93: 1033932.9 | B93: 1378577.2 | C93: 249316.87 | D93: 0.32 | F93: 1127926.9 | G93: 1503902.5 | H93: 271981.99 | I93: 0.32
A94: 1378577.2 | B94: 4135731.7 | C94: 359602.98 | D94: 0.34 | F94: 1503902.5 | G94: 4511707.4 | H94: 392294.17 | I94: 0.34
A95: 4135731.7 | B95: En adelante | C95: 1297035.5 | D95: 0.35 | F95: 4511707.4 | G95: En adelante | H95: 1414947.9 | I95: 0.35
A97: Tarifa para el pago provisional del mes de diciembre de 2020, aplicable a los ingresos que perciban los contribuyentes a que se refiere el Capítulo II, Sección I, del Título IV de la Ley del Impuesto sobre la Renta.
A98: Límite inferior | B98: Límite superior | C98: Cuota fija | D98: Por ciento para aplicarse sobre
D99: el excedente del límite inferior
A100: $ | B100: $ | C100: $ | D100: %
A101: 0.01 | B101: 7735 | C101: 0 | D101: 0.0192
A102: 7735.01 | B102: 65651.07 | C102: 148.51 | D102: 0.064
A103: 65651.08 | B103: 115375.9 | C103: 3855.14 | D103: 0.1088
A104: 115375.91 | B104: 134119.41 | C104: 9265.2 | D104: 0.16
A105: 134119.42 | B105: 160577.65 | C105: 12264.16 | D105: 0.1792
A106: 160577.66 | B106: 323862 | C106: 17005.47 | D106: 0.2136
...

Sheet ING
A1: MES | C1: FECHA DE EMISION | D1: FECHA COBRO | E1: Tipo Ingreso (tasa de iva) | F1: FOLIO | G1: CLIENTE | H1: RFC | J1: IMPORTE | K1: IVA | L1: IVA RETENIDO | M1: ISR RETENIDO | N1: TOTAL | O1: codigo postal | P1: REGIMEN
A2: =IF(D2>0,MONTH(D2),0) -> 1 | B2: =VLOOKUP(A2,[1]Hoja3!$C$3:$D$14,2,FALSE) -> ENERO | C2: 45302 | D2: 45302 | E2: PG | G2: MARIELA OLMOS GAONA | H2: =IF(G2="EFREN ABUNDEZ REYNA","AURE7306187IA",IF(G2="LUIS ALEJANDRO HERNANDEZ REYNA","HERL850705AL2",IF(G2="ANA BEATRIZ ESTRADA ARGOTE","EAAA860701UP2",IF(G2="SERGIO ROMERO DURAN","RODS620908QAA",IF(G2="MARIELA OLMOS GAONA","OOGM010703NX1",IF(G2="LUCIANO MIJAIL ORTEGA MUÑOZ","OEML881105IK2",IF(G2="GUSTAVO HUMBERTO VELAZCO GALVAN","VEGG9211019T1",IF(G2="JESUS AGUSTIN VELAZQUEZ FLORES","VEFJ900303M65",IF(G2="KARLA ESTEFANIA SALAZAR FLORES","SAFK9807277N1",IF(G2="ANGEL TERRAZAS MONROY","TEMA7105035N4")))))))))) -> OOGM010703NX1 | I2: =+B2 -> ENERO | J2: 13500 | K2: 0 | N2: =+J2+K2-L2-M2 -> 13500 | O2: =IF(G2="EFREN ABUNDEZ REYNA","37295",IF(G2="LUIS ALEJANDRO HERNANDEZ REYNA","HERL850705AL2",IF(G2="ANA BEATRIZ ESTRADA ARGOTE","EAAA860701UP2",IF(G2="SERGIO ROMERO DURAN","RODS620908QAA",IF(G2="MARIELA OLMOS GAONA","37675",IF(G2="LUCIANO MIJAIL ORTEGA MUÑOZ","37297",IF(G2="GUSTAVO HUMBERTO VELAZCO GALVAN","VEGG9211019T1",IF(G2="JESUS AGUSTIN VELAZQUEZ FLORES","VEFJ900303M65",IF(G2="KARLA ESTEFANIA SALAZAR FLORES","SAFK9807277N1",IF(G2="ANGEL TERRAZAS MONROY","TEMA7105035N4")))))))))) -> 37675 | P2: =IF(G2="EFREN ABUNDEZ REYNA","PFAEP",IF(G2="LUIS ALEJANDRO HERNANDEZ REYNA","HERL850705AL2",IF(G2="ANA BEATRIZ ESTRADA ARGOTE","EAAA860701UP2",IF(G2="SERGIO ROMERO DURAN","RODS620908QAA",IF(G2="MARIELA OLMOS GAONA","RESICO",IF(G2="LUCIANO MIJAIL ORTEGA MUÑOZ","RIF",IF(G2="GUSTAVO HUMBERTO VELAZCO GALVAN","VEGG9211019T1",IF(G2="JESUS AGUSTIN VELAZQUEZ FLORES","VEFJ900303M65",IF(G2="KARLA ESTEFANIA SALAZAR FLORES","SAFK9807277N1",IF(G2="ANGEL TERRAZAS MONROY","TEMA7105035N4")))))))))) -> RESICO
A3: =IF(D3>0,MONTH(D3),0) -> 1 | B3: =VLOOKUP(A3,[1]Hoja3!$C$3:$D$14,2,FALSE) -> ENERO | C3: 45302 | D3: 45302 | E3: 16 | G3: MARIELA OLMOS GAONA | H3: =IF(G3="EFREN ABUNDEZ REYNA","AURE7306187IA",IF(G3="LUIS ALEJANDRO HERNANDEZ REYNA","HERL850705AL2",IF(G3="ANA BEATRIZ ESTRADA ARGOTE","EAAA860701UP2",IF(G3="SERGIO ROMERO DURAN","RODS620908QAA",IF(G3="MARIELA OLMOS GAONA","OOGM010703NX1",IF(G3="LUCIANO MIJAIL ORTEGA MUÑOZ","OEML881105IK2",IF(G3="GUSTAVO HUMBERTO VELAZCO GALVAN","VEGG9211019T1",IF(G3="JESUS AGUSTIN VELAZQUEZ FLORES","VEFJ900303M65",IF(G3="KARLA ESTEFANIA SALAZAR FLORES","SAFK9807277N1",IF(G3="ANGEL TERRAZAS MONROY","TEMA7105035N4")))))))))) -> OOGM010703NX1 | I3: =+B3 -> ENERO | J3: 5850 | K3: 0 | N3: =+J3+K3-L3-M3 -> 5850 | O3: =IF(G3="EFREN ABUNDEZ REYNA","37295",IF(G3="LUIS ALEJANDRO HERNANDEZ REYNA","HERL850705AL2",IF(G3="ANA BEATRIZ ESTRADA ARGOTE","EAAA860701UP2",IF(G3="SERGIO ROMERO DURAN","RODS620908QAA",IF(G3="MARIELA OLMOS GAONA","37675",IF(G3="LUCIANO MIJAIL ORTEGA MUÑOZ","37297",IF(G3="GUSTAVO HUMBERTO VELAZCO GALVAN","VEGG9211019T1",IF(G3="JESUS AGUSTIN VELAZQUEZ FLORES","VEFJ900303M65",IF(G3="KARLA ESTEFANIA SALAZAR FLORES","SAFK9807277N1",IF(G3="ANGEL TERRAZAS MONROY","TEMA7105035N4")))))))))) -> 37675 | P3: =IF(G3="EFREN ABUNDEZ REYNA","PFAEP",IF(G3="LUIS ALEJANDRO HERNANDEZ REYNA","HERL850705AL2",IF(G3="ANA BEATRIZ ESTRADA ARGOTE","EAAA860701UP2",IF(G3="SERGIO ROMERO DURAN","RODS620908QAA",IF(G3="MARIELA OLMOS GAONA","RESICO",IF(G3="LUCIANO MIJAIL ORTEGA MUÑOZ","RIF",IF(G3="GUSTAVO HUMBERTO VELAZCO GALVAN","VEGG9211019T1",IF(G3="JESUS AGUSTIN VELAZQUEZ FLORES","VEFJ900303M65",IF(G3="KARLA ESTEFANIA SALAZAR FLORES","SAFK9807277N1",IF(G3="ANGEL TERRAZAS MONROY","TEMA7105035N4")))))))))) -> RESICO
A4: =IF(D4>0,MONTH(D4),0) -> 1 | B4: =VLOOKUP(A4,[1]Hoja3!$C$3:$D$14,2,FALSE) -> ENERO | C4: 45302 | D4: 45302 | G4: EFREN ABUNDEZ REYNA | H4: =IF(G4="EFREN ABUNDEZ REYNA","AURE7306187IA",IF(G4="LUIS ALEJANDRO HERNANDEZ REYNA","HERL850705AL2",IF(G4="ANA BEATRIZ ESTRADA ARGOTE","EAAA860701UP2",IF(G4="SERGIO ROMERO DURAN","RODS620908QAA",IF(G4="MARIELA OLMOS GAONA","OOGM010703NX1",IF(G4="LUCIANO MIJAIL ORTEGA MUÑOZ","OEML881105IK2",IF(G4="GUSTAVO HUMBERTO VELAZCO GALVAN","VEGG9211019T1",IF(G4="JESUS AGUSTIN VELAZQUEZ FLORES","VEFJ900303M65",IF(G4="KARLA ESTEFANIA SALAZAR FLORES","SAFK9807277N1",IF(G4="ANGEL TERRAZAS MONROY","TEMA7105035N4")))))))))) -> AURE7306187IA | I4: =+B4 -> ENERO | J4: 1090 | K4: 0 | N4: =+J4+K4-L4-M4 -> 1090 | O4: =IF(G4="EFREN ABUNDEZ REYNA","37295",IF(G4="LUIS ALEJANDRO HERNANDEZ REYNA","HERL850705AL2",IF(G4="ANA BEATRIZ ESTRADA ARGOTE","EAAA860701UP2",IF(G4="SERGIO ROMERO DURAN","RODS620908QAA",IF(G4="MARIELA OLMOS GAONA","37675",IF(G4="LUCIANO MIJAIL ORTEGA MUÑOZ","37297",IF(G4="GUSTAVO HUMBERTO VELAZCO GALVAN","VEGG9211019T1",IF(G4="JESUS AGUSTIN VELAZQUEZ FLORES","VEFJ900303M65",IF(G4="KARLA ESTEFANIA SALAZAR FLORES","SAFK9807277N1",IF(G4="ANGEL TERRAZAS MONROY","TEMA7105035N4")))))))))) -> 37295 | P4: =IF(G4="EFREN ABUNDEZ REYNA","PFAEP",IF(G4="LUIS ALEJANDRO HERNANDEZ REYNA","HERL850705AL2",IF(G4="ANA BEATRIZ ESTRADA ARGOTE","EAAA860701UP2",IF(G4="SERGIO ROMERO DURAN","RODS620908QAA",IF(G4="MARIELA OLMOS GAONA","RESICO",IF(G4="LUCIANO MIJAIL ORTEGA MUÑOZ","RIF",IF(G4="GUSTAVO HUMBERTO VELAZCO GALVAN","VEGG9211019T1",IF(G4="JESUS AGUSTIN VELAZQUEZ FLORES","VEFJ900303M65",IF(G4="KARLA ESTEFANIA SALAZAR FLORES","SAFK9807277N1",IF(G4="ANGEL TERRAZAS MONROY","TEMA7105035N4")))))))))) -> PFAEP
A5: =IF(D5>0,MONTH(D5),0) -> 1 | B5: =VLOOKUP(A5,[1]Hoja3!$C$3:$D$14,2,FALSE) -> ENERO | C5: 45302 | D5: 45302 | G5: EFREN ABUNDEZ REYNA | H5: =IF(G5="EFREN ABUNDEZ REYNA","AURE7306187IA",IF(G5="LUIS ALEJANDRO HERNANDEZ REYNA","HERL850705AL2",IF(G5="ANA BEATRIZ ESTRADA ARGOTE","EAAA860701UP2",IF(G5="SERGIO ROMERO DURAN","RODS620908QAA",IF(G5="MARIELA OLMOS GAONA","OOGM010703NX1",IF(G5="LUCIANO MIJAIL ORTEGA MUÑOZ","OEML881105IK2",IF(G5="GUSTAVO HUMBERTO VELAZCO GALVAN","VEGG9211019T1",IF(G5="JESUS AGUSTIN VELAZQUEZ FLORES","VEFJ900303M65",IF(G5="KARLA ESTEFANIA SALAZAR FLORES","SAFK9807277N1",IF(G5="ANGEL TERRAZAS MONROY","TEMA7105035N4")))))))))) -> AURE7306187IA | I5: =+B5 -> ENERO | J5: 1090 | K5: 0 | N5: =+J5+K5-L5-M5 -> 1090 | O5: =IF(G5="EFREN ABUNDEZ REYNA","37295",IF(G5="LUIS ALEJANDRO HERNANDEZ REYNA","HERL850705AL2",IF(G5="ANA BEATRIZ ESTRADA ARGOTE","EAAA860701UP2",IF(G5="SERGIO ROMERO DURAN","RODS620908QAA",IF(G5="MARIELA OLMOS GAONA","37675",IF(G5="LUCIANO MIJAIL ORTEGA MUÑOZ","37297",IF(G5="GUSTAVO HUMBERTO VELAZCO GALVAN","VEGG9211019T1",IF(G5="JESUS AGUSTIN VELAZQUEZ FLORES","VEFJ900303M65",IF(G5="KARLA ESTEFANIA SALAZAR FLORES","SAFK9807277N1",IF(G5="ANGEL TERRAZAS MONROY","TEMA7105035N4")))))))))) -> 37295 | P5: =IF(G5="EFREN ABUNDEZ REYNA","PFAEP",IF(G5="LUIS ALEJANDRO HERNANDEZ REYNA","HERL850705AL2",IF(G5="ANA BEATRIZ ESTRADA ARGOTE","EAAA860701UP2",IF(G5="SERGIO ROMERO DURAN","RODS620908QAA",IF(G5="MARIELA OLMOS GAONA","RESICO",IF(G5="LUCIANO MIJAIL ORTEGA MUÑOZ","RIF",IF(G5="GUSTAVO HUMBERTO VELAZCO GALVAN","VEGG9211019T1",IF(G5="JESUS AGUSTIN VELAZQUEZ FLORES","VEFJ900303M65",IF(G5="KARLA ESTEFANIA SALAZAR FLORES","SAFK9807277N1",IF(G5="ANGEL TERRAZAS MONROY","TEMA7105035N4")))))))))) -> PFAEP
A6: =IF(D6>0,MONTH(D6),0) -> 1 | B6: =VLOOKUP(A6,[1]Hoja3!$C$3:$D$14,2,FALSE) -> ENERO | C6: 45309 | D6: 45309 | G6: CAJA POPULAR MEXICANA | H6: CPM960127M3A | I6: =+B6 -> ENERO | J6: 510 | K6: =+J6*0.16 -> 81.6 | N6: =+J6+K6-L6-M6 -> 591.6 | O6: 37004 | P6: moral no lucrativa | Q6: hedj124791234@gmail.com
A7: =IF(D7>0,MONTH(D7),0) -> 1 | B7: =VLOOKUP(A7,[1]Hoja3!$C$3:$D$14,2,FALSE) -> ENERO | C7: 45309 | D7: 45309 | G7: MARIELA OLMOS GAONA | H7: =IF(G7="EFREN ABUNDEZ REYNA","AURE7306187IA",IF(G7="LUIS ALEJANDRO HERNANDEZ REYNA","HERL850705AL2",IF(G7="ANA BEATRIZ ESTRADA ARGOTE","EAAA860701UP2",IF(G7="SERGIO ROMERO DURAN","RODS620908QAA",IF(G7="MARIELA OLMOS GAONA","OOGM010703NX1",IF(G7="LUCIANO MIJAIL ORTEGA MUÑOZ","OEML881105IK2",IF(G7="GUSTAVO HUMBERTO VELAZCO GALVAN","VEGG9211019T1",IF(G7="JESUS AGUSTIN VELAZQUEZ FLORES","VEFJ900303M65",IF(G7="KARLA ESTEFANIA SALAZAR FLORES","SAFK9807277N1",IF(G7="ANGEL TERRAZAS MONROY","TEMA7105035N4")))))))))) -> OOGM010703NX1 | I7: =+B7 -> ENERO | J7: 7025 | K7: 0 | N7: =+J7+K7-L7-M7 -> 7025 | O7: =IF(G7="EFREN ABUNDEZ REYNA","37295",IF(G7="LUIS ALEJANDRO HERNANDEZ REYNA","HERL850705AL2",IF(G7="ANA BEATRIZ ESTRADA ARGOTE","EAAA860701UP2",IF(G7="SERGIO ROMERO DURAN","RODS620908QAA",IF(G7="MARIELA OLMOS GAONA","37675",IF(G7="LUCIANO MIJAIL ORTEGA MUÑOZ","37297",IF(G7="GUSTAVO HUMBERTO VELAZCO GALVAN","VEGG9211019T1",IF(G7="JESUS AGUSTIN VELAZQUEZ FLORES","VEFJ900303M65",IF(G7="KARLA ESTEFANIA SALAZAR FLORES","SAFK9807277N1",IF(G7="ANGEL TERRAZAS MONROY","TEMA7105035N4")))))))))) -> 37675 | P7: =IF(G7="EFREN ABUNDEZ REYNA","PFAEP",IF(G7="LUIS ALEJANDRO HERNANDEZ REYNA","HERL850705AL2",IF(G7="ANA BEATRIZ ESTRADA ARGOTE","EAAA860701UP2",IF(G7="SERGIO ROMERO DURAN","RODS620908QAA",IF(G7="MARIELA OLMOS GAONA","RESICO",IF(G7="LUCIANO MIJAIL ORTEGA MUÑOZ","RIF",IF(G7="GUSTAVO HUMBERTO VELAZCO GALVAN","VEGG9211019T1",IF(G7="JESUS AGUSTIN VELAZQUEZ FLORES","VEFJ900303M65",IF(G7="KARLA ESTEFANIA SALAZAR FLORES","SAFK9807277N1",IF(G7="ANGEL TERRAZAS MONROY","TEMA7105035N4")))))))))) -> RESICO
A8: =IF(D8>0,MONTH(D8),0) -> 1 | B8: =VLOOKUP(A8,[1]Hoja3!$C$3:$D$14,2,FALSE) -> ENERO | C8: 45309 | D8: 45309 | G8: EFREN ABUNDEZ REYNA | H8: =IF(G8="EFREN ABUNDEZ REYNA","AURE7306187IA",IF(G8="LUIS ALEJANDRO HERNANDEZ REYNA","HERL850705AL2",IF(G8="ANA BEATRIZ ESTRADA ARGOTE","EAAA860701UP2",IF(G8="SERGIO ROMERO DURAN","RODS620908QAA",IF(G8="MARIELA OLMOS GAONA","OOGM010703NX1",IF(G8="LUCIANO MIJAIL ORTEGA MUÑOZ","OEML881105IK2",IF(G8="GUSTAVO HUMBERTO VELAZCO GALVAN","VEGG9211019T1",IF(G8="JESUS AGUSTIN VELAZQUEZ FLORES","VEFJ900303M65",IF(G8="KARLA ESTEFANIA SALAZAR FLORES","SAFK9807277N1",IF(G8="ANGEL TERRAZAS MONROY","TEMA7105035N4")))))))))) -> AURE7306187IA | I8: =+B8 -> ENERO | J8: 1977 | K8: 0 | N8: =+J8+K8-L8-M8 -> 1977 | O8: =IF(G8="EFREN ABUNDEZ REYNA","37295",IF(G8="LUIS ALEJANDRO HERNANDEZ REYNA","HERL850705AL2",IF(G8="ANA BEATRIZ ESTRADA ARGOTE","EAAA860701UP2",IF(G8="SERGIO ROMERO DURAN","RODS620908QAA",IF(G8="MARIELA OLMOS GAONA","37675",IF(G8="LUCIANO MIJAIL ORTEGA MUÑOZ","37297",IF(G8="GUSTAVO HUMBERTO VELAZCO GALVAN","VEGG9211019T1",IF(G8="JESUS AGUSTIN VELAZQUEZ FLORES","VEFJ900303M65",IF(G8="KARLA ESTEFANIA SALAZAR FLORES","SAFK9807277N1",IF(G8="ANGEL TERRAZAS MONROY","TEMA7105035N4")))))))))) -> 37295 | P8: =IF(G8="EFREN ABUNDEZ REYNA","PFAEP",IF(G8="LUIS ALEJANDRO HERNANDEZ REYNA","HERL850705AL2",IF(G8="ANA BEATRIZ ESTRADA ARGOTE","EAAA860701UP2",IF(G8="SERGIO ROMERO DURAN","RODS620908QAA",IF(G8="MARIELA OLMOS GAONA","RESICO",IF(G8="LUCIANO MIJAIL ORTEGA MUÑOZ","RIF",IF(G8="GUSTAVO HUMBERTO VELAZCO GALVAN","VEGG9211019T1",IF(G8="JESUS AGUSTIN VELAZQUEZ FLORES","VEFJ900303M65",IF(G8="KARLA ESTEFANIA SALAZAR FLORES","SAFK9807277N1",IF(G8="ANGEL TERRAZAS MONROY","TEMA7105035N4")))))))))) -> PFAEP
A9: =IF(D9>0,MONTH(D9),0) -> 1 | B9: =VLOOKUP(A9,[1]Hoja3!$C$3:$D$14,2,FALSE) -> ENERO | C9: 45309 | D9: 45309 | G9: EFREN ABUNDEZ REYNA | H9: =IF(G9="EFREN ABUNDEZ REYNA","AURE7306187IA",IF(G9="LUIS ALEJANDRO HERNANDEZ REYNA","HERL850705AL2",IF(G9="ANA BEATRIZ ESTRADA ARGOTE","EAAA860701UP2",IF(G9="SERGIO ROMERO DURAN","RODS620908QAA",IF(G9="MARIELA OLMOS GAONA","OOGM010703NX1",IF(G9="LUCIANO MIJAIL ORTEGA MUÑOZ","OEML881105IK2",IF(G9="GUSTAVO HUMBERTO VELAZCO GALVAN","VEGG9211019T1",IF(G9="JESUS AGUSTIN VELAZQUEZ FLORES","VEFJ900303M65",IF(G9="KARLA ESTEFANIA SALAZAR FLORES","SAFK9807277N1",IF(G9="ANGEL TERRAZAS MONROY","TEMA7105035N4")))))))))) -> AURE7306187IA | I9: =+B9 -> ENERO | J9: 1977 | K9: 0 | N9: =+J9+K9-L9-M9 -> 1977 | O9: =IF(G9="EFREN ABUNDEZ REYNA","37295",IF(G9="LUIS ALEJANDRO HERNANDEZ REYNA","HERL850705AL2",IF(G9="ANA BEATRIZ ESTRADA ARGOTE","EAAA860701UP2",IF(G9="SERGIO ROMERO DURAN","RODS620908QAA",IF(G9="MARIELA OLMOS GAONA","37675",IF(G9="LUCIANO MIJAIL ORTEGA MUÑOZ","37297",IF(G9="GUSTAVO HUMBERTO VELAZCO GALVAN","VEGG9211019T1",IF(G9="JESUS AGUSTIN VELAZQUEZ FLORES","VEFJ900303M65",IF(G9="KARLA ESTEFANIA SALAZAR FLORES","SAFK9807277N1",IF(G9="ANGEL TERRAZAS MONROY","TEMA7105035N4")))))))))) -> 37295 | P9: =IF(G9="EFREN ABUNDEZ REYNA","PFAEP",IF(G9="LUIS ALEJANDRO HERNANDEZ REYNA","HERL850705AL2",IF(G9="ANA BEATRIZ ESTRADA ARGOTE","EAAA860701UP2",IF(G9="SERGIO ROMERO DURAN","RODS620908QAA",IF(G9="MARIELA OLMOS GAONA","RESICO",IF(G9="LUCIANO MIJAIL ORTEGA MUÑOZ","RIF",IF(G9="GUSTAVO HUMBERTO VELAZCO GALVAN","VEGG9211019T1",IF(G9="JESUS AGUSTIN VELAZQUEZ FLORES","VEFJ900303M65",IF(G9="KARLA ESTEFANIA SALAZAR FLORES","SAFK9807277N1",IF(G9="ANGEL TERRAZAS MONROY","TEMA7105035N4")))))))))) -> PFAEP
A10: =IF(D10>0,MONTH(D10),0) -> 1 | B10: =VLOOKUP(A10,[1]Hoja3!$C$3:$D$14,2,FALSE) -> ENERO | C10: 45316 | D10: 45316 | G10: MARIELA OLMOS GAONA | H10: =IF(G10="EFREN ABUNDEZ REYNA","AURE7306187IA",IF(G10="LUIS ALEJANDRO HERNANDEZ REYNA","HERL850705AL2",IF(G10="ANA BEATRIZ ESTRADA ARGOTE","EAAA860701UP2",IF(G10="SERGIO ROMERO DURAN","RODS620908QAA",IF(G10="MARIELA OLMOS GAONA","OOGM010703NX1",IF(G10="LUCIANO MIJAIL ORTEGA MUÑOZ","OEML881105IK2",IF(G10="GUSTAVO HUMBERTO VELAZCO GALVAN","VEGG9211019T1",IF(G10="JESUS AGUSTIN VELAZQUEZ FLORES","VEFJ900303M65",IF(G10="KARLA ESTEFANIA SALAZAR FLORES","SAFK9807277N1",IF(G10="ANGEL TERRAZAS MONROY","TEMA7105035N4")))))))))) -> OOGM010703NX1 | I10: =+B10 -> ENERO | J10: 6990 | K10: 0 | N10: =+J10+K10-L10-M10 -> 6990 | O10: =IF(G10="EFREN ABUNDEZ REYNA","37295",IF(G10="LUIS ALEJANDRO HERNANDEZ REYNA","HERL850705AL2",IF(G10="ANA BEATRIZ ESTRADA ARGOTE","EAAA860701UP2",IF(G10="SERGIO ROMERO DURAN","RODS620908QAA",IF(G10="MARIELA OLMOS GAONA","37675",IF(G10="LUCIANO MIJAIL ORTEGA MUÑOZ","37297",IF(G10="GUSTAVO HUMBERTO VELAZCO GALVAN","VEGG9211019T1",IF(G10="JESUS AGUSTIN VELAZQUEZ FLORES","VEFJ900303M65",IF(G10="KARLA ESTEFANIA SALAZAR FLORES","SAFK9807277N1",IF(G10="ANGEL TERRAZAS MONROY","TEMA7105035N4")))))))))) -> 37675 | P10: =IF(G10="EFREN ABUNDEZ REYNA","PFAEP",IF(G10="LUIS ALEJANDRO HERNANDEZ REYNA","HERL850705AL2",IF(G10="ANA BEATRIZ ESTRADA ARGOTE","EAAA860701UP2",IF(G10="SERGIO ROMERO DURAN","RODS620908QAA",IF(G10="MARIELA OLMOS GAONA","RESICO",IF(G10="LUCIANO MIJAIL ORTEGA MUÑOZ","RIF",IF(G10="GUSTAVO HUMBERTO VELAZCO GALVAN","VEGG9211019T1",IF(G10="JESUS AGUSTIN VELAZQUEZ FLORES","VEFJ900303M65",IF(G10="KARLA ESTEFANIA SALAZAR FLORES","SAFK9807277N1",IF(G10="ANGEL TERRAZAS MONROY","TEMA7105035N4")))))))))) -> RESICO
A11: =IF(D11>0,MONTH(D11),0) -> 1 | B11: =VLOOKUP(A11,[1]Hoja3!$C$3:$D$14,2,FALSE) -> ENERO | C11: 45316 | D11: 45316 | G11: EFREN ABUNDEZ REYNA | H11: =IF(G11="EFREN ABUNDEZ REYNA","AURE7306187IA",IF(G11="LUIS ALEJANDRO HERNANDEZ REYNA","HERL850705AL2",IF(G11="ANA BEATRIZ ESTRADA ARGOTE","EAAA860701UP2",IF(G11="SERGIO ROMERO DURAN","RODS620908QAA",IF(G11="MARIELA OLMOS GAONA","OOGM010703NX1",IF(G11="LUCIANO MIJAIL ORTEGA MUÑOZ","OEML881105IK2",IF(G11="GUSTAVO HUMBERTO VELAZCO GALVAN","VEGG9211019T1",IF(G11="JESUS AGUSTIN VELAZQUEZ FLORES","VEFJ900303M65",IF(G11="KARLA ESTEFANIA SALAZAR FLORES","SAFK9807277N1",IF(G11="ANGEL TERRAZAS MONROY","TEMA7105035N4")))))))))) -> AURE7306187IA | I11: =+B11 -> ENERO | J11: 1615 | K11: 0 | N11: =+J11+K11-L11-M11 -> 1615 | O11: =IF(G11="EFREN ABUNDEZ REYNA","37295",IF(G11="LUIS ALEJANDRO HERNANDEZ REYNA","HERL850705AL2",IF(G11="ANA BEATRIZ ESTRADA ARGOTE","EAAA860701UP2",IF(G11="SERGIO ROMERO DURAN","RODS620908QAA",IF(G11="MARIELA OLMOS GAONA","37675",IF(G11="LUCIANO MIJAIL ORTEGA MUÑOZ","37297",IF(G11="GUSTAVO HUMBERTO VELAZCO GALVAN","VEGG9211019T1",IF(G11="JESUS AGUSTIN VELAZQUEZ FLORES","VEFJ900303M65",IF(G11="KARLA ESTEFANIA SALAZAR FLORES","SAFK9807277N1",IF(G11="ANGEL TERRAZAS MONROY","TEMA7105035N4")))))))))) -> 37295 | P11: =IF(G11="EFREN ABUNDEZ REYNA","PFAEP",IF(G11="LUIS ALEJANDRO HERNANDEZ REYNA","HERL850705AL2",IF(G11="ANA BEATRIZ ESTRADA ARGOTE","EAAA860701UP2",IF(G11="SERGIO ROMERO DURAN","RODS620908QAA",IF(G11="MARIELA OLMOS GAONA","RESICO",IF(G11="LUCIANO MIJAIL ORTEGA MUÑOZ","RIF",IF(G11="GUSTAVO HUMBERTO VELAZCO GALVAN","VEGG9211019T1",IF(G11="JESUS AGUSTIN VELAZQUEZ FLORES","VEFJ900303M65",IF(G11="KARLA ESTEFANIA SALAZAR FLORES","SAFK9807277N1",IF(G11="ANGEL TERRAZAS MONROY","TEMA7105035N4")))))))))) -> PFAEP
A12: =IF(D12>0,MONTH(D12),0) -> 1 | B12: =VLOOKUP(A12,[1]Hoja3!$C$3:$D$14,2,FALSE) -> ENERO | C12: 45321 | D12: 45321 | G12: IITS IDENTIFICATION E INFORMATION TRANSPORT SYSTEMS | H12: IIE101203RU0 | I12: =+B12 -> ENERO | J12: 219 | K12: =+J12*0.16 -> 35.04 | N12: =+J12+K12-L12-M12 -> 254.04 | O12: 11289 | P12: MORAL | Q12: elopez@iits.com.mx | R12: T.D.
A13: =IF(D13>0,MONTH(D13),0) -> 1 | B13: =VLOOKUP(A13,[1]Hoja3!$C$3:$D$14,2,FALSE) -> ENERO | C13: 45321 | D13: 45321 | G13: MARIELA OLMOS GAONA | H13: =IF(G13="EFREN ABUNDEZ REYNA","AURE7306187IA",IF(G13="LUIS ALEJANDRO HERNANDEZ REYNA","HERL850705AL2",IF(G13="ANA BEATRIZ ESTRADA ARGOTE","EAAA860701UP2",IF(G13="SERGIO ROMERO DURAN","RODS620908QAA",IF(G13="MARIELA OLMOS GAONA","OOGM010703NX1",IF(G13="LUCIANO MIJAIL ORTEGA MUÑOZ","OEML881105IK2",IF(G13="GUSTAVO HUMBERTO VELAZCO GALVAN","VEGG9211019T1",IF(G13="JESUS AGUSTIN VELAZQUEZ FLORES","VEFJ900303M65",IF(G13="KARLA ESTEFANIA SALAZAR FLORES","SAFK9807277N1",IF(G13="ANGEL TERRAZAS MONROY","TEMA7105035N4")))))))))) -> OOGM010703NX1 | I13: =+B13 -> ENERO | J13: 8155 | K13: 0 | N13: =+J13+K13-L13-M13 -> 8155 | O13: =IF(G13="EFREN ABUNDEZ REYNA","37295",IF(G13="LUIS ALEJANDRO HERNANDEZ REYNA","HERL850705AL2",IF(G13="ANA BEATRIZ ESTRADA ARGOTE","EAAA860701UP2",IF(G13="SERGIO ROMERO DURAN","RODS620908QAA",IF(G13="MARIELA OLMOS GAONA","37675",IF(G13="LUCIANO MIJAIL ORTEGA MUÑOZ","37297",IF(G13="GUSTAVO HUMBERTO VELAZCO GALVAN","VEGG9211019T1",IF(G13="JESUS AGUSTIN VELAZQUEZ FLORES","VEFJ900303M65",IF(G13="KARLA ESTEFANIA SALAZAR FLORES","SAFK9807277N1",IF(G13="ANGEL TERRAZAS MONROY","TEMA7105035N4")))))))))) -> 37675 | P13: =IF(G13="EFREN ABUNDEZ REYNA","PFAEP",IF(G13="LUIS ALEJANDRO HERNANDEZ REYNA","HERL850705AL2",IF(G13="ANA BEATRIZ ESTRADA ARGOTE","EAAA860701UP2",IF(G13="SERGIO ROMERO DURAN","RODS620908QAA",IF(G13="MARIELA OLMOS GAONA","RESICO",IF(G13="LUCIANO MIJAIL ORTEGA MUÑOZ","RIF",IF(G13="GUSTAVO HUMBERTO VELAZCO GALVAN","VEGG9211019T1",IF(G13="JESUS AGUSTIN VELAZQUEZ FLORES","VEFJ900303M65",IF(G13="KARLA ESTEFANIA SALAZAR FLORES","SAFK9807277N1",IF(G13="ANGEL TERRAZAS MONROY","TEMA7105035N4")))))))))) -> RESICO
A14: =IF(D14>0,MONTH(D14),0) -> 1 | B14: =VLOOKUP(A14,[1]Hoja3!$C$3:$D$14,2,FALSE) -> ENERO | C14: 45321 | D14: 45321 | G14: IITS IDENTIFICATION E INFORMATION TRANSPORT SYSTEMS | H14: IIE101203RU0 | I14: =+B14 -> ENERO | J14: 436 | K14: =+J14*0.16 -> 69.76 | N14: =+J14+K14-L14-M14 -> 505.76 | O14: 11289 | P14: MORAL | Q14: ofernandez@iits.com.mx
A15: =IF(D15>0,MONTH(D15),0) -> 2 | B15: =VLOOKUP(A15,[1]Hoja3!$C$3:$D$14,2,FALSE) -> FEBRERO | C15: 45323 | D15: 45323 | G15: EFREN ABUNDEZ REYNA | H15: =IF(G15="EFREN ABUNDEZ REYNA","AURE7306187IA",IF(G15="LUIS ALEJANDRO HERNANDEZ REYNA","HERL850705AL2",IF(G15="ANA BEATRIZ ESTRADA ARGOTE","EAAA860701UP2",IF(G15="SERGIO ROMERO DURAN","RODS620908QAA",IF(G15="MARIELA OLMOS GAONA","OOGM010703NX1",IF(G15="LUCIANO MIJAIL ORTEGA MUÑOZ","OEML881105IK2",IF(G15="GUSTAVO HUMBERTO VELAZCO GALVAN","VEGG9211019T1",IF(G15="JESUS AGUSTIN VELAZQUEZ FLORES","VEFJ900303M65",IF(G15="KARLA ESTEFANIA SALAZAR FLORES","SAFK9807277N1",IF(G15="ANGEL TERRAZAS MONROY","TEMA7105035N4")))))))))) -> AURE7306187IA | I15: =+B15 -> FEBRERO | J15: 1116 | K15: 0 | N15: =+J15+K15-L15-M15 -> 1116 | O15: =IF(G15="EFREN ABUNDEZ REYNA","37295",IF(G15="LUIS ALEJANDRO HERNANDEZ REYNA","HERL850705AL2",IF(G15="ANA BEATRIZ ESTRADA ARGOTE","EAAA860701UP2",IF(G15="SERGIO ROMERO DURAN","RODS620908QAA",IF(G15="MARIELA OLMOS GAONA","37675",IF(G15="LUCIANO MIJAIL ORTEGA MUÑOZ","37297",IF(G15="GUSTAVO HUMBERTO VELAZCO GALVAN","VEGG9211019T1",IF(G15="JESUS AGUSTIN VELAZQUEZ FLORES","VEFJ900303M65",IF(G15="KARLA ESTEFANIA SALAZAR FLORES","SAFK9807277N1",IF(G15="ANGEL TERRAZAS MONROY","TEMA7105035N4")))))))))) -> 37295 | P15: =IF(G15="EFREN ABUNDEZ REYNA","PFAEP",IF(G15="LUIS ALEJANDRO HERNANDEZ REYNA","HERL850705AL2",IF(G15="ANA BEATRIZ ESTRADA ARGOTE","EAAA860701UP2",IF(G15="SERGIO ROMERO DURAN","RODS620908QAA",IF(G15="MARIELA OLMOS GAONA","RESICO",IF(G15="LUCIANO MIJAIL ORTEGA MUÑOZ","RIF",IF(G15="GUSTAVO HUMBERTO VELAZCO GALVAN","VEGG9211019T1",IF(G15="JESUS AGUSTIN VELAZQUEZ FLORES","VEFJ900303M65",IF(G15="KARLA ESTEFANIA SALAZAR FLORES","SAFK9807277N1",IF(G15="ANGEL TERRAZAS MONROY","TEMA7105035N4")))))))))) -> PFAEP
A16: =IF(D16>0,MONTH(D16),0) -> 2 | B16: =VLOOKUP(A16,[1]Hoja3!$C$3:$D$14,2,FALSE) -> FEBRERO | C16: 45323 | D16: 45323 | G16: EFREN ABUNDEZ REYNA | H16: =IF(G16="EFREN ABUNDEZ REYNA","AURE7306187IA",IF(G16="LUIS ALEJANDRO HERNANDEZ REYNA","HERL850705AL2",IF(G16="ANA BEATRIZ ESTRADA ARGOTE","EAAA860701UP2",IF(G16="SERGIO ROMERO DURAN","RODS620908QAA",IF(G16="MARIELA OLMOS GAONA","OOGM010703NX1",IF(G16="LUCIANO MIJAIL ORTEGA MUÑOZ","OEML881105IK2",IF(G16="GUSTAVO HUMBERTO VELAZCO GALVAN","VEGG9211019T1",IF(G16="JESUS AGUSTIN VELAZQUEZ FLORES","VEFJ900303M65",IF(G16="KARLA ESTEFANIA SALAZAR FLORES","SAFK9807277N1",IF(G16="ANGEL TERRAZAS MONROY","TEMA7105035N4")))))))))) -> AURE7306187IA | I16: =+B16 -> FEBRERO | J16: 1116 | K16: 0 | N16: =+J16+K16-L16-M16 -> 1116 | O16: =IF(G16="EFREN ABUNDEZ REYNA","37295",IF(G16="LUIS ALEJANDRO HERNANDEZ REYNA","HERL850705AL2",IF(G16="ANA BEATRIZ ESTRADA ARGOTE","EAAA860701UP2",IF(G16="SERGIO ROMERO DURAN","RODS620908QAA",IF(G16="MARIELA OLMOS GAONA","37675",IF(G16="LUCIANO MIJAIL ORTEGA MUÑOZ","37297",IF(G16="GUSTAVO HUMBERTO VELAZCO GALVAN","VEGG9211019T1",IF(G16="JESUS AGUSTIN VELAZQUEZ FLORES","VEFJ900303M65",IF(G16="KARLA ESTEFANIA SALAZAR FLORES","SAFK9807277N1",IF(G16="ANGEL TERRAZAS MONROY","TEMA7105035N4")))))))))) -> 37295 | P16: =IF(G16="EFREN ABUNDEZ REYNA","PFAEP",IF(G16="LUIS ALEJANDRO HERNANDEZ REYNA","HERL850705AL2",IF(G16="ANA BEATRIZ ESTRADA ARGOTE","EAAA860701UP2",IF(G16="SERGIO ROMERO DURAN","RODS620908QAA",IF(G16="MARIELA OLMOS GAONA","RESICO",IF(G16="LUCIANO MIJAIL ORTEGA MUÑOZ","RIF",IF(G16="GUSTAVO HUMBERTO VELAZCO GALVAN","VEGG9211019T1",IF(G16="JESUS AGUSTIN VELAZQUEZ FLORES","VEFJ900303M65",IF(G16="KARLA ESTEFANIA SALAZAR FLORES","SAFK9807277N1",IF(G16="ANGEL TERRAZAS MONROY","TEMA7105035N4")))))))))) -> PFAEP
A17: =IF(D17>0,MONTH(D17),0) -> 2 | B17: =VLOOKUP(A17,[1]Hoja3!$C$3:$D$14,2,FALSE) -> FEBRERO | C17: 45329 | D17: 45329 | G17: GRISELDA CELINA POOL NOH | H17: PONG860110V5A | I17: =+B17 -> FEBRERO | J17: 1470 | K17: =+J17*0.16 -> 235.2 | N17: =+J17+K17-L17-M17 -> 1705.2 | O17: 22237 | P17: PFAEP | Q17: javier.arcive@gmail.com
A18: =IF(D18>0,MONTH(D18),0) -> 2 | B18: =VLOOKUP(A18,[1]Hoja3!$C$3:$D$14,2,FALSE) -> FEBRERO | C18: 45329 | D18: 45329 | G18: EFREN ABUNDEZ REYNA | H18: =IF(G18="EFREN ABUNDEZ REYNA","AURE7306187IA",IF(G18="LUIS ALEJANDRO HERNANDEZ REYNA","HERL850705AL2",IF(G18="ANA BEATRIZ ESTRADA ARGOTE","EAAA860701UP2",IF(G18="SERGIO ROMERO DURAN","RODS620908QAA",IF(G18="MARIELA OLMOS GAONA","OOGM010703NX1",IF(G18="LUCIANO MIJAIL ORTEGA MUÑOZ","OEML881105IK2",IF(G18="GUSTAVO HUMBERTO VELAZCO GALVAN","VEGG9211019T1",IF(G18="JESUS AGUSTIN VELAZQUEZ FLORES","VEFJ900303M65",IF(G18="KARLA ESTEFANIA SALAZAR FLORES","SAFK9807277N1",IF(G18="ANGEL TERRAZAS MONROY","TEMA7105035N4")))))))))) -> AURE7306187IA | I18: =+B18 -> FEBRERO | J18: 1201 | K18: 0 | N18: =+J18+K18-L18-M18 -> 1201 | O18: =IF(G18="EFREN ABUNDEZ REYNA","37295",IF(G18="LUIS ALEJANDRO HERNANDEZ REYNA","HERL850705AL2",IF(G18="ANA BEATRIZ ESTRADA ARGOTE","EAAA860701UP2",IF(G18="SERGIO ROMERO DURAN","RODS620908QAA",IF(G18="MARIELA OLMOS GAONA","37675",IF(G18="LUCIANO MIJAIL ORTEGA MUÑOZ","37297",IF(G18="GUSTAVO HUMBERTO VELAZCO GALVAN","VEGG9211019T1",IF(G18="JESUS AGUSTIN VELAZQUEZ FLORES","VEFJ900303M65",IF(G18="KARLA ESTEFANIA SALAZAR FLORES","SAFK9807277N1",IF(G18="ANGEL TERRAZAS MONROY","TEMA7105035N4")))))))))) -> 37295 | P18: =IF(G18="EFREN ABUNDEZ REYNA","PFAEP",IF(G18="LUIS ALEJANDRO HERNANDEZ REYNA","HERL850705AL2",IF(G18="ANA BEATRIZ ESTRADA ARGOTE","EAAA860701UP2",IF(G18="SERGIO ROMERO DURAN","RODS620908QAA",IF(G18="MARIELA OLMOS GAONA","RESICO",IF(G18="LUCIANO MIJAIL ORTEGA MUÑOZ","RIF",IF(G18="GUSTAVO HUMBERTO VELAZCO GALVAN","VEGG9211019T1",IF(G18="JESUS AGUSTIN VELAZQUEZ FLORES","VEFJ900303M65",IF(G18="KARLA ESTEFANIA SALAZAR FLORES","SAFK9807277N1",IF(G18="ANGEL TERRAZAS MONROY","TEMA7105035N4")))))))))) -> PFAEP
A19: =IF(D19>0,MONTH(D19),0) -> 2 | B19: =VLOOKUP(A19,[1]Hoja3!$C$3:$D$14,2,FALSE) -> FEBRERO | C19: 45329 | D19: 45329 | G19: MARIELA OLMOS GAONA | H19: =IF(G19="EFREN ABUNDEZ REYNA","AURE7306187IA",IF(G19="LUIS ALEJANDRO HERNANDEZ REYNA","HERL850705AL2",IF(G19="ANA BEATRIZ ESTRADA ARGOTE","EAAA860701UP2",IF(G19="SERGIO ROMERO DURAN","RODS620908QAA",IF(G19="MARIELA OLMOS GAONA","OOGM010703NX1",IF(G19="LUCIANO MIJAIL ORTEGA MUÑOZ","OEML881105IK2",IF(G19="GUSTAVO HUMBERTO VELAZCO GALVAN","VEGG9211019T1",IF(G19="JESUS AGUSTIN VELAZQUEZ FLORES","VEFJ900303M65",IF(G19="KARLA ESTEFANIA SALAZAR FLORES","SAFK9807277N1",IF(G19="ANGEL TERRAZAS MONROY","TEMA7105035N4")))))))))) -> OOGM010703NX1 | I19: =+B19 -> FEBRERO | J19: 5980 | K19: 0 | N19: =+J19+K19-L19-M19 -> 5980 | O19: =IF(G19="EFREN ABUNDEZ REYNA","37295",IF(G19="LUIS ALEJANDRO HERNANDEZ REYNA","HERL850705AL2",IF(G19="ANA BEATRIZ ESTRADA ARGOTE","EAAA860701UP2",IF(G19="SERGIO ROMERO DURAN","RODS620908QAA",IF(G19="MARIELA OLMOS GAONA","37675",IF(G19="LUCIANO MIJAIL ORTEGA MUÑOZ","37297",IF(G19="GUSTAVO HUMBERTO VELAZCO GALVAN","VEGG9211019T1",IF(G19="JESUS AGUSTIN VELAZQUEZ FLORES","VEFJ900303M65",IF(G19="KARLA ESTEFANIA SALAZAR FLORES","SAFK9807277N1",IF(G19="ANGEL TERRAZAS MONROY","TEMA7105035N4")))))))))) -> 37675 | P19: =IF(G19="EFREN ABUNDEZ REYNA","PFAEP",IF(G19="LUIS ALEJANDRO HERNANDEZ REYNA","HERL850705AL2",IF(G19="ANA BEATRIZ ESTRADA ARGOTE","EAAA860701UP2",IF(G19="SERGIO ROMERO DURAN","RODS620908QAA",IF(G19="MARIELA OLMOS GAONA","RESICO",IF(G19="LUCIANO MIJAIL ORTEGA MUÑOZ","RIF",IF(G19="GUSTAVO HUMBERTO VELAZCO GALVAN","VEGG9211019T1",IF(G19="JESUS AGUSTIN VELAZQUEZ FLORES","VEFJ900303M65",IF(G19="KARLA ESTEFANIA SALAZAR FLORES","SAFK9807277N1",IF(G19="ANGEL TERRAZAS MONROY","TEMA7105035N4")))))))))) -> RESICO
A20: =IF(D20>0,MONTH(D20),0) -> 2 | B20: =VLOOKUP(A20,[1]Hoja3!$C$3:$D$14,2,FALSE) -> FEBRERO | C20: 45344 | D20: 45344 | G20: MARIELA OLMOS GAONA | H20: =IF(G20="EFREN ABUNDEZ REYNA","AURE7306187IA",IF(G20="LUIS ALEJANDRO HERNANDEZ REYNA","HERL850705AL2",IF(G20="ANA BEATRIZ ESTRADA ARGOTE","EAAA860701UP2",IF(G20="SERGIO ROMERO DURAN","RODS620908QAA",IF(G20="MARIELA OLMOS GAONA","OOGM010703NX1",IF(G20="LUCIANO MIJAIL ORTEGA MUÑOZ","OEML881105IK2",IF(G20="GUSTAVO HUMBERTO VELAZCO GALVAN","VEGG9211019T1",IF(G20="JESUS AGUSTIN VELAZQUEZ FLORES","VEFJ900303M65",IF(G20="KARLA ESTEFANIA SALAZAR FLORES","SAFK9807277N1",IF(G20="ANGEL TERRAZAS MONROY","TEMA7105035N4")))))))))) -> OOGM010703NX1 | I20: =+B20 -> FEBRERO | J20: 8980 | K20: 0 | N20: =+J20+K20-L20-M20 -> 8980 | O20: =IF(G20="EFREN ABUNDEZ REYNA","37295",IF(G20="LUIS ALEJANDRO HERNANDEZ REYNA","HERL850705AL2",IF(G20="ANA BEATRIZ ESTRADA ARGOTE","EAAA860701UP2",IF(G20="SERGIO ROMERO DURAN","RODS620908QAA",IF(G20="MARIELA OLMOS GAONA","37675",IF(G20="LUCIANO MIJAIL ORTEGA MUÑOZ","37297",IF(G20="GUSTAVO HUMBERTO VELAZCO GALVAN","VEGG9211019T1",IF(G20="JESUS AGUSTIN VELAZQUEZ FLORES","VEFJ900303M65",IF(G20="KARLA ESTEFANIA SALAZAR FLORES","SAFK9807277N1",IF(G20="ANGEL TERRAZAS MONROY","TEMA7105035N4")))))))))) -> 37675 | P20: =IF(G20="EFREN ABUNDEZ REYNA","PFAEP",IF(G20="LUIS ALEJANDRO HERNANDEZ REYNA","HERL850705AL2",IF(G20="ANA BEATRIZ ESTRADA ARGOTE","EAAA860701UP2",IF(G20="SERGIO ROMERO DURAN","RODS620908QAA",IF(G20="MARIELA OLMOS GAONA","RESICO",IF(G20="LUCIANO MIJAIL ORTEGA MUÑOZ","RIF",IF(G20="GUSTAVO HUMBERTO VELAZCO GALVAN","VEGG9211019T1",IF(G20="JESUS AGUSTIN VELAZQUEZ FLORES","VEFJ900303M65",IF(G20="KARLA ESTEFANIA SALAZAR FLORES","SAFK9807277N1",IF(G20="ANGEL TERRAZAS MONROY","TEMA7105035N4")))))))))) -> RESICO
A21: =IF(D21>0,MONTH(D21),0) -> 2 | B21: =VLOOKUP(A21,[1]Hoja3!$C$3:$D$14,2,FALSE) -> FEBRERO | C21: 45344 | D21: 45344 | G21: EFREN ABUNDEZ REYNA | H21: =IF(G21="EFREN ABUNDEZ REYNA","AURE7306187IA",IF(G21="LUIS ALEJANDRO HERNANDEZ REYNA","HERL850705AL2",IF(G21="ANA BEATRIZ ESTRADA ARGOTE","EAAA860701UP2",IF(G21="SERGIO ROMERO DURAN","RODS620908QAA",IF(G21="MARIELA OLMOS GAONA","OOGM010703NX1",IF(G21="LUCIANO MIJAIL ORTEGA MUÑOZ","OEML881105IK2",IF(G21="GUSTAVO HUMBERTO VELAZCO GALVAN","VEGG9211019T1",IF(G21="JESUS AGUSTIN VELAZQUEZ FLORES","VEFJ900303M65",IF(G21="KARLA ESTEFANIA SALAZAR FLORES","SAFK9807277N1",IF(G21="ANGEL TERRAZAS MONROY","TEMA7105035N4")))))))))) -> AURE7306187IA | I21: =+B21 -> FEBRERO | J21: 1777 | K21: 0 | N21: =+J21+K21-L21-M21 -> 1777 | O21: =IF(G21="EFREN ABUNDEZ REYNA","37295",IF(G21="LUIS ALEJANDRO HERNANDEZ REYNA","HERL850705AL2",IF(G21="ANA BEATRIZ ESTRADA ARGOTE","EAAA860701UP2",IF(G21="SERGIO ROMERO DURAN","RODS620908QAA",IF(G21="MARIELA OLMOS GAONA","37675",IF(G21="LUCIANO MIJAIL ORTEGA MUÑOZ","37297",IF(G21="GUSTAVO HUMBERTO VELAZCO GALVAN","VEGG9211019T1",IF(G21="JESUS AGUSTIN VELAZQUEZ FLORES","VEFJ900303M65",IF(G21="KARLA ESTEFANIA SALAZAR FLORES","SAFK9807277N1",IF(G21="ANGEL TERRAZAS MONROY","TEMA7105035N4")))))))))) -> 37295 | P21: =IF(G21="EFREN ABUNDEZ REYNA","PFAEP",IF(G21="LUIS ALEJANDRO HERNANDEZ REYNA","HERL850705AL2",IF(G21="ANA BEATRIZ ESTRADA ARGOTE","EAAA860701UP2",IF(G21="SERGIO ROMERO DURAN","RODS620908QAA",IF(G21="MARIELA OLMOS GAONA","RESICO",IF(G21="LUCIANO MIJAIL ORTEGA MUÑOZ","RIF",IF(G21="GUSTAVO HUMBERTO VELAZCO GALVAN","VEGG9211019T1",IF(G21="JESUS AGUSTIN VELAZQUEZ FLORES","VEFJ900303M65",IF(G21="KARLA ESTEFANIA SALAZAR FLORES","SAFK9807277N1",IF(G21="ANGEL TERRAZAS MONROY","TEMA7105035N4")))))))))) -> PFAEP
A22: =IF(D22>0,MONTH(D22),0) -> 2 | B22: =VLOOKUP(A22,[1]Hoja3!$C$3:$D$14,2,FALSE) -> FEBRERO | C22: 45344 | D22: 45344 | G22: MARIELA OLMOS GAONA | H22: =IF(G22="EFREN ABUNDEZ REYNA","AURE7306187IA",IF(G22="LUIS ALEJANDRO HERNANDEZ REYNA","HERL850705AL2",IF(G22="ANA BEATRIZ ESTRADA ARGOTE","EAAA860701UP2",IF(G22="SERGIO ROMERO DURAN","RODS620908QAA",IF(G22="MARIELA OLMOS GAONA","OOGM010703NX1",IF(G22="LUCIANO MIJAIL ORTEGA MUÑOZ","OEML881105IK2",IF(G22="GUSTAVO HUMBERTO VELAZCO GALVAN","VEGG9211019T1",IF(G22="JESUS AGUSTIN VELAZQUEZ FLORES","VEFJ900303M65",IF(G22="KARLA ESTEFANIA SALAZAR FLORES","SAFK9807277N1",IF(G22="ANGEL TERRAZAS MONROY","TEMA7105035N4")))))))))) -> OOGM010703NX1 | I22: =+B22 -> FEBRERO | J22: 8317 | K22: 0 | N22: =+J22+K22-L22-M22 -> 8317 | O22: =IF(G22="EFREN ABUNDEZ REYNA","37295",IF(G22="LUIS ALEJANDRO HERNANDEZ REYNA","HERL850705AL2",IF(G22="ANA BEATRIZ ESTRADA ARGOTE","EAAA860701UP2",IF(G22="SERGIO ROMERO DURAN","RODS620908QAA",IF(G22="MARIELA OLMOS GAONA","37675",IF(G22="LUCIANO MIJAIL ORTEGA MUÑOZ","37297",IF(G22="GUSTAVO HUMBERTO VELAZCO GALVAN","VEGG9211019T1",IF(G22="JESUS AGUSTIN VELAZQUEZ FLORES","VEFJ900303M65",IF(G22="KARLA ESTEFANIA SALAZAR FLORES","SAFK9807277N1",IF(G22="ANGEL TERRAZAS MONROY","TEMA7105035N4")))))))))) -> 37675 | P22: =IF(G22="EFREN ABUNDEZ REYNA","PFAEP",IF(G22="LUIS ALEJANDRO HERNANDEZ REYNA","HERL850705AL2",IF(G22="ANA BEATRIZ ESTRADA ARGOTE","EAAA860701UP2",IF(G22="SERGIO ROMERO DURAN","RODS620908QAA",IF(G22="MARIELA OLMOS GAONA","RESICO",IF(G22="LUCIANO MIJAIL ORTEGA MUÑOZ","RIF",IF(G22="GUSTAVO HUMBERTO VELAZCO GALVAN","VEGG9211019T1",IF(G22="JESUS AGUSTIN VELAZQUEZ FLORES","VEFJ900303M65",IF(G22="KARLA ESTEFANIA SALAZAR FLORES","SAFK9807277N1",IF(G22="ANGEL TERRAZAS MONROY","TEMA7105035N4")))))))))) -> RESICO
A23: =IF(D23>0,MONTH(D23),0) -> 2 | B23: =VLOOKUP(A23,[1]Hoja3!$C$3:$D$14,2,FALSE) -> FEBRERO | C23: 45344 | D23: 45344 | G23: CAJA POPULAR MEXICANA | H23: CPM960127M3A | I23: =+B23 -> FEBRERO | J23: 431.03448 | K23: =+J23*0.16 -> 68.965517 | N23: =+J23+K23-L23-M23 -> 500 | O23: 37004 | P23: moral no lucrativa | Q23: hedj124791234@gmail.com
A24: =IF(D24>0,MONTH(D24),0) -> 2 | B24: =VLOOKUP(A24,[1]Hoja3!$C$3:$D$14,2,FALSE) -> FEBRERO | C24: 45349 | D24: 45349 | G24: MARIELA OLMOS GAONA | H24: =IF(G24="EFREN ABUNDEZ REYNA","AURE7306187IA",IF(G24="LUIS ALEJANDRO HERNANDEZ REYNA","HERL850705AL2",IF(G24="ANA BEATRIZ ESTRADA ARGOTE","EAAA860701UP2",IF(G24="SERGIO ROMERO DURAN","RODS620908QAA",IF(G24="MARIELA OLMOS GAONA","OOGM010703NX1",IF(G24="LUCIANO MIJAIL ORTEGA MUÑOZ","OEML881105IK2",IF(G24="GUSTAVO HUMBERTO VELAZCO GALVAN","VEGG9211019T1",IF(G24="JESUS AGUSTIN VELAZQUEZ FLORES","VEFJ900303M65",IF(G24="KARLA ESTEFANIA SALAZAR FLORES","SAFK9807277N1",IF(G24="ANGEL TERRAZAS MONROY","TEMA7105035N4")))))))))) -> OOGM010703NX1 | I24: =+B24 -> FEBRERO | J24: 4950 | K24: 0 | N24: =+J24+K24-L24-M24 -> 4950 | O24: =IF(G24="EFREN ABUNDEZ REYNA","37295",IF(G24="LUIS ALEJANDRO HERNANDEZ REYNA","HERL850705AL2",IF(G24="ANA BEATRIZ ESTRADA ARGOTE","EAAA860701UP2",IF(G24="SERGIO ROMERO DURAN","RODS620908QAA",IF(G24="MARIELA OLMOS GAONA","37675",IF(G24="LUCIANO MIJAIL ORTEGA MUÑOZ","37297",IF(G24="GUSTAVO HUMBERTO VELAZCO GALVAN","VEGG9211019T1",IF(G24="JESUS AGUSTIN VELAZQUEZ FLORES","VEFJ900303M65",IF(G24="KARLA ESTEFANIA SALAZAR FLORES","SAFK9807277N1",IF(G24="ANGEL TERRAZAS MONROY","TEMA7105035N4")))))))))) -> 37675 | P24: =IF(G24="EFREN ABUNDEZ REYNA","PFAEP",IF(G24="LUIS ALEJANDRO HERNANDEZ REYNA","HERL850705AL2",IF(G24="ANA BEATRIZ ESTRADA ARGOTE","EAAA860701UP2",IF(G24="SERGIO ROMERO DURAN","RODS620908QAA",IF(G24="MARIELA OLMOS GAONA","RESICO",IF(G24="LUCIANO MIJAIL ORTEGA MUÑOZ","RIF",IF(G24="GUSTAVO HUMBERTO VELAZCO GALVAN","VEGG9211019T1",IF(G24="JESUS AGUSTIN VELAZQUEZ FLORES","VEFJ900303M65",IF(G24="KARLA ESTEFANIA SALAZAR FLORES","SAFK9807277N1",IF(G24="ANGEL TERRAZAS MONROY","TEMA7105035N4")))))))))) -> RESICO
A25: =IF(D25>0,MONTH(D25),0) -> 1 | B25: =VLOOKUP(A25,[1]Hoja3!$C$3:$D$14,2,FALSE) -> ENERO | C25: 45322 | D25: 45322 | G25: PUBLICO EN GENERAL | H25: =IF(G25="EFREN ABUNDEZ REYNA","AURE7306187IA",IF(G25="LUIS ALEJANDRO HERNANDEZ REYNA","HERL850705AL2",IF(G25="ANA BEATRIZ ESTRADA ARGOTE","EAAA860701UP2",IF(G25="SERGIO ROMERO DURAN","RODS620908QAA",IF(G25="MARIELA OLMOS GAONA","OOGM010703NX1",IF(G25="LUCIANO MIJAIL ORTEGA MUÑOZ","OEML881105IK2",IF(G25="GUSTAVO HUMBERTO VELAZCO GALVAN","VEGG9211019T1",IF(G25="JESUS AGUSTIN VELAZQUEZ FLORES","VEFJ900303M65",IF(G25="KARLA ESTEFANIA SALAZAR FLORES","SAFK9807277N1",IF(G25="ANGEL TERRAZAS MONROY","TEMA7105035N4")))))))))) -> FALSE | I25: =+B25 -> ENERO | J25: 260145 | K25: 0 | N25: =+J25+K25-L25-M25 -> 260145 | O25: =IF(G25="EFREN ABUNDEZ REYNA","37295",IF(G25="LUIS ALEJANDRO HERNANDEZ REYNA","HERL850705AL2",IF(G25="ANA BEATRIZ ESTRADA ARGOTE","EAAA860701UP2",IF(G25="SERGIO ROMERO DURAN","RODS620908QAA",IF(G25="MARIELA OLMOS GAONA","37675",IF(G25="LUCIANO MIJAIL ORTEGA MUÑOZ","37297",IF(G25="GUSTAVO HUMBERTO VELAZCO GALVAN","VEGG9211019T1",IF(G25="JESUS AGUSTIN VELAZQUEZ FLORES","VEFJ900303M65",IF(G25="KARLA ESTEFANIA SALAZAR FLORES","SAFK9807277N1",IF(G25="ANGEL TERRAZAS MONROY","TEMA7105035N4")))))))))) -> FALSE | P25: =IF(G25="EFREN ABUNDEZ REYNA","PFAEP",IF(G25="LUIS ALEJANDRO HERNANDEZ REYNA","HERL850705AL2",IF(G25="ANA BEATRIZ ESTRADA ARGOTE","EAAA860701UP2",IF(G25="SERGIO ROMERO DURAN","RODS620908QAA",IF(G25="MARIELA OLMOS GAONA","RESICO",IF(G25="LUCIANO MIJAIL ORTEGA MUÑOZ","RIF",IF(G25="GUSTAVO HUMBERTO VELAZCO GALVAN","VEGG9211019T1",IF(G25="JESUS AGUSTIN VELAZQUEZ FLORES","VEFJ900303M65",IF(G25="KARLA ESTEFANIA SALAZAR FLORES","SAFK9807277N1",IF(G25="ANGEL TERRAZAS MONROY","TEMA7105035N4")))))))))) -> FALSE
A26: =IF(D26>0,MONTH(D26),0) -> 3 | B26: =VLOOKUP(A26,[1]Hoja3!$C$3:$D$14,2,FALSE) -> MARZO | C26: 45358 | D26: 45358 | G26: MARIELA OLMOS GAONA | H26: =IF(G26="EFREN ABUNDEZ REYNA","AURE7306187IA",IF(G26="LUIS ALEJANDRO HERNANDEZ REYNA","HERL850705AL2",IF(G26="ANA BEATRIZ ESTRADA ARGOTE","EAAA860701UP2",IF(G26="SERGIO ROMERO DURAN","RODS620908QAA",IF(G26="MARIELA OLMOS GAONA","OOGM010703NX1",IF(G26="LUCIANO MIJAIL ORTEGA MUÑOZ","OEML881105IK2",IF(G26="GUSTAVO HUMBERTO VELAZCO GALVAN","VEGG9211019T1",IF(G26="JESUS AGUSTIN VELAZQUEZ FLORES","VEFJ900303M65",IF(G26="KARLA ESTEFANIA SALAZAR FLORES","SAFK9807277N1",IF(G26="ANGEL TERRAZAS MONROY","TEMA7105035N4")))))))))) -> OOGM010703NX1 | I26: =+B26 -> MARZO | J26: 7125 | K26: 0 | N26: =+J26+K26-L26-M26 -> 7125 | O26: =IF(G26="EFREN ABUNDEZ REYNA","37295",IF(G26="LUIS ALEJANDRO HERNANDEZ REYNA","HERL850705AL2",IF(G26="ANA BEATRIZ ESTRADA ARGOTE","EAAA860701UP2",IF(G26="SERGIO ROMERO DURAN","RODS620908QAA",IF(G26="MARIELA OLMOS GAONA","37675",IF(G26="LUCIANO MIJAIL ORTEGA MUÑOZ","37297",IF(G26="GUSTAVO HUMBERTO VELAZCO GALVAN","VEGG9211019T1",IF(G26="JESUS AGUSTIN VELAZQUEZ FLORES","VEFJ900303M65",IF(G26="KARLA ESTEFANIA SALAZAR FLORES","SAFK9807277N1",IF(G26="ANGEL TERRAZAS MONROY","TEMA7105035N4")))))))))) -> 37675 | P26: =IF(G26="EFREN ABUNDEZ REYNA","PFAEP",IF(G26="LUIS ALEJANDRO HERNANDEZ REYNA","HERL850705AL2",IF(G26="ANA BEATRIZ ESTRADA ARGOTE","EAAA860701UP2",IF(G26="SERGIO ROMERO DURAN","RODS620908QAA",IF(G26="MARIELA OLMOS GAONA","RESICO",IF(G26="LUCIANO MIJAIL ORTEGA MUÑOZ","RIF",IF(G26="GUSTAVO HUMBERTO VELAZCO GALVAN","VEGG9211019T1",IF(G26="JESUS AGUSTIN VELAZQUEZ FLORES","VEFJ900303M65",IF(G26="KARLA ESTEFANIA SALAZAR FLORES","SAFK9807277N1",IF(G26="ANGEL TERRAZAS MONROY","TEMA7105035N4")))))))))) -> RESICO
A27: =IF(D27>0,MONTH(D27),0) -> 3 | B27: =VLOOKUP(A27,[1]Hoja3!$C$3:$D$14,2,FALSE) -> MARZO | C27: 45358 | D27: 45358 | G27: FARMACIA GUADALAJARA | H27: FGU830930PD3 | I27: =+B27 -> MARZO | J27: 180.17 | K27: =+J27*0.16 -> 28.8272 | N27: =+J27+K27-L27-M27 -> 208.9972 | O27: 44610 | P27: MORAL
A28: =IF(D28>0,MONTH(D28),0) -> 3 | B28: =VLOOKUP(A28,[1]Hoja3!$C$3:$D$14,2,FALSE) -> MARZO | C28: 45358 | D28: 45358 | G28: FARMACIA GUADALAJARA | H28: FGU830930PD3 | I28: =+B28 -> MARZO | J28: 839.65517 | K28: =+J28*0.16 -> 134.34483 | N28: =+J28+K28-L28-M28 -> 974 | O28: 44610 | P28: MORAL
A29: =IF(D29>0,MONTH(D29),0) -> 3 | B29: =VLOOKUP(A29,[1]Hoja3!$C$3:$D$14,2,FALSE) -> MARZO | C29: 45363 | D29: 45363 | G29: MARIELA OLMOS GAONA | H29: =IF(G29="EFREN ABUNDEZ REYNA","AURE7306187IA",IF(G29="LUIS ALEJANDRO HERNANDEZ REYNA","HERL850705AL2",IF(G29="ANA BEATRIZ ESTRADA ARGOTE","EAAA860701UP2",IF(G29="SERGIO ROMERO DURAN","RODS620908QAA",IF(G29="MARIELA OLMOS GAONA","OOGM010703NX1",IF(G29="LUCIANO MIJAIL ORTEGA MUÑOZ","OEML881105IK2",IF(G29="GUSTAVO HUMBERTO VELAZCO GALVAN","VEGG9211019T1",IF(G29="JESUS AGUSTIN VELAZQUEZ FLORES","VEFJ900303M65",IF(G29="KARLA ESTEFANIA SALAZAR FLORES","SAFK9807277N1",IF(G29="ANGEL TERRAZAS MONROY","TEMA7105035N4")))))))))) -> OOGM010703NX1 | I29: =+B29 -> MARZO | J29: 71906.46 | K29: 0 | N29: =+J29+K29-L29-M29 -> 71906.46 | O29: =IF(G29="EFREN ABUNDEZ REYNA","37295",IF(G29="LUIS ALEJANDRO HERNANDEZ REYNA","HERL850705AL2",IF(G29="ANA BEATRIZ ESTRADA ARGOTE","EAAA860701UP2",IF(G29="SERGIO ROMERO DURAN","RODS620908QAA",IF(G29="MARIELA OLMOS GAONA","37675",IF(G29="LUCIANO MIJAIL ORTEGA MUÑOZ","37297",IF(G29="GUSTAVO HUMBERTO VELAZCO GALVAN","VEGG9211019T1",IF(G29="JESUS AGUSTIN VELAZQUEZ FLORES","VEFJ900303M65",IF(G29="KARLA ESTEFANIA SALAZAR FLORES","SAFK9807277N1",IF(G29="ANGEL TERRAZAS MONROY","TEMA7105035N4")))))))))) -> 37675 | P29: =IF(G29="EFREN ABUNDEZ REYNA","PFAEP",IF(G29="LUIS ALEJANDRO HERNANDEZ REYNA","HERL850705AL2",IF(G29="ANA BEATRIZ ESTRADA ARGOTE","EAAA860701UP2",IF(G29="SERGIO ROMERO DURAN","RODS620908QAA",IF(G29="MARIELA OLMOS GAONA","RESICO",IF(G29="LUCIANO MIJAIL ORTEGA MUÑOZ","RIF",IF(G29="GUSTAVO HUMBERTO VELAZCO GALVAN","VEGG9211019T1",IF(G29="JESUS AGUSTIN VELAZQUEZ FLORES","VEFJ900303M65",IF(G29="KARLA ESTEFANIA SALAZAR FLORES","SAFK9807277N1",IF(G29="ANGEL TERRAZAS MONROY","TEMA7105035N4")))))))))) -> RESICO
A30: =IF(D30>0,MONTH(D30),0) -> 2 | B30: =VLOOKUP(A30,[1]Hoja3!$C$3:$D$14,2,FALSE) -> FEBRERO | C30: 45342 | D30: 45351 | G30: PUBLICO EN GENERAL | H30: =IF(G30="EFREN ABUNDEZ REYNA","AURE7306187IA",IF(G30="LUIS ALEJANDRO HERNANDEZ REYNA","HERL850705AL2",IF(G30="ANA BEATRIZ ESTRADA ARGOTE","EAAA860701UP2",IF(G30="SERGIO ROMERO DURAN","RODS620908QAA",IF(G30="MARIELA OLMOS GAONA","OOGM010703NX1",IF(G30="LUCIANO MIJAIL ORTEGA MUÑOZ","OEML881105IK2",IF(G30="GUSTAVO HUMBERTO VELAZCO GALVAN","VEGG9211019T1",IF(G30="JESUS AGUSTIN VELAZQUEZ FLORES","VEFJ900303M65",IF(G30="KARLA ESTEFANIA SALAZAR FLORES","SAFK9807277N1",IF(G30="ANGEL TERRAZAS MONROY","TEMA7105035N4")))))))))) -> FALSE | I30: =+B30 -> FEBRERO | J30: 195234 | K30: 0 | N30: =+J30+K30-L30-M30 -> 195234 | O30: =IF(G30="EFREN ABUNDEZ REYNA","37295",IF(G30="LUIS ALEJANDRO HERNANDEZ REYNA","HERL850705AL2",IF(G30="ANA BEATRIZ ESTRADA ARGOTE","EAAA860701UP2",IF(G30="SERGIO ROMERO DURAN","RODS620908QAA",IF(G30="MARIELA OLMOS GAONA","37675",IF(G30="LUCIANO MIJAIL ORTEGA MUÑOZ","37297",IF(G30="GUSTAVO HUMBERTO VELAZCO GALVAN","VEGG9211019T1",IF(G30="JESUS AGUSTIN VELAZQUEZ FLORES","VEFJ900303M65",IF(G30="KARLA ESTEFANIA SALAZAR FLORES","SAFK9807277N1",IF(G30="ANGEL TERRAZAS MONROY","TEMA7105035N4")))))))))) -> FALSE | P30: =IF(G30="EFREN ABUNDEZ REYNA","PFAEP",IF(G30="LUIS ALEJANDRO HERNANDEZ REYNA","HERL850705AL2",IF(G30="ANA BEATRIZ ESTRADA ARGOTE","EAAA860701UP2",IF(G30="SERGIO ROMERO DURAN","RODS620908QAA",IF(G30="MARIELA OLMOS GAONA","RESICO",IF(G30="LUCIANO MIJAIL ORTEGA MUÑOZ","RIF",IF(G30="GUSTAVO HUMBERTO VELAZCO GALVAN","VEGG9211019T1",IF(G30="JESUS AGUSTIN VELAZQUEZ FLORES","VEFJ900303M65",IF(G30="KARLA ESTEFANIA SALAZAR FLORES","SAFK9807277N1",IF(G30="ANGEL TERRAZAS MONROY","TEMA7105035N4")))))))))) -> FALSE
A31: =IF(D31>0,MONTH(D31),0) -> 4 | B31: =VLOOKUP(A31,[1]Hoja3!$C$3:$D$14,2,FALSE) -> ABRIL | C31: 45405 | D31: 45405 | G31: POWERQRO | H31: POW210709HU2 | I31: =+B31 -> ABRIL | J31: 210 | K31: =+J31*0.16 -> 33.6 | N31: =+J31+K31-L31-M31 -> 243.6 | O31: 76226 | P31: MORAL | Q31: Seguridad@powerqro.mx
A32: =IF(D32>0,MONTH(D32),0) -> 4 | B32: =VLOOKUP(A32,[1]Hoja3!$C$3:$D$14,2,FALSE) -> ABRIL | C32: 45405 | D32: 45405 | G32: POWERQRO | H32: POW210709HU2 | I32: =+B32 -> ABRIL | J32: 190 | K32: =+J32*0.16 -> 30.4 | N32: =+J32+K32-L32-M32 -> 220.4 | O32: 76226 | P32: MORAL | Q32: Seguridad@powerqro.mx
A33: =IF(D33>0,MONTH(D33),0) -> 4 | B33: =VLOOKUP(A33,[1]Hoja3!$C$3:$D$14,2,FALSE) -> ABRIL | C33: 45412 | D33: 45412 | G33: CALIBRACMM DE MEXICO | H33: CME040519990 | I33: =+B33 -> ABRIL | J33: 457.75862 | K33: =+J33*0.16 -> 73.241379 | N33: =+J33+K33-L33-M33 -> 531 | O33: 72210 | P33: MORAL | Q33: jesusariz@hotmail.com
A34: =IF(D34>0,MONTH(D34),0) -> 3 | B34: =VLOOKUP(A34,[1]Hoja3!$C$3:$D$14,2,FALSE) -> MARZO | C34: 45380 | D34: 45380 | G34: PUBLICO EN GENERAL | H34: =IF(G34="EFREN ABUNDEZ REYNA","AURE7306187IA",IF(G34="LUIS ALEJANDRO HERNANDEZ REYNA","HERL850705AL2",IF(G34="ANA BEATRIZ ESTRADA ARGOTE","EAAA860701UP2",IF(G34="SERGIO ROMERO DURAN","RODS620908QAA",IF(G34="MARIELA OLMOS GAONA","OOGM010703NX1",IF(G34="LUCIANO MIJAIL ORTEGA MUÑOZ","OEML881105IK2",IF(G34="GUSTAVO HUMBERTO VELAZCO GALVAN","VEGG9211019T1",IF(G34="JESUS AGUSTIN VELAZQUEZ FLORES","VEFJ900303M65",IF(G34="KARLA ESTEFANIA SALAZAR FLORES","SAFK9807277N1",IF(G34="ANGEL TERRAZAS MONROY","TEMA7105035N4")))))))))) -> FALSE | I34: =+B34 -> MARZO | J34: 160757.6 | K34: 0 | N34: =+J34+K34-L34-M34 -> 160757.6 | O34: =IF(G34="EFREN ABUNDEZ REYNA","37295",IF(G34="LUIS ALEJANDRO HERNANDEZ REYNA","HERL850705AL2",IF(G34="ANA BEATRIZ ESTRADA ARGOTE","EAAA860701UP2",IF(G34="SERGIO ROMERO DURAN","RODS620908QAA",IF(G34="MARIELA OLMOS GAONA","37675",IF(G34="LUCIANO MIJAIL ORTEGA MUÑOZ","37297",IF(G34="GUSTAVO HUMBERTO VELAZCO GALVAN","VEGG9211019T1",IF(G34="JESUS AGUSTIN VELAZQUEZ FLORES","VEFJ900303M65",IF(G34="KARLA ESTEFANIA SALAZAR FLORES","SAFK9807277N1",IF(G34="ANGEL TERRAZAS MONROY","TEMA7105035N4")))))))))) -> FALSE | P34: =IF(G34="EFREN ABUNDEZ REYNA","PFAEP",IF(G34="LUIS ALEJANDRO HERNANDEZ REYNA","HERL850705AL2",IF(G34="ANA BEATRIZ ESTRADA ARGOTE","EAAA860701UP2",IF(G34="SERGIO ROMERO DURAN","RODS620908QAA",IF(G34="MARIELA OLMOS GAONA","RESICO",IF(G34="LUCIANO MIJAIL ORTEGA MUÑOZ","RIF",IF(G34="GUSTAVO HUMBERTO VELAZCO GALVAN","VEGG9211019T1",IF(G34="JESUS AGUSTIN VELAZQUEZ FLORES","VEFJ900303M65",IF(G34="KARLA ESTEFANIA SALAZAR FLORES","SAFK9807277N1",IF(G34="ANGEL TERRAZAS MONROY","TEMA7105035N4")))))))))) -> FALSE
A35: =IF(D35>0,MONTH(D35),0) -> 5 | B35: =VLOOKUP(A35,[1]Hoja3!$C$3:$D$14,2,FALSE) -> MAYO | C35: 45414 | D35: 45414 | G35: MARIELA OLMOS GAONA | H35: =IF(G35="EFREN ABUNDEZ REYNA","AURE7306187IA",IF(G35="LUIS ALEJANDRO HERNANDEZ REYNA","HERL850705AL2",IF(G35="ANA BEATRIZ ESTRADA ARGOTE","EAAA860701UP2",IF(G35="SERGIO ROMERO DURAN","RODS620908QAA",IF(G35="MARIELA OLMOS GAONA","OOGM010703NX1",IF(G35="LUCIANO MIJAIL ORTEGA MUÑOZ","OEML881105IK2",IF(G35="GUSTAVO HUMBERTO VELAZCO GALVAN","VEGG9211019T1",IF(G35="JESUS AGUSTIN VELAZQUEZ FLORES","VEFJ900303M65",IF(G35="KARLA ESTEFANIA SALAZAR FLORES","SAFK9807277N1",IF(G35="ANGEL TERRAZAS MONROY","TEMA7105035N4")))))))))) -> OOGM010703NX1 | I35: =+B35 -> MAYO | J35: 7238 | K35: 0 | N35: =+J35+K35-L35-M35 -> 7238 | O35: =IF(G35="EFREN ABUNDEZ REYNA","37295",IF(G35="LUIS ALEJANDRO HERNANDEZ REYNA","HERL850705AL2",IF(G35="ANA BEATRIZ ESTRADA ARGOTE","EAAA860701UP2",IF(G35="SERGIO ROMERO DURAN","RODS620908QAA",IF(G35="MARIELA OLMOS GAONA","37675",IF(G35="LUCIANO MIJAIL ORTEGA MUÑOZ","37297",IF(G35="GUSTAVO HUMBERTO VELAZCO GALVAN","VEGG9211019T1",IF(G35="JESUS AGUSTIN VELAZQUEZ FLORES","VEFJ900303M65",IF(G35="KARLA ESTEFANIA SALAZAR FLORES","SAFK9807277N1",IF(G35="ANGEL TERRAZAS MONROY","TEMA7105035N4")))))))))) -> 37675 | P35: =IF(G35="EFREN ABUNDEZ REYNA","PFAEP",IF(G35="LUIS ALEJANDRO HERNANDEZ REYNA","HERL850705AL2",IF(G35="ANA BEATRIZ ESTRADA ARGOTE","EAAA860701UP2",IF(G35="SERGIO ROMERO DURAN","RODS620908QAA",IF(G35="MARIELA OLMOS GAONA","RESICO",IF(G35="LUCIANO MIJAIL ORTEGA MUÑOZ","RIF",IF(G35="GUSTAVO HUMBERTO VELAZCO GALVAN","VEGG9211019T1",IF(G35="JESUS AGUSTIN VELAZQUEZ FLORES","VEFJ900303M65",IF(G35="KARLA ESTEFANIA SALAZAR FLORES","SAFK9807277N1",IF(G35="ANGEL TERRAZAS MONROY","TEMA7105035N4")))))))))) -> RESICO
A36: =IF(D36>0,MONTH(D36),0) -> 5 | B36: =VLOOKUP(A36,[1]Hoja3!$C$3:$D$14,2,FALSE) -> MAYO | C36: 45420 | D36: 45420 | G36: MARIELA OLMOS GAONA | H36: =IF(G36="EFREN ABUNDEZ REYNA","AURE7306187IA",IF(G36="LUIS ALEJANDRO HERNANDEZ REYNA","HERL850705AL2",IF(G36="ANA BEATRIZ ESTRADA ARGOTE","EAAA860701UP2",IF(G36="SERGIO ROMERO DURAN","RODS620908QAA",IF(G36="MARIELA OLMOS GAONA","OOGM010703NX1",IF(G36="LUCIANO MIJAIL ORTEGA MUÑOZ","OEML881105IK2",IF(G36="GUSTAVO HUMBERTO VELAZCO GALVAN","VEGG9211019T1",IF(G36="JESUS AGUSTIN VELAZQUEZ FLORES","VEFJ900303M65",IF(G36="KARLA ESTEFANIA SALAZAR FLORES","SAFK9807277N1",IF(G36="ANGEL TERRAZAS MONROY","TEMA7105035N4")))))))))) -> OOGM010703NX1 | I36: =+B36 -> MAYO | J36: 12950 | K36: 0 | N36: =+J36+K36-L36-M36 -> 12950 | O36: =IF(G36="EFREN ABUNDEZ REYNA","37295",IF(G36="LUIS ALEJANDRO HERNANDEZ REYNA","HERL850705AL2",IF(G36="ANA BEATRIZ ESTRADA ARGOTE","EAAA860701UP2",IF(G36="SERGIO ROMERO DURAN","RODS620908QAA",IF(G36="MARIELA OLMOS GAONA","37675",IF(G36="LUCIANO MIJAIL ORTEGA MUÑOZ","37297",IF(G36="GUSTAVO HUMBERTO VELAZCO GALVAN","VEGG9211019T1",IF(G36="JESUS AGUSTIN VELAZQUEZ FLORES","VEFJ900303M65",IF(G36="KARLA ESTEFANIA SALAZAR FLORES","SAFK9807277N1",IF(G36="ANGEL TERRAZAS MONROY","TEMA7105035N4")))))))))) -> 37675 | P36: =IF(G36="EFREN ABUNDEZ REYNA","PFAEP",IF(G36="LUIS ALEJANDRO HERNANDEZ REYNA","HERL850705AL2",IF(G36="ANA BEATRIZ ESTRADA ARGOTE","EAAA860701UP2",IF(G36="SERGIO ROMERO DURAN","RODS620908QAA",IF(G36="MARIELA OLMOS GAONA","RESICO",IF(G36="LUCIANO MIJAIL ORTEGA MUÑOZ","RIF",IF(G36="GUSTAVO HUMBERTO VELAZCO GALVAN","VEGG9211019T1",IF(G36="JESUS AGUSTIN VELAZQUEZ FLORES","VEFJ900303M65",IF(G36="KARLA ESTEFANIA SALAZAR FLORES","SAFK9807277N1",IF(G36="ANGEL TERRAZAS MONROY","TEMA7105035N4")))))))))) -> RESICO
A37: =IF(D37>0,MONTH(D37),0) -> 5 | B37: =VLOOKUP(A37,[1]Hoja3!$C$3:$D$14,2,FALSE) -> MAYO | C37: 45427 | D37: 45427 | G37: MARIELA OLMOS GAONA | H37: =IF(G37="EFREN ABUNDEZ REYNA","AURE7306187IA",IF(G37="LUIS ALEJANDRO HERNANDEZ REYNA","HERL850705AL2",IF(G37="ANA BEATRIZ ESTRADA ARGOTE","EAAA860701UP2",IF(G37="SERGIO ROMERO DURAN","RODS620908QAA",IF(G37="MARIELA OLMOS GAONA","OOGM010703NX1",IF(G37="LUCIANO MIJAIL ORTEGA MUÑOZ","OEML881105IK2",IF(G37="GUSTAVO HUMBERTO VELAZCO GALVAN","VEGG9211019T1",IF(G37="JESUS AGUSTIN VELAZQUEZ FLORES","VEFJ900303M65",IF(G37="KARLA ESTEFANIA SALAZAR FLORES","SAFK9807277N1",IF(G37="ANGEL TERRAZAS MONROY","TEMA7105035N4")))))))))) -> OOGM010703NX1 | I37: =+B37 -> MAYO | J37: 24207 | K37: 0 | N37: =+J37+K37-L37-M37 -> 24207 | O37: =IF(G37="EFREN ABUNDEZ REYNA","37295",IF(G37="LUIS ALEJANDRO HERNANDEZ REYNA","HERL850705AL2",IF(G37="ANA BEATRIZ ESTRADA ARGOTE","EAAA860701UP2",IF(G37="SERGIO ROMERO DURAN","RODS620908QAA",IF(G37="MARIELA OLMOS GAONA","37675",IF(G37="LUCIANO MIJAIL ORTEGA MUÑOZ","37297",IF(G37="GUSTAVO HUMBERTO VELAZCO GALVAN","VEGG9211019T1",IF(G37="JESUS AGUSTIN VELAZQUEZ FLORES","VEFJ900303M65",IF(G37="KARLA ESTEFANIA SALAZAR FLORES","SAFK9807277N1",IF(G37="ANGEL TERRAZAS MONROY","TEMA7105035N4")))))))))) -> 37675 | P37: =IF(G37="EFREN ABUNDEZ REYNA","PFAEP",IF(G37="LUIS ALEJANDRO HERNANDEZ REYNA","HERL850705AL2",IF(G37="ANA BEATRIZ ESTRADA ARGOTE","EAAA860701UP2",IF(G37="SERGIO ROMERO DURAN","RODS620908QAA",IF(G37="MARIELA OLMOS GAONA","RESICO",IF(G37="LUCIANO MIJAIL ORTEGA MUÑOZ","RIF",IF(G37="GUSTAVO HUMBERTO VELAZCO GALVAN","VEGG9211019T1",IF(G37="JESUS AGUSTIN VELAZQUEZ FLORES","VEFJ900303M65",IF(G37="KARLA ESTEFANIA SALAZAR FLORES","SAFK9807277N1",IF(G37="ANGEL TERRAZAS MONROY","TEMA7105035N4")))))))))) -> RESICO
A38: =IF(D38>0,MONTH(D38),0) -> 5 | B38: =VLOOKUP(A38,[1]Hoja3!$C$3:$D$14,2,FALSE) -> MAYO | C38: 45427 | D38: 45427 | G38: CONSTRUCCIONES INDUSTRIALES Y ARQUITECTONICAS DE OCOTLAN | H38: CIA991006EP9 | I38: =+B38 -> MAYO | J38: 1295.6897 | K38: =+J38*0.16 -> 207.31034 | N38: =+J38+K38-L38-M38 -> 1503 | O38: 47882 | P38: MORAL
A39: =IF(D39>0,MONTH(D39),0) -> 5 | B39: =VLOOKUP(A39,[1]Hoja3!$C$3:$D$14,2,FALSE) -> MAYO | C39: 45434 | D39: 45434 | G39: MARIELA OLMOS GAONA | H39: =IF(G39="EFREN ABUNDEZ REYNA","AURE7306187IA",IF(G39="LUIS ALEJANDRO HERNANDEZ REYNA","HERL850705AL2",IF(G39="ANA BEATRIZ ESTRADA ARGOTE","EAAA860701UP2",IF(G39="SERGIO ROMERO DURAN","RODS620908QAA",IF(G39="MARIELA OLMOS GAONA","OOGM010703NX1",IF(G39="LUCIANO MIJAIL ORTEGA MUÑOZ","OEML881105IK2",IF(G39="GUSTAVO HUMBERTO VELAZCO GALVAN","VEGG9211019T1",IF(G39="JESUS AGUSTIN VELAZQUEZ FLORES","VEFJ900303M65",IF(G39="KARLA ESTEFANIA SALAZAR FLORES","SAFK9807277N1",IF(G39="ANGEL TERRAZAS MONROY","TEMA7105035N4")))))))))) -> OOGM010703NX1 | I39: =+B39 -> MAYO | J39: 11918 | K39: 0 | N39: =+J39+K39-L39-M39 -> 11918 | O39: =IF(G39="EFREN ABUNDEZ REYNA","37295",IF(G39="LUIS ALEJANDRO HERNANDEZ REYNA","HERL850705AL2",IF(G39="ANA BEATRIZ ESTRADA ARGOTE","37530",IF(G39="SERGIO ROMERO DURAN","RODS620908QAA",IF(G39="MARIELA OLMOS GAONA","37675",IF(G39="LUCIANO MIJAIL ORTEGA MUÑOZ","37297",IF(G39="GUSTAVO HUMBERTO VELAZCO GALVAN","VEGG9211019T1",IF(G39="JESUS AGUSTIN VELAZQUEZ FLORES","VEFJ900303M65",IF(G39="KARLA ESTEFANIA SALAZAR FLORES","SAFK9807277N1",IF(G39="ANGEL TERRAZAS MONROY","TEMA7105035N4")))))))))) -> 37675 | P39: =IF(G39="EFREN ABUNDEZ REYNA","PFAEP",IF(G39="LUIS ALEJANDRO HERNANDEZ REYNA","HERL850705AL2",IF(G39="ANA BEATRIZ ESTRADA ARGOTE","RIF",IF(G39="SERGIO ROMERO DURAN","RODS620908QAA",IF(G39="MARIELA OLMOS GAONA","RESICO",IF(G39="LUCIANO MIJAIL ORTEGA MUÑOZ","RIF",IF(G39="GUSTAVO HUMBERTO VELAZCO GALVAN","VEGG9211019T1",IF(G39="JESUS AGUSTIN VELAZQUEZ FLORES","VEFJ900303M65",IF(G39="KARLA ESTEFANIA SALAZAR FLORES","SAFK9807277N1",IF(G39="ANGEL TERRAZAS MONROY","TEMA7105035N4")))))))))) -> RESICO
A40: =IF(D40>0,MONTH(D40),0) -> 6 | B40: =VLOOKUP(A40,[1]Hoja3!$C$3:$D$14,2,FALSE) -> JUNIO | C40: 45457 | D40: 45457 | G40: MARIELA OLMOS GAONA | H40: =IF(G40="EFREN ABUNDEZ REYNA","AURE7306187IA",IF(G40="LUIS ALEJANDRO HERNANDEZ REYNA","HERL850705AL2",IF(G40="ANA BEATRIZ ESTRADA ARGOTE","EAAA860701UP2",IF(G40="SERGIO ROMERO DURAN","RODS620908QAA",IF(G40="MARIELA OLMOS GAONA","OOGM010703NX1",IF(G40="LUCIANO MIJAIL ORTEGA MUÑOZ","OEML881105IK2",IF(G40="GUSTAVO HUMBERTO VELAZCO GALVAN","VEGG9211019T1",IF(G40="JESUS AGUSTIN VELAZQUEZ FLORES","VEFJ900303M65",IF(G40="KARLA ESTEFANIA SALAZAR FLORES","SAFK9807277N1",IF(G40="ANGEL TERRAZAS MONROY","TEMA7105035N4")))))))))) -> OOGM010703NX1 | I40: =+B40 -> JUNIO | J40: 6665 | K40: 0 | N40: =+J40+K40-L40-M40 -> 6665 | O40: =IF(G40="EFREN ABUNDEZ REYNA","37295",IF(G40="LUIS ALEJANDRO HERNANDEZ REYNA","HERL850705AL2",IF(G40="ANA BEATRIZ ESTRADA ARGOTE","37530",IF(G40="SERGIO ROMERO DURAN","RODS620908QAA",IF(G40="MARIELA OLMOS GAONA","37675",IF(G40="LUCIANO MIJAIL ORTEGA MUÑOZ","37297",IF(G40="GUSTAVO HUMBERTO VELAZCO GALVAN","VEGG9211019T1",IF(G40="JESUS AGUSTIN VELAZQUEZ FLORES","VEFJ900303M65",IF(G40="KARLA ESTEFANIA SALAZAR FLORES","SAFK9807277N1",IF(G40="ANGEL TERRAZAS MONROY","TEMA7105035N4")))))))))) -> 37675 | P40: =IF(G40="EFREN ABUNDEZ REYNA","PFAEP",IF(G40="LUIS ALEJANDRO HERNANDEZ REYNA","HERL850705AL2",IF(G40="ANA BEATRIZ ESTRADA ARGOTE","RIF",IF(G40="SERGIO ROMERO DURAN","RODS620908QAA",IF(G40="MARIELA OLMOS GAONA","RESICO",IF(G40="LUCIANO MIJAIL ORTEGA MUÑOZ","RIF",IF(G40="GUSTAVO HUMBERTO VELAZCO GALVAN","VEGG9211019T1",IF(G40="JESUS AGUSTIN VELAZQUEZ FLORES","VEFJ900303M65",IF(G40="KARLA ESTEFANIA SALAZAR FLORES","SAFK9807277N1",IF(G40="ANGEL TERRAZAS MONROY","TEMA7105035N4")))))))))) -> RESICO
A41: =IF(D41>0,MONTH(D41),0) -> 6 | B41: =VLOOKUP(A41,[1]Hoja3!$C$3:$D$14,2,FALSE) -> JUNIO | C41: 45457 | D41: 45457 | G41: MARIELA OLMOS GAONA | H41: =IF(G41="EFREN ABUNDEZ REYNA","AURE7306187IA",IF(G41="LUIS ALEJANDRO HERNANDEZ REYNA","HERL850705AL2",IF(G41="ANA BEATRIZ ESTRADA ARGOTE","EAAA860701UP2",IF(G41="SERGIO ROMERO DURAN","RODS620908QAA",IF(G41="MARIELA OLMOS GAONA","OOGM010703NX1",IF(G41="LUCIANO MIJAIL ORTEGA MUÑOZ","OEML881105IK2",IF(G41="GUSTAVO HUMBERTO VELAZCO GALVAN","VEGG9211019T1",IF(G41="JESUS AGUSTIN VELAZQUEZ FLORES","VEFJ900303M65",IF(G41="KARLA ESTEFANIA SALAZAR FLORES","SAFK9807277N1",IF(G41="ANGEL TERRAZAS MONROY","TEMA7105035N4")))))))))) -> OOGM010703NX1 | I41: =+B41 -> JUNIO | J41: 7775 | K41: 0 | N41: =+J41+K41-L41-M41 -> 7775 | O41: =IF(G41="EFREN ABUNDEZ REYNA","37295",IF(G41="LUIS ALEJANDRO HERNANDEZ REYNA","HERL850705AL2",IF(G41="ANA BEATRIZ ESTRADA ARGOTE","37530",IF(G41="SERGIO ROMERO DURAN","RODS620908QAA",IF(G41="MARIELA OLMOS GAONA","37675",IF(G41="LUCIANO MIJAIL ORTEGA MUÑOZ","37297",IF(G41="GUSTAVO HUMBERTO VELAZCO GALVAN","VEGG9211019T1",IF(G41="JESUS AGUSTIN VELAZQUEZ FLORES","VEFJ900303M65",IF(G41="KARLA ESTEFANIA SALAZAR FLORES","SAFK9807277N1",IF(G41="ANGEL TERRAZAS MONROY","TEMA7105035N4")))))))))) -> 37675 | P41: =IF(G41="EFREN ABUNDEZ REYNA","PFAEP",IF(G41="LUIS ALEJANDRO HERNANDEZ REYNA","HERL850705AL2",IF(G41="ANA BEATRIZ ESTRADA ARGOTE","RIF",IF(G41="SERGIO ROMERO DURAN","RODS620908QAA",IF(G41="MARIELA OLMOS GAONA","RESICO",IF(G41="LUCIANO MIJAIL ORTEGA MUÑOZ","RIF",IF(G41="GUSTAVO HUMBERTO VELAZCO GALVAN","VEGG9211019T1",IF(G41="JESUS AGUSTIN VELAZQUEZ FLORES","VEFJ900303M65",IF(G41="KARLA ESTEFANIA SALAZAR FLORES","SAFK9807277N1",IF(G41="ANGEL TERRAZAS MONROY","TEMA7105035N4")))))))))) -> RESICO
A42: =IF(D42>0,MONTH(D42),0) -> 6 | B42: =VLOOKUP(A42,[1]Hoja3!$C$3:$D$14,2,FALSE) -> JUNIO | C42: 45457 | D42: 45457 | G42: MARIELA OLMOS GAONA | H42: =IF(G42="EFREN ABUNDEZ REYNA","AURE7306187IA",IF(G42="LUIS ALEJANDRO HERNANDEZ REYNA","HERL850705AL2",IF(G42="ANA BEATRIZ ESTRADA ARGOTE","EAAA860701UP2",IF(G42="SERGIO ROMERO DURAN","RODS620908QAA",IF(G42="MARIELA OLMOS GAONA","OOGM010703NX1",IF(G42="LUCIANO MIJAIL ORTEGA MUÑOZ","OEML881105IK2",IF(G42="GUSTAVO HUMBERTO VELAZCO GALVAN","VEGG9211019T1",IF(G42="JESUS AGUSTIN VELAZQUEZ FLORES","VEFJ900303M65",IF(G42="KARLA ESTEFANIA SALAZAR FLORES","SAFK9807277N1",IF(G42="ANGEL TERRAZAS MONROY","TEMA7105035N4")))))))))) -> OOGM010703NX1 | I42: =+B42 -> JUNIO | J42: 9677 | K42: 0 | N42: =+J42+K42-L42-M42 -> 9677 | O42: =IF(G42="EFREN ABUNDEZ REYNA","37295",IF(G42="LUIS ALEJANDRO HERNANDEZ REYNA","HERL850705AL2",IF(G42="ANA BEATRIZ ESTRADA ARGOTE","37530",IF(G42="SERGIO ROMERO DURAN","RODS620908QAA",IF(G42="MARIELA OLMOS GAONA","37675",IF(G42="LUCIANO MIJAIL ORTEGA MUÑOZ","37297",IF(G42="GUSTAVO HUMBERTO VELAZCO GALVAN","VEGG9211019T1",IF(G42="JESUS AGUSTIN VELAZQUEZ FLORES","VEFJ900303M65",IF(G42="KARLA ESTEFANIA SALAZAR FLORES","SAFK9807277N1",IF(G42="ANGEL TERRAZAS MONROY","TEMA7105035N4")))))))))) -> 37675 | P42: =IF(G42="EFREN ABUNDEZ REYNA","PFAEP",IF(G42="LUIS ALEJANDRO HERNANDEZ REYNA","HERL850705AL2",IF(G42="ANA BEATRIZ ESTRADA ARGOTE","RIF",IF(G42="SERGIO ROMERO DURAN","RODS620908QAA",IF(G42="MARIELA OLMOS GAONA","RESICO",IF(G42="LUCIANO MIJAIL ORTEGA MUÑOZ","RIF",IF(G42="GUSTAVO HUMBERTO VELAZCO GALVAN","VEGG9211019T1",IF(G42="JESUS AGUSTIN VELAZQUEZ FLORES","VEFJ900303M65",IF(G42="KARLA ESTEFANIA SALAZAR FLORES","SAFK9807277N1",IF(G42="ANGEL TERRAZAS MONROY","TEMA7105035N4")))))))))) -> RESICO
A43: =IF(D43>0,MONTH(D43),0) -> 7 | B43: =VLOOKUP(A43,[1]Hoja3!$C$3:$D$14,2,FALSE) -> JULIO | C43: 45474 | D43: 45474 | G43: APOLLO VTS MEXICO | H43: AVM230707SJ9 | I43: =+B43 -> JULIO | J43: 418.10345 | K43: =+J43*0.16 -> 66.896552 | N43: =+J43+K43-L43-M43 -> 485 | O43: 72830 | P43: MORAL | Q43: adrian.yescasg@gmail.com
A44: =IF(D44>0,MONTH(D44),0) -> 7 | B44: =VLOOKUP(A44,[1]Hoja3!$C$3:$D$14,2,FALSE) -> JULIO | C44: 45474 | D44: 45474 | G44: MARIELA OLMOS GAONA | H44: =IF(G44="EFREN ABUNDEZ REYNA","AURE7306187IA",IF(G44="LUIS ALEJANDRO HERNANDEZ REYNA","HERL850705AL2",IF(G44="ANA BEATRIZ ESTRADA ARGOTE","EAAA860701UP2",IF(G44="SERGIO ROMERO DURAN","RODS620908QAA",IF(G44="MARIELA OLMOS GAONA","OOGM010703NX1",IF(G44="LUCIANO MIJAIL ORTEGA MUÑOZ","OEML881105IK2",IF(G44="GUSTAVO HUMBERTO VELAZCO GALVAN","VEGG9211019T1",IF(G44="JESUS AGUSTIN VELAZQUEZ FLORES","VEFJ900303M65",IF(G44="KARLA ESTEFANIA SALAZAR FLORES","SAFK9807277N1",IF(G44="ANGEL TERRAZAS MONROY","TEMA7105035N4")))))))))) -> OOGM010703NX1 | I44: =+B44 -> JULIO | J44: 11485 | K44: 0 | N44: =+J44+K44-L44-M44 -> 11485 | O44: =IF(G44="EFREN ABUNDEZ REYNA","37295",IF(G44="LUIS ALEJANDRO HERNANDEZ REYNA","HERL850705AL2",IF(G44="ANA BEATRIZ ESTRADA ARGOTE","37530",IF(G44="SERGIO ROMERO DURAN","RODS620908QAA",IF(G44="MARIELA OLMOS GAONA","37675",IF(G44="LUCIANO MIJAIL ORTEGA MUÑOZ","37297",IF(G44="GUSTAVO HUMBERTO VELAZCO GALVAN","VEGG9211019T1",IF(G44="JESUS AGUSTIN VELAZQUEZ FLORES","VEFJ900303M65",IF(G44="KARLA ESTEFANIA SALAZAR FLORES","SAFK9807277N1",IF(G44="ANGEL TERRAZAS MONROY","TEMA7105035N4")))))))))) -> 37675 | P44: =IF(G44="EFREN ABUNDEZ REYNA","PFAEP",IF(G44="LUIS ALEJANDRO HERNANDEZ REYNA","HERL850705AL2",IF(G44="ANA BEATRIZ ESTRADA ARGOTE","RIF",IF(G44="SERGIO ROMERO DURAN","RODS620908QAA",IF(G44="MARIELA OLMOS GAONA","RESICO",IF(G44="LUCIANO MIJAIL ORTEGA MUÑOZ","RIF",IF(G44="GUSTAVO HUMBERTO VELAZCO GALVAN","VEGG9211019T1",IF(G44="JESUS AGUSTIN VELAZQUEZ FLORES","VEFJ900303M65",IF(G44="KARLA ESTEFANIA SALAZAR FLORES","SAFK9807277N1",IF(G44="ANGEL TERRAZAS MONROY","TEMA7105035N4")))))))))) -> RESICO
A45: =IF(D45>0,MONTH(D45),0) -> 7 | B45: =VLOOKUP(A45,[1]Hoja3!$C$3:$D$14,2,FALSE) -> JULIO | C45: 45477 | D45: 45477 | G45: MARIELA OLMOS GAONA | H45: =IF(G45="EFREN ABUNDEZ REYNA","AURE7306187IA",IF(G45="LUIS ALEJANDRO HERNANDEZ REYNA","HERL850705AL2",IF(G45="ANA BEATRIZ ESTRADA ARGOTE","EAAA860701UP2",IF(G45="SERGIO ROMERO DURAN","RODS620908QAA",IF(G45="MARIELA OLMOS GAONA","OOGM010703NX1",IF(G45="LUCIANO MIJAIL ORTEGA MUÑOZ","OEML881105IK2",IF(G45="GUSTAVO HUMBERTO VELAZCO GALVAN","VEGG9211019T1",IF(G45="JESUS AGUSTIN VELAZQUEZ FLORES","VEFJ900303M65",IF(G45="KARLA ESTEFANIA SALAZAR FLORES","SAFK9807277N1",IF(G45="ANGEL TERRAZAS MONROY","TEMA7105035N4")))))))))) -> OOGM010703NX1 | I45: =+B45 -> JULIO | J45: 5487 | K45: 0 | N45: =+J45+K45-L45-M45 -> 5487 | O45: =IF(G45="EFREN ABUNDEZ REYNA","37295",IF(G45="LUIS ALEJANDRO HERNANDEZ REYNA","HERL850705AL2",IF(G45="ANA BEATRIZ ESTRADA ARGOTE","37530",IF(G45="SERGIO ROMERO DURAN","RODS620908QAA",IF(G45="MARIELA OLMOS GAONA","37675",IF(G45="LUCIANO MIJAIL ORTEGA MUÑOZ","37297",IF(G45="GUSTAVO HUMBERTO VELAZCO GALVAN","VEGG9211019T1",IF(G45="JESUS AGUSTIN VELAZQUEZ FLORES","VEFJ900303M65",IF(G45="KARLA ESTEFANIA SALAZAR FLORES","SAFK9807277N1",IF(G45="ANGEL TERRAZAS MONROY","TEMA7105035N4")))))))))) -> 37675 | P45: =IF(G45="EFREN ABUNDEZ REYNA","PFAEP",IF(G45="LUIS ALEJANDRO HERNANDEZ REYNA","HERL850705AL2",IF(G45="ANA BEATRIZ ESTRADA ARGOTE","RIF",IF(G45="SERGIO ROMERO DURAN","RODS620908QAA",IF(G45="MARIELA OLMOS GAONA","RESICO",IF(G45="LUCIANO MIJAIL ORTEGA MUÑOZ","RIF",IF(G45="GUSTAVO HUMBERTO VELAZCO GALVAN","VEGG9211019T1",IF(G45="JESUS AGUSTIN VELAZQUEZ FLORES","VEFJ900303M65",IF(G45="KARLA ESTEFANIA SALAZAR FLORES","SAFK9807277N1",IF(G45="ANGEL TERRAZAS MONROY","TEMA7105035N4")))))))))) -> RESICO
A46: =IF(D46>0,MONTH(D46),0) -> 7 | B46: =VLOOKUP(A46,[1]Hoja3!$C$3:$D$14,2,FALSE) -> JULIO | C46: 45498 | D46: 45498 | G46: MARIELA OLMOS GAONA | H46: =IF(G46="EFREN ABUNDEZ REYNA","AURE7306187IA",IF(G46="LUIS ALEJANDRO HERNANDEZ REYNA","HERL850705AL2",IF(G46="ANA BEATRIZ ESTRADA ARGOTE","EAAA860701UP2",IF(G46="SERGIO ROMERO DURAN","RODS620908QAA",IF(G46="MARIELA OLMOS GAONA","OOGM010703NX1",IF(G46="LUCIANO MIJAIL ORTEGA MUÑOZ","OEML881105IK2",IF(G46="GUSTAVO HUMBERTO VELAZCO GALVAN","VEGG9211019T1",IF(G46="JESUS AGUSTIN VELAZQUEZ FLORES","VEFJ900303M65",IF(G46="KARLA ESTEFANIA SALAZAR FLORES","SAFK9807277N1",IF(G46="ANGEL TERRAZAS MONROY","TEMA7105035N4")))))))))) -> OOGM010703NX1 | I46: =+B46 -> JULIO | J46: 8782 | K46: 0 | N46: =+J46+K46-L46-M46 -> 8782 | O46: =IF(G46="EFREN ABUNDEZ REYNA","37295",IF(G46="LUIS ALEJANDRO HERNANDEZ REYNA","HERL850705AL2",IF(G46="ANA BEATRIZ ESTRADA ARGOTE","37530",IF(G46="SERGIO ROMERO DURAN","RODS620908QAA",IF(G46="MARIELA OLMOS GAONA","37675",IF(G46="LUCIANO MIJAIL ORTEGA MUÑOZ","37297",IF(G46="GUSTAVO HUMBERTO VELAZCO GALVAN","VEGG9211019T1",IF(G46="JESUS AGUSTIN VELAZQUEZ FLORES","VEFJ900303M65",IF(G46="KARLA ESTEFANIA SALAZAR FLORES","SAFK9807277N1",IF(G46="ANGEL TERRAZAS MONROY","TEMA7105035N4")))))))))) -> 37675 | P46: =IF(G46="EFREN ABUNDEZ REYNA","PFAEP",IF(G46="LUIS ALEJANDRO HERNANDEZ REYNA","HERL850705AL2",IF(G46="ANA BEATRIZ ESTRADA ARGOTE","RIF",IF(G46="SERGIO ROMERO DURAN","RODS620908QAA",IF(G46="MARIELA OLMOS GAONA","RESICO",IF(G46="LUCIANO MIJAIL ORTEGA MUÑOZ","RIF",IF(G46="GUSTAVO HUMBERTO VELAZCO GALVAN","VEGG9211019T1",IF(G46="JESUS AGUSTIN VELAZQUEZ FLORES","VEFJ900303M65",IF(G46="KARLA ESTEFANIA SALAZAR FLORES","SAFK9807277N1",IF(G46="ANGEL TERRAZAS MONROY","TEMA7105035N4")))))))))) -> RESICO
A47: =IF(D47>0,MONTH(D47),0) -> 7 | B47: =VLOOKUP(A47,[1]Hoja3!$C$3:$D$14,2,FALSE) -> JULIO | C47: 45498 | D47: 45498 | G47: MARIELA OLMOS GAONA | H47: =IF(G47="EFREN ABUNDEZ REYNA","AURE7306187IA",IF(G47="LUIS ALEJANDRO HERNANDEZ REYNA","HERL850705AL2",IF(G47="ANA BEATRIZ ESTRADA ARGOTE","EAAA860701UP2",IF(G47="SERGIO ROMERO DURAN","RODS620908QAA",IF(G47="MARIELA OLMOS GAONA","OOGM010703NX1",IF(G47="LUCIANO MIJAIL ORTEGA MUÑOZ","OEML881105IK2",IF(G47="GUSTAVO HUMBERTO VELAZCO GALVAN","VEGG9211019T1",IF(G47="JESUS AGUSTIN VELAZQUEZ FLORES","VEFJ900303M65",IF(G47="KARLA ESTEFANIA SALAZAR FLORES","SAFK9807277N1",IF(G47="ANGEL TERRAZAS MONROY","TEMA7105035N4")))))))))) -> OOGM010703NX1 | I47: =+B47 -> JULIO | J47: 8408 | K47: 0 | N47: =+J47+K47-L47-M47 -> 8408 | O47: =IF(G47="EFREN ABUNDEZ REYNA","37295",IF(G47="LUIS ALEJANDRO HERNANDEZ REYNA","HERL850705AL2",IF(G47="ANA BEATRIZ ESTRADA ARGOTE","37530",IF(G47="SERGIO ROMERO DURAN","RODS620908QAA",IF(G47="MARIELA OLMOS GAONA","37675",IF(G47="LUCIANO MIJAIL ORTEGA MUÑOZ","37297",IF(G47="GUSTAVO HUMBERTO VELAZCO GALVAN","VEGG9211019T1",IF(G47="JESUS AGUSTIN VELAZQUEZ FLORES","VEFJ900303M65",IF(G47="KARLA ESTEFANIA SALAZAR FLORES","SAFK9807277N1",IF(G47="ANGEL TERRAZAS MONROY","TEMA7105035N4")))))))))) -> 37675 | P47: =IF(G47="EFREN ABUNDEZ REYNA","PFAEP",IF(G47="LUIS ALEJANDRO HERNANDEZ REYNA","HERL850705AL2",IF(G47="ANA BEATRIZ ESTRADA ARGOTE","RIF",IF(G47="SERGIO ROMERO DURAN","RODS620908QAA",IF(G47="MARIELA OLMOS GAONA","RESICO",IF(G47="LUCIANO MIJAIL ORTEGA MUÑOZ","RIF",IF(G47="GUSTAVO HUMBERTO VELAZCO GALVAN","VEGG9211019T1",IF(G47="JESUS AGUSTIN VELAZQUEZ FLORES","VEFJ900303M65",IF(G47="KARLA ESTEFANIA SALAZAR FLORES","SAFK9807277N1",IF(G47="ANGEL TERRAZAS MONROY","TEMA7105035N4")))))))))) -> RESICO
A48: =IF(D48>0,MONTH(D48),0) -> 7 | B48: =VLOOKUP(A48,[1]Hoja3!$C$3:$D$14,2,FALSE) -> JULIO | C48: 45498 | D48: 45498 | G48: MARIELA OLMOS GAONA | H48: =IF(G48="EFREN ABUNDEZ REYNA","AURE7306187IA",IF(G48="LUIS ALEJANDRO HERNANDEZ REYNA","HERL850705AL2",IF(G48="ANA BEATRIZ ESTRADA ARGOTE","EAAA860701UP2",IF(G48="SERGIO ROMERO DURAN","RODS620908QAA",IF(G48="MARIELA OLMOS GAONA","OOGM010703NX1",IF(G48="LUCIANO MIJAIL ORTEGA MUÑOZ","OEML881105IK2",IF(G48="GUSTAVO HUMBERTO VELAZCO GALVAN","VEGG9211019T1",IF(G48="JESUS AGUSTIN VELAZQUEZ FLORES","VEFJ900303M65",IF(G48="KARLA ESTEFANIA SALAZAR FLORES","SAFK9807277N1",IF(G48="ANGEL TERRAZAS MONROY","TEMA7105035N4")))))))))) -> OOGM010703NX1 | I48: =+B48 -> JULIO | J48: 8862 | K48: 0 | N48: =+J48+K48-L48-M48 -> 8862 | O48: =IF(G48="EFREN ABUNDEZ REYNA","37295",IF(G48="LUIS ALEJANDRO HERNANDEZ REYNA","HERL850705AL2",IF(G48="ANA BEATRIZ ESTRADA ARGOTE","37530",IF(G48="SERGIO ROMERO DURAN","RODS620908QAA",IF(G48="MARIELA OLMOS GAONA","37675",IF(G48="LUCIANO MIJAIL ORTEGA MUÑOZ","37297",IF(G48="GUSTAVO HUMBERTO VELAZCO GALVAN","VEGG9211019T1",IF(G48="JESUS AGUSTIN VELAZQUEZ FLORES","VEFJ900303M65",IF(G48="KARLA ESTEFANIA SALAZAR FLORES","SAFK9807277N1",IF(G48="ANGEL TERRAZAS MONROY","TEMA7105035N4")))))))))) -> 37675 | P48: =IF(G48="EFREN ABUNDEZ REYNA","PFAEP",IF(G48="LUIS ALEJANDRO HERNANDEZ REYNA","HERL850705AL2",IF(G48="ANA BEATRIZ ESTRADA ARGOTE","RIF",IF(G48="SERGIO ROMERO DURAN","RODS620908QAA",IF(G48="MARIELA OLMOS GAONA","RESICO",IF(G48="LUCIANO MIJAIL ORTEGA MUÑOZ","RIF",IF(G48="GUSTAVO HUMBERTO VELAZCO GALVAN","VEGG9211019T1",IF(G48="JESUS AGUSTIN VELAZQUEZ FLORES","VEFJ900303M65",IF(G48="KARLA ESTEFANIA SALAZAR FLORES","SAFK9807277N1",IF(G48="ANGEL TERRAZAS MONROY","TEMA7105035N4")))))))))) -> RESICO
A49: =IF(D49>0,MONTH(D49),0) -> 7 | B49: =VLOOKUP(A49,[1]Hoja3!$C$3:$D$14,2,FALSE) -> JULIO | C49: 45504 | D49: 45504 | G49: MARIELA OLMOS GAONA | H49: =IF(G49="EFREN ABUNDEZ REYNA","AURE7306187IA",IF(G49="LUIS ALEJANDRO HERNANDEZ REYNA","HERL850705AL2",IF(G49="ANA BEATRIZ ESTRADA ARGOTE","EAAA860701UP2",IF(G49="SERGIO ROMERO DURAN","RODS620908QAA",IF(G49="MARIELA OLMOS GAONA","OOGM010703NX1",IF(G49="LUCIANO MIJAIL ORTEGA MUÑOZ","OEML881105IK2",IF(G49="GUSTAVO HUMBERTO VELAZCO GALVAN","VEGG9211019T1",IF(G49="JESUS AGUSTIN VELAZQUEZ FLORES","VEFJ900303M65",IF(G49="KARLA ESTEFANIA SALAZAR FLORES","SAFK9807277N1",IF(G49="ANGEL TERRAZAS MONROY","TEMA7105035N4")))))))))) -> OOGM010703NX1 | I49: =+B49 -> JULIO | J49: 15300 | K49: 0 | N49: =+J49+K49-L49-M49 -> 15300 | O49: =IF(G49="EFREN ABUNDEZ REYNA","37295",IF(G49="LUIS ALEJANDRO HERNANDEZ REYNA","HERL850705AL2",IF(G49="ANA BEATRIZ ESTRADA ARGOTE","37530",IF(G49="SERGIO ROMERO DURAN","RODS620908QAA",IF(G49="MARIELA OLMOS GAONA","37675",IF(G49="LUCIANO MIJAIL ORTEGA MUÑOZ","37297",IF(G49="GUSTAVO HUMBERTO VELAZCO GALVAN","VEGG9211019T1",IF(G49="JESUS AGUSTIN VELAZQUEZ FLORES","VEFJ900303M65",IF(G49="KARLA ESTEFANIA SALAZAR FLORES","SAFK9807277N1",IF(G49="ANGEL TERRAZAS MONROY","TEMA7105035N4")))))))))) -> 37675 | P49: =IF(G49="EFREN ABUNDEZ REYNA","PFAEP",IF(G49="LUIS ALEJANDRO HERNANDEZ REYNA","HERL850705AL2",IF(G49="ANA BEATRIZ ESTRADA ARGOTE","RIF",IF(G49="SERGIO ROMERO DURAN","RODS620908QAA",IF(G49="MARIELA OLMOS GAONA","RESICO",IF(G49="LUCIANO MIJAIL ORTEGA MUÑOZ","RIF",IF(G49="GUSTAVO HUMBERTO VELAZCO GALVAN","VEGG9211019T1",IF(G49="JESUS AGUSTIN VELAZQUEZ FLORES","VEFJ900303M65",IF(G49="KARLA ESTEFANIA SALAZAR FLORES","SAFK9807277N1",IF(G49="ANGEL TERRAZAS MONROY","TEMA7105035N4")))))))))) -> RESICO
A50: =IF(D50>0,MONTH(D50),0) -> 4 | B50: =VLOOKUP(A50,[1]Hoja3!$C$3:$D$14,2,FALSE) -> ABRIL | C50: 45412 | D50: 45412 | G50: PUBLICO EN GENERAL | H50: =IF(G50="EFREN ABUNDEZ REYNA","AURE7306187IA",IF(G50="LUIS ALEJANDRO HERNANDEZ REYNA","HERL850705AL2",IF(G50="ANA BEATRIZ ESTRADA ARGOTE","EAAA860701UP2",IF(G50="SERGIO ROMERO DURAN","RODS620908QAA",IF(G50="MARIELA OLMOS GAONA","OOGM010703NX1",IF(G50="LUCIANO MIJAIL ORTEGA MUÑOZ","OEML881105IK2",IF(G50="GUSTAVO HUMBERTO VELAZCO GALVAN","VEGG9211019T1",IF(G50="JESUS AGUSTIN VELAZQUEZ FLORES","VEFJ900303M65",IF(G50="KARLA ESTEFANIA SALAZAR FLORES","SAFK9807277N1",IF(G50="ANGEL TERRAZAS MONROY","TEMA7105035N4")))))))))) -> FALSE | I50: =+B50 -> ABRIL | J50: 356234 | K50: 0 | N50: =+J50+K50-L50-M50 -> 356234 | O50: =IF(G50="EFREN ABUNDEZ REYNA","37295",IF(G50="LUIS ALEJANDRO HERNANDEZ REYNA","HERL850705AL2",IF(G50="ANA BEATRIZ ESTRADA ARGOTE","37530",IF(G50="SERGIO ROMERO DURAN","RODS620908QAA",IF(G50="MARIELA OLMOS GAONA","37675",IF(G50="LUCIANO MIJAIL ORTEGA MUÑOZ","37297",IF(G50="GUSTAVO HUMBERTO VELAZCO GALVAN","VEGG9211019T1",IF(G50="JESUS AGUSTIN VELAZQUEZ FLORES","VEFJ900303M65",IF(G50="KARLA ESTEFANIA SALAZAR FLORES","SAFK9807277N1",IF(G50="ANGEL TERRAZAS MONROY","TEMA7105035N4")))))))))) -> FALSE | P50: =IF(G50="EFREN ABUNDEZ REYNA","PFAEP",IF(G50="LUIS ALEJANDRO HERNANDEZ REYNA","HERL850705AL2",IF(G50="ANA BEATRIZ ESTRADA ARGOTE","RIF",IF(G50="SERGIO ROMERO DURAN","RODS620908QAA",IF(G50="MARIELA OLMOS GAONA","RESICO",IF(G50="LUCIANO MIJAIL ORTEGA MUÑOZ","RIF",IF(G50="GUSTAVO HUMBERTO VELAZCO GALVAN","VEGG9211019T1",IF(G50="JESUS AGUSTIN VELAZQUEZ FLORES","VEFJ900303M65",IF(G50="KARLA ESTEFANIA SALAZAR FLORES","SAFK9807277N1",IF(G50="ANGEL TERRAZAS MONROY","TEMA7105035N4")))))))))) -> FALSE
A51: =IF(D51>0,MONTH(D51),0) -> 5 | B51: =VLOOKUP(A51,[1]Hoja3!$C$3:$D$14,2,FALSE) -> MAYO | C51: 45442 | D51: 45442 | G51: PUBLICO EN GENERAL | H51: =IF(G51="EFREN ABUNDEZ REYNA","AURE7306187IA",IF(G51="LUIS ALEJANDRO HERNANDEZ REYNA","HERL850705AL2",IF(G51="ANA BEATRIZ ESTRADA ARGOTE","EAAA860701UP2",IF(G51="SERGIO ROMERO DURAN","RODS620908QAA",IF(G51="MARIELA OLMOS GAONA","OOGM010703NX1",IF(G51="LUCIANO MIJAIL ORTEGA MUÑOZ","OEML881105IK2",IF(G51="GUSTAVO HUMBERTO VELAZCO GALVAN","VEGG9211019T1",IF(G51="JESUS AGUSTIN VELAZQUEZ FLORES","VEFJ900303M65",IF(G51="KARLA ESTEFANIA SALAZAR FLORES","SAFK9807277N1",IF(G51="ANGEL TERRAZAS MONROY","TEMA7105035N4")))))))))) -> FALSE | I51: =+B51 -> MAYO | J51: 304823 | K51: 0 | N51: =+J51+K51-L51-M51 -> 304823 | O51: =IF(G51="EFREN ABUNDEZ REYNA","37295",IF(G51="LUIS ALEJANDRO HERNANDEZ REYNA","HERL850705AL2",IF(G51="ANA BEATRIZ ESTRADA ARGOTE","37530",IF(G51="SERGIO ROMERO DURAN","RODS620908QAA",IF(G51="MARIELA OLMOS GAONA","37675",IF(G51="LUCIANO MIJAIL ORTEGA MUÑOZ","37297",IF(G51="GUSTAVO HUMBERTO VELAZCO GALVAN","VEGG9211019T1",IF(G51="JESUS AGUSTIN VELAZQUEZ FLORES","VEFJ900303M65",IF(G51="KARLA ESTEFANIA SALAZAR FLORES","SAFK9807277N1",IF(G51="ANGEL TERRAZAS MONROY","TEMA7105035N4")))))))))) -> FALSE | P51: =IF(G51="EFREN ABUNDEZ REYNA","PFAEP",IF(G51="LUIS ALEJANDRO HERNANDEZ REYNA","HERL850705AL2",IF(G51="ANA BEATRIZ ESTRADA ARGOTE","RIF",IF(G51="SERGIO ROMERO DURAN","RODS620908QAA",IF(G51="MARIELA OLMOS GAONA","RESICO",IF(G51="LUCIANO MIJAIL ORTEGA MUÑOZ","RIF",IF(G51="GUSTAVO HUMBERTO VELAZCO GALVAN","VEGG9211019T1",IF(G51="JESUS AGUSTIN VELAZQUEZ FLORES","VEFJ900303M65",IF(G51="KARLA ESTEFANIA SALAZAR FLORES","SAFK9807277N1",IF(G51="ANGEL TERRAZAS MONROY","TEMA7105035N4")))))))))) -> FALSE
A52: =IF(D52>0,MONTH(D52),0) -> 6 | B52: =VLOOKUP(A52,[1]Hoja3!$C$3:$D$14,2,FALSE) -> JUNIO | C52: 45473 | D52: 45473 | G52: PUBLICO EN GENERAL | H52: =IF(G52="EFREN ABUNDEZ REYNA","AURE7306187IA",IF(G52="LUIS ALEJANDRO HERNANDEZ REYNA","HERL850705AL2",IF(G52="ANA BEATRIZ ESTRADA ARGOTE","EAAA860701UP2",IF(G52="SERGIO ROMERO DURAN","RODS620908QAA",IF(G52="MARIELA OLMOS GAONA","OOGM010703NX1",IF(G52="LUCIANO MIJAIL ORTEGA MUÑOZ","OEML881105IK2",IF(G52="GUSTAVO HUMBERTO VELAZCO GALVAN","VEGG9211019T1",IF(G52="JESUS AGUSTIN VELAZQUEZ FLORES","VEFJ900303M65",IF(G52="KARLA ESTEFANIA SALAZAR FLORES","SAFK9807277N1",IF(G52="ANGEL TERRAZAS MONROY","TEMA7105035N4")))))))))) -> FALSE | I52: =+B52 -> JUNIO | J52: 400589 | K52: 0 | N52: =+J52+K52-L52-M52 -> 400589 | O52: =IF(G52="EFREN ABUNDEZ REYNA","37295",IF(G52="LUIS ALEJANDRO HERNANDEZ REYNA","HERL850705AL2",IF(G52="ANA BEATRIZ ESTRADA ARGOTE","37530",IF(G52="SERGIO ROMERO DURAN","RODS620908QAA",IF(G52="MARIELA OLMOS GAONA","37675",IF(G52="LUCIANO MIJAIL ORTEGA MUÑOZ","37297",IF(G52="GUSTAVO HUMBERTO VELAZCO GALVAN","VEGG9211019T1",IF(G52="JESUS AGUSTIN VELAZQUEZ FLORES","VEFJ900303M65",IF(G52="KARLA ESTEFANIA SALAZAR FLORES","SAFK9807277N1",IF(G52="ANGEL TERRAZAS MONROY","TEMA7105035N4")))))))))) -> FALSE | P52: =IF(G52="EFREN ABUNDEZ REYNA","PFAEP",IF(G52="LUIS ALEJANDRO HERNANDEZ REYNA","HERL850705AL2",IF(G52="ANA BEATRIZ ESTRADA ARGOTE","RIF",IF(G52="SERGIO ROMERO DURAN","RODS620908QAA",IF(G52="MARIELA OLMOS GAONA","RESICO",IF(G52="LUCIANO MIJAIL ORTEGA MUÑOZ","RIF",IF(G52="GUSTAVO HUMBERTO VELAZCO GALVAN","VEGG9211019T1",IF(G52="JESUS AGUSTIN VELAZQUEZ FLORES","VEFJ900303M65",IF(G52="KARLA ESTEFANIA SALAZAR FLORES","SAFK9807277N1",IF(G52="ANGEL TERRAZAS MONROY","TEMA7105035N4")))))))))) -> FALSE
A53: =IF(D53>0,MONTH(D53),0) -> 7 | B53: =VLOOKUP(A53,[1]Hoja3!$C$3:$D$14,2,FALSE) -> JULIO | C53: 45504 | D53: 45504 | G53: PUBLICO EN GENERAL | H53: =IF(G53="EFREN ABUNDEZ REYNA","AURE7306187IA",IF(G53="LUIS ALEJANDRO HERNANDEZ REYNA","HERL850705AL2",IF(G53="ANA BEATRIZ ESTRADA ARGOTE","EAAA860701UP2",IF(G53="SERGIO ROMERO DURAN","RODS620908QAA",IF(G53="MARIELA OLMOS GAONA","OOGM010703NX1",IF(G53="LUCIANO MIJAIL ORTEGA MUÑOZ","OEML881105IK2",IF(G53="GUSTAVO HUMBERTO VELAZCO GALVAN","VEGG9211019T1",IF(G53="JESUS AGUSTIN VELAZQUEZ FLORES","VEFJ900303M65",IF(G53="KARLA ESTEFANIA SALAZAR FLORES","SAFK9807277N1",IF(G53="ANGEL TERRAZAS MONROY","TEMA7105035N4")))))))))) -> FALSE | I53: =+B53 -> JULIO | J53: 213654 | K53: 0 | N53: =+J53+K53-L53-M53 -> 213654 | O53: =IF(G53="EFREN ABUNDEZ REYNA","37295",IF(G53="LUIS ALEJANDRO HERNANDEZ REYNA","HERL850705AL2",IF(G53="ANA BEATRIZ ESTRADA ARGOTE","37530",IF(G53="SERGIO ROMERO DURAN","RODS620908QAA",IF(G53="MARIELA OLMOS GAONA","37675",IF(G53="LUCIANO MIJAIL ORTEGA MUÑOZ","37297",IF(G53="GUSTAVO HUMBERTO VELAZCO GALVAN","VEGG9211019T1",IF(G53="JESUS AGUSTIN VELAZQUEZ FLORES","VEFJ900303M65",IF(G53="KARLA ESTEFANIA SALAZAR FLORES","SAFK9807277N1",IF(G53="ANGEL TERRAZAS MONROY","TEMA7105035N4")))))))))) -> FALSE | P53: =IF(G53="EFREN ABUNDEZ REYNA","PFAEP",IF(G53="LUIS ALEJANDRO HERNANDEZ REYNA","HERL850705AL2",IF(G53="ANA BEATRIZ ESTRADA ARGOTE","RIF",IF(G53="SERGIO ROMERO DURAN","RODS620908QAA",IF(G53="MARIELA OLMOS GAONA","RESICO",IF(G53="LUCIANO MIJAIL ORTEGA MUÑOZ","RIF",IF(G53="GUSTAVO HUMBERTO VELAZCO GALVAN","VEGG9211019T1",IF(G53="JESUS AGUSTIN VELAZQUEZ FLORES","VEFJ900303M65",IF(G53="KARLA ESTEFANIA SALAZAR FLORES","SAFK9807277N1",IF(G53="ANGEL TERRAZAS MONROY","TEMA7105035N4")))))))))) -> FALSE
A54: =IF(D54>0,MONTH(D54),0) -> 8 | B54: =VLOOKUP(A54,[1]Hoja3!$C$3:$D$14,2,FALSE) -> AGOSTO | C54: 45524 | D54: 45524 | G54: MARIELA OLMOS GAONA | H54: =IF(G54="EFREN ABUNDEZ REYNA","AURE7306187IA",IF(G54="LUIS ALEJANDRO HERNANDEZ REYNA","HERL850705AL2",IF(G54="ANA BEATRIZ ESTRADA ARGOTE","EAAA860701UP2",IF(G54="SERGIO ROMERO DURAN","RODS620908QAA",IF(G54="MARIELA OLMOS GAONA","OOGM010703NX1",IF(G54="LUCIANO MIJAIL ORTEGA MUÑOZ","OEML881105IK2",IF(G54="GUSTAVO HUMBERTO VELAZCO GALVAN","VEGG9211019T1",IF(G54="JESUS AGUSTIN VELAZQUEZ FLORES","VEFJ900303M65",IF(G54="KARLA ESTEFANIA SALAZAR FLORES","SAFK9807277N1",IF(G54="ANGEL TERRAZAS MONROY","TEMA7105035N4")))))))))) -> OOGM010703NX1 | I54: =+B54 -> AGOSTO | J54: 11271 | K54: 0 | N54: =+J54+K54-L54-M54 -> 11271 | O54: =IF(G54="EFREN ABUNDEZ REYNA","37295",IF(G54="LUIS ALEJANDRO HERNANDEZ REYNA","HERL850705AL2",IF(G54="ANA BEATRIZ ESTRADA ARGOTE","37530",IF(G54="SERGIO ROMERO DURAN","RODS620908QAA",IF(G54="MARIELA OLMOS GAONA","37675",IF(G54="LUCIANO MIJAIL ORTEGA MUÑOZ","37297",IF(G54="GUSTAVO HUMBERTO VELAZCO GALVAN","VEGG9211019T1",IF(G54="JESUS AGUSTIN VELAZQUEZ FLORES","VEFJ900303M65",IF(G54="KARLA ESTEFANIA SALAZAR FLORES","SAFK9807277N1",IF(G54="ANGEL TERRAZAS MONROY","TEMA7105035N4")))))))))) -> 37675 | P54: =IF(G54="EFREN ABUNDEZ REYNA","PFAEP",IF(G54="LUIS ALEJANDRO HERNANDEZ REYNA","HERL850705AL2",IF(G54="ANA BEATRIZ ESTRADA ARGOTE","RIF",IF(G54="SERGIO ROMERO DURAN","RODS620908QAA",IF(G54="MARIELA OLMOS GAONA","RESICO",IF(G54="LUCIANO MIJAIL ORTEGA MUÑOZ","RIF",IF(G54="GUSTAVO HUMBERTO VELAZCO GALVAN","VEGG9211019T1",IF(G54="JESUS AGUSTIN VELAZQUEZ FLORES","VEFJ900303M65",IF(G54="KARLA ESTEFANIA SALAZAR FLORES","SAFK9807277N1",IF(G54="ANGEL TERRAZAS MONROY","TEMA7105035N4")))))))))) -> RESICO
A55: =IF(D55>0,MONTH(D55),0) -> 8 | B55: =VLOOKUP(A55,[1]Hoja3!$C$3:$D$14,2,FALSE) -> AGOSTO | C55: 45524 | D55: 45524 | G55: MARIELA OLMOS GAONA | H55: =IF(G55="EFREN ABUNDEZ REYNA","AURE7306187IA",IF(G55="LUIS ALEJANDRO HERNANDEZ REYNA","HERL850705AL2",IF(G55="ANA BEATRIZ ESTRADA ARGOTE","EAAA860701UP2",IF(G55="SERGIO ROMERO DURAN","RODS620908QAA",IF(G55="MARIELA OLMOS GAONA","OOGM010703NX1",IF(G55="LUCIANO MIJAIL ORTEGA MUÑOZ","OEML881105IK2",IF(G55="GUSTAVO HUMBERTO VELAZCO GALVAN","VEGG9211019T1",IF(G55="JESUS AGUSTIN VELAZQUEZ FLORES","VEFJ900303M65",IF(G55="KARLA ESTEFANIA SALAZAR FLORES","SAFK9807277N1",IF(G55="ANGEL TERRAZAS MONROY","TEMA7105035N4")))))))))) -> OOGM010703NX1 | I55: =+B55 -> AGOSTO | J55: 13227 | K55: 0 | N55: =+J55+K55-L55-M55 -> 13227 | O55: =IF(G55="EFREN ABUNDEZ REYNA","37295",IF(G55="LUIS ALEJANDRO HERNANDEZ REYNA","HERL850705AL2",IF(G55="ANA BEATRIZ ESTRADA ARGOTE","37530",IF(G55="SERGIO ROMERO DURAN","RODS620908QAA",IF(G55="MARIELA OLMOS GAONA","37675",IF(G55="LUCIANO MIJAIL ORTEGA MUÑOZ","37297",IF(G55="GUSTAVO HUMBERTO VELAZCO GALVAN","VEGG9211019T1",IF(G55="JESUS AGUSTIN VELAZQUEZ FLORES","VEFJ900303M65",IF(G55="KARLA ESTEFANIA SALAZAR FLORES","SAFK9807277N1",IF(G55="ANGEL TERRAZAS MONROY","TEMA7105035N4")))))))))) -> 37675 | P55: =IF(G55="EFREN ABUNDEZ REYNA","PFAEP",IF(G55="LUIS ALEJANDRO HERNANDEZ REYNA","HERL850705AL2",IF(G55="ANA BEATRIZ ESTRADA ARGOTE","RIF",IF(G55="SERGIO ROMERO DURAN","RODS620908QAA",IF(G55="MARIELA OLMOS GAONA","RESICO",IF(G55="LUCIANO MIJAIL ORTEGA MUÑOZ","RIF",IF(G55="GUSTAVO HUMBERTO VELAZCO GALVAN","VEGG9211019T1",IF(G55="JESUS AGUSTIN VELAZQUEZ FLORES","VEFJ900303M65",IF(G55="KARLA ESTEFANIA SALAZAR FLORES","SAFK9807277N1",IF(G55="ANGEL TERRAZAS MONROY","TEMA7105035N4")))))))))) -> RESICO
A56: =IF(D56>0,MONTH(D56),0) -> 8 | B56: =VLOOKUP(A56,[1]Hoja3!$C$3:$D$14,2,FALSE) -> AGOSTO | C56: 45524 | D56: 45524 | G56: MARIELA OLMOS GAONA | H56: =IF(G56="EFREN ABUNDEZ REYNA","AURE7306187IA",IF(G56="LUIS ALEJANDRO HERNANDEZ REYNA","HERL850705AL2",IF(G56="ANA BEATRIZ ESTRADA ARGOTE","EAAA860701UP2",IF(G56="SERGIO ROMERO DURAN","RODS620908QAA",IF(G56="MARIELA OLMOS GAONA","OOGM010703NX1",IF(G56="LUCIANO MIJAIL ORTEGA MUÑOZ","OEML881105IK2",IF(G56="GUSTAVO HUMBERTO VELAZCO GALVAN","VEGG9211019T1",IF(G56="JESUS AGUSTIN VELAZQUEZ FLORES","VEFJ900303M65",IF(G56="KARLA ESTEFANIA SALAZAR FLORES","SAFK9807277N1",IF(G56="ANGEL TERRAZAS MONROY","TEMA7105035N4")))))))))) -> OOGM010703NX1 | I56: =+B56 -> AGOSTO | J56: 8987 | K56: 0 | N56: =+J56+K56-L56-M56 -> 8987 | O56: =IF(G56="EFREN ABUNDEZ REYNA","37295",IF(G56="LUIS ALEJANDRO HERNANDEZ REYNA","HERL850705AL2",IF(G56="ANA BEATRIZ ESTRADA ARGOTE","37530",IF(G56="SERGIO ROMERO DURAN","RODS620908QAA",IF(G56="MARIELA OLMOS GAONA","37675",IF(G56="LUCIANO MIJAIL ORTEGA MUÑOZ","37297",IF(G56="GUSTAVO HUMBERTO VELAZCO GALVAN","VEGG9211019T1",IF(G56="JESUS AGUSTIN VELAZQUEZ FLORES","VEFJ900303M65",IF(G56="KARLA ESTEFANIA SALAZAR FLORES","SAFK9807277N1",IF(G56="ANGEL TERRAZAS MONROY","TEMA7105035N4")))))))))) -> 37675 | P56: =IF(G56="EFREN ABUNDEZ REYNA","PFAEP",IF(G56="LUIS ALEJANDRO HERNANDEZ REYNA","HERL850705AL2",IF(G56="ANA BEATRIZ ESTRADA ARGOTE","RIF",IF(G56="SERGIO ROMERO DURAN","RODS620908QAA",IF(G56="MARIELA OLMOS GAONA","RESICO",IF(G56="LUCIANO MIJAIL ORTEGA MUÑOZ","RIF",IF(G56="GUSTAVO HUMBERTO VELAZCO GALVAN","VEGG9211019T1",IF(G56="JESUS AGUSTIN VELAZQUEZ FLORES","VEFJ900303M65",IF(G56="KARLA ESTEFANIA SALAZAR FLORES","SAFK9807277N1",IF(G56="ANGEL TERRAZAS MONROY","TEMA7105035N4")))))))))) -> RESICO
A57: =IF(D57>0,MONTH(D57),0) -> 8 | B57: =VLOOKUP(A57,[1]Hoja3!$C$3:$D$14,2,FALSE) -> AGOSTO | C57: 45531 | D57: 45531 | G57: DULCE BERENICE MORA OLMOS | H57: MOOD910806Q85 | I57: =+B57 -> AGOSTO | J57: 491.37931 | K57: =+J57*0.16 -> 78.62069 | N57: =+J57+K57-L57-M57 -> 570 | O57: 37220 | P57: RIF
A58: =IF(D58>0,MONTH(D58),0) -> 8 | B58: =VLOOKUP(A58,[1]Hoja3!$C$3:$D$14,2,FALSE) -> AGOSTO | C58: 45531 | D58: 45531 | G58: MARIELA OLMOS GAONA | H58: =IF(G58="EFREN ABUNDEZ REYNA","AURE7306187IA",IF(G58="LUIS ALEJANDRO HERNANDEZ REYNA","HERL850705AL2",IF(G58="ANA BEATRIZ ESTRADA ARGOTE","EAAA860701UP2",IF(G58="SERGIO ROMERO DURAN","RODS620908QAA",IF(G58="MARIELA OLMOS GAONA","OOGM010703NX1",IF(G58="LUCIANO MIJAIL ORTEGA MUÑOZ","OEML881105IK2",IF(G58="GUSTAVO HUMBERTO VELAZCO GALVAN","VEGG9211019T1",IF(G58="JESUS AGUSTIN VELAZQUEZ FLORES","VEFJ900303M65",IF(G58="KARLA ESTEFANIA SALAZAR FLORES","SAFK9807277N1",IF(G58="ANGEL TERRAZAS MONROY","TEMA7105035N4")))))))))) -> OOGM010703NX1 | I58: =+B58 -> AGOSTO | J58: 8405 | K58: 0 | N58: =+J58+K58-L58-M58 -> 8405 | O58: =IF(G58="EFREN ABUNDEZ REYNA","37295",IF(G58="LUIS ALEJANDRO HERNANDEZ REYNA","HERL850705AL2",IF(G58="ANA BEATRIZ ESTRADA ARGOTE","37530",IF(G58="SERGIO ROMERO DURAN","RODS620908QAA",IF(G58="MARIELA OLMOS GAONA","37675",IF(G58="LUCIANO MIJAIL ORTEGA MUÑOZ","37297",IF(G58="GUSTAVO HUMBERTO VELAZCO GALVAN","VEGG9211019T1",IF(G58="JESUS AGUSTIN VELAZQUEZ FLORES","VEFJ900303M65",IF(G58="KARLA ESTEFANIA SALAZAR FLORES","SAFK9807277N1",IF(G58="ANGEL TERRAZAS MONROY","TEMA7105035N4")))))))))) -> 37675 | P58: =IF(G58="EFREN ABUNDEZ REYNA","PFAEP",IF(G58="LUIS ALEJANDRO HERNANDEZ REYNA","HERL850705AL2",IF(G58="ANA BEATRIZ ESTRADA ARGOTE","RIF",IF(G58="SERGIO ROMERO DURAN","RODS620908QAA",IF(G58="MARIELA OLMOS GAONA","RESICO",IF(G58="LUCIANO MIJAIL ORTEGA MUÑOZ","RIF",IF(G58="GUSTAVO HUMBERTO VELAZCO GALVAN","VEGG9211019T1",IF(G58="JESUS AGUSTIN VELAZQUEZ FLORES","VEFJ900303M65",IF(G58="KARLA ESTEFANIA SALAZAR FLORES","SAFK9807277N1",IF(G58="ANGEL TERRAZAS MONROY","TEMA7105035N4")))))))))) -> RESICO
A59: =IF(D59>0,MONTH(D59),0) -> 8 | B59: =VLOOKUP(A59,[1]Hoja3!$C$3:$D$14,2,FALSE) -> AGOSTO | C59: 45531 | D59: 45531 | G59: MINERVA TREJO MARTINEZ | H59: TEMM710110FJ3 | I59: =+B59 -> AGOSTO | J59: 646.55172 | K59: =+J59*0.16 -> 103.44828 | N59: =+J59+K59-L59-M59 -> 750 | O59: 76116 | P59: PFAEP | Q59: tmine066@gmail.com
A60: =IF(D60>0,MONTH(D60),0) -> 9 | B60: =VLOOKUP(A60,[1]Hoja3!$C$3:$D$14,2,FALSE) -> SEPTIEMBRE | C60: 45539 | D60: 45539 | G60: MARIELA OLMOS GAONA | H60: =IF(G60="EFREN ABUNDEZ REYNA","AURE7306187IA",IF(G60="LUIS ALEJANDRO HERNANDEZ REYNA","HERL850705AL2",IF(G60="ANA BEATRIZ ESTRADA ARGOTE","EAAA860701UP2",IF(G60="SERGIO ROMERO DURAN","RODS620908QAA",IF(G60="MARIELA OLMOS GAONA","OOGM010703NX1",IF(G60="LUCIANO MIJAIL ORTEGA MUÑOZ","OEML881105IK2",IF(G60="GUSTAVO HUMBERTO VELAZCO GALVAN","VEGG9211019T1",IF(G60="JESUS AGUSTIN VELAZQUEZ FLORES","VEFJ900303M65",IF(G60="KARLA ESTEFANIA SALAZAR FLORES","SAFK9807277N1",IF(G60="ANGEL TERRAZAS MONROY","TEMA7105035N4")))))))))) -> OOGM010703NX1 | I60: =+B60 -> SEPTIEMBRE | J60: 9998 | K60: 0 | N60: =+J60+K60-L60-M60 -> 9998 | O60: =IF(G60="EFREN ABUNDEZ REYNA","37295",IF(G60="LUIS ALEJANDRO HERNANDEZ REYNA","HERL850705AL2",IF(G60="ANA BEATRIZ ESTRADA ARGOTE","37530",IF(G60="SERGIO ROMERO DURAN","RODS620908QAA",IF(G60="MARIELA OLMOS GAONA","37675",IF(G60="LUCIANO MIJAIL ORTEGA MUÑOZ","37297",IF(G60="GUSTAVO HUMBERTO VELAZCO GALVAN","VEGG9211019T1",IF(G60="JESUS AGUSTIN VELAZQUEZ FLORES","VEFJ900303M65",IF(G60="KARLA ESTEFANIA SALAZAR FLORES","SAFK9807277N1",IF(G60="ANGEL TERRAZAS MONROY","TEMA7105035N4")))))))))) -> 37675 | P60: =IF(G60="EFREN ABUNDEZ REYNA","PFAEP",IF(G60="LUIS ALEJANDRO HERNANDEZ REYNA","HERL850705AL2",IF(G60="ANA BEATRIZ ESTRADA ARGOTE","RIF",IF(G60="SERGIO ROMERO DURAN","RODS620908QAA",IF(G60="MARIELA OLMOS GAONA","RESICO",IF(G60="LUCIANO MIJAIL ORTEGA MUÑOZ","RIF",IF(G60="GUSTAVO HUMBERTO VELAZCO GALVAN","VEGG9211019T1",IF(G60="JESUS AGUSTIN VELAZQUEZ FLORES","VEFJ900303M65",IF(G60="KARLA ESTEFANIA SALAZAR FLORES","SAFK9807277N1",IF(G60="ANGEL TERRAZAS MONROY","TEMA7105035N4")))))))))) -> RESICO
A61: =IF(D61>0,MONTH(D61),0) -> 8 | B61: =VLOOKUP(A61,[1]Hoja3!$C$3:$D$14,2,FALSE) -> AGOSTO | C61: 45534 | D61: 45534 | G61: PUBLICO EN GENERAL | H61: =IF(G61="EFREN ABUNDEZ REYNA","AURE7306187IA",IF(G61="LUIS ALEJANDRO HERNANDEZ REYNA","HERL850705AL2",IF(G61="ANA BEATRIZ ESTRADA ARGOTE","EAAA860701UP2",IF(G61="SERGIO ROMERO DURAN","RODS620908QAA",IF(G61="MARIELA OLMOS GAONA","OOGM010703NX1",IF(G61="LUCIANO MIJAIL ORTEGA MUÑOZ","OEML881105IK2",IF(G61="GUSTAVO HUMBERTO VELAZCO GALVAN","VEGG9211019T1",IF(G61="JESUS AGUSTIN VELAZQUEZ FLORES","VEFJ900303M65",IF(G61="KARLA ESTEFANIA SALAZAR FLORES","SAFK9807277N1",IF(G61="ANGEL TERRAZAS MONROY","TEMA7105035N4")))))))))) -> FALSE | I61: =+B61 -> AGOSTO | J61: 204567 | K61: 0 | N61: =+J61+K61-L61-M61 -> 204567 | O61: =IF(G61="EFREN ABUNDEZ REYNA","37295",IF(G61="LUIS ALEJANDRO HERNANDEZ REYNA","HERL850705AL2",IF(G61="ANA BEATRIZ ESTRADA ARGOTE","37530",IF(G61="SERGIO ROMERO DURAN","RODS620908QAA",IF(G61="MARIELA OLMOS GAONA","37675",IF(G61="LUCIANO MIJAIL ORTEGA MUÑOZ","37297",IF(G61="GUSTAVO HUMBERTO VELAZCO GALVAN","VEGG9211019T1",IF(G61="JESUS AGUSTIN VELAZQUEZ FLORES","VEFJ900303M65",IF(G61="KARLA ESTEFANIA SALAZAR FLORES","SAFK9807277N1",IF(G61="ANGEL TERRAZAS MONROY","TEMA7105035N4")))))))))) -> FALSE | P61: =IF(G61="EFREN ABUNDEZ REYNA","PFAEP",IF(G61="LUIS ALEJANDRO HERNANDEZ REYNA","HERL850705AL2",IF(G61="ANA BEATRIZ ESTRADA ARGOTE","RIF",IF(G61="SERGIO ROMERO DURAN","RODS620908QAA",IF(G61="MARIELA OLMOS GAONA","RESICO",IF(G61="LUCIANO MIJAIL ORTEGA MUÑOZ","RIF",IF(G61="GUSTAVO HUMBERTO VELAZCO GALVAN","VEGG9211019T1",IF(G61="JESUS AGUSTIN VELAZQUEZ FLORES","VEFJ900303M65",IF(G61="KARLA ESTEFANIA SALAZAR FLORES","SAFK9807277N1",IF(G61="ANGEL TERRAZAS MONROY","TEMA7105035N4")))))))))) -> FALSE
A62: =IF(D62>0,MONTH(D62),0) -> 9 | B62: =VLOOKUP(A62,[1]Hoja3!$C$3:$D$14,2,FALSE) -> SEPTIEMBRE | C62: 45541 | D62: 45541 | G62: CHEM-AQUA MEXICO | H62: CAM9612093J2 | I62: =+B62 -> SEPTIEMBRE | J62: 60.34 | K62: =+J62*0.16 -> 9.6544 | N62: =+J62+K62-L62-M62 -> 69.9944 | O62: 54750 | P62: MORAL
A63: =IF(D63>0,MONTH(D63),0) -> 9 | B63: =VLOOKUP(A63,[1]Hoja3!$C$3:$D$14,2,FALSE) -> SEPTIEMBRE | C63: 45541 | D63: 45541 | G63: CHEM-AQUA MEXICO | H63: CAM9612093J2 | I63: =+B63 -> SEPTIEMBRE | J63: 120.69 | K63: =+J63*0.16 -> 19.3104 | N63: =+J63+K63-L63-M63 -> 140.0004 | O63: 54750 | P63: MORAL
A64: =IF(D64>0,MONTH(D64),0) -> 9 | B64: =VLOOKUP(A64,[1]Hoja3!$C$3:$D$14,2,FALSE) -> SEPTIEMBRE | C64: 45546 | D64: 45546 | G64: MARIELA OLMOS GAONA | H64: =IF(G64="EFREN ABUNDEZ REYNA","AURE7306187IA",IF(G64="LUIS ALEJANDRO HERNANDEZ REYNA","HERL850705AL2",IF(G64="ANA BEATRIZ ESTRADA ARGOTE","EAAA860701UP2",IF(G64="SERGIO ROMERO DURAN","RODS620908QAA",IF(G64="MARIELA OLMOS GAONA","OOGM010703NX1",IF(G64="LUCIANO MIJAIL ORTEGA MUÑOZ","OEML881105IK2",IF(G64="GUSTAVO HUMBERTO VELAZCO GALVAN","VEGG9211019T1",IF(G64="JESUS AGUSTIN VELAZQUEZ FLORES","VEFJ900303M65",IF(G64="KARLA ESTEFANIA SALAZAR FLORES","SAFK9807277N1",IF(G64="ANGEL TERRAZAS MONROY","TEMA7105035N4")))))))))) -> OOGM010703NX1 | I64: =+B64 -> SEPTIEMBRE | J64: 8937 | K64: 0 | N64: =+J64+K64-L64-M64 -> 8937 | O64: =IF(G64="EFREN ABUNDEZ REYNA","37295",IF(G64="LUIS ALEJANDRO HERNANDEZ REYNA","HERL850705AL2",IF(G64="ANA BEATRIZ ESTRADA ARGOTE","37530",IF(G64="SERGIO ROMERO DURAN","RODS620908QAA",IF(G64="MARIELA OLMOS GAONA","37675",IF(G64="LUCIANO MIJAIL ORTEGA MUÑOZ","37297",IF(G64="GUSTAVO HUMBERTO VELAZCO GALVAN","VEGG9211019T1",IF(G64="JESUS AGUSTIN VELAZQUEZ FLORES","VEFJ900303M65",IF(G64="KARLA ESTEFANIA SALAZAR FLORES","SAFK9807277N1",IF(G64="ANGEL TERRAZAS MONROY","TEMA7105035N4")))))))))) -> 37675 | P64: =IF(G64="EFREN ABUNDEZ REYNA","PFAEP",IF(G64="LUIS ALEJANDRO HERNANDEZ REYNA","HERL850705AL2",IF(G64="ANA BEATRIZ ESTRADA ARGOTE","RIF",IF(G64="SERGIO ROMERO DURAN","RODS620908QAA",IF(G64="MARIELA OLMOS GAONA","RESICO",IF(G64="LUCIANO MIJAIL ORTEGA MUÑOZ","RIF",IF(G64="GUSTAVO HUMBERTO VELAZCO GALVAN","VEGG9211019T1",IF(G64="JESUS AGUSTIN VELAZQUEZ FLORES","VEFJ900303M65",IF(G64="KARLA ESTEFANIA SALAZAR FLORES","SAFK9807277N1",IF(G64="ANGEL TERRAZAS MONROY","TEMA7105035N4")))))))))) -> RESICO
A65: =IF(D65>0,MONTH(D65),0) -> 9 | B65: =VLOOKUP(A65,[1]Hoja3!$C$3:$D$14,2,FALSE) -> SEPTIEMBRE | C65: 45547 | D65: 45547 | G65: CALIBRACMM DE MEXICO | H65: CME040519990 | I65: =+B65 -> SEPTIEMBRE | J65: 1230 | K65: =+J65*0.16 -> 196.8 | N65: =+J65+K65-L65-M65 -> 1426.8 | O65: 72210 | P65: MORAL | Q65: jesusariz@hotmail.com
A66: =IF(D66>0,MONTH(D66),0) -> 9 | B66: =VLOOKUP(A66,[1]Hoja3!$C$3:$D$14,2,FALSE) -> SEPTIEMBRE | C66: 45552 | D66: 45552 | G66: CALIBRACMM DE MEXICO | H66: CME040519990 | I66: =+B66 -> SEPTIEMBRE | J66: 903.44828 | K66: =+J66*0.16 -> 144.55172 | N66: =+J66+K66-L66-M66 -> 1048 | O66: 72210 | P66: MORAL | Q66: jesusariz@hotmail.com
A67: =IF(D67>0,MONTH(D67),0) -> 9 | B67: =VLOOKUP(A67,[1]Hoja3!$C$3:$D$14,2,FALSE) -> SEPTIEMBRE | C67: 45552 | D67: 45552 | G67: CHEM-AQUA MEXICO | H67: CAM9612093J2 | I67: =+B67 -> SEPTIEMBRE | J67: 862.06897 | K67: =+J67*0.16 -> 137.93103 | N67: =+J67+K67-L67-M67 -> 1000 | O67: 54750 | P67: MORAL
A68: =IF(D68>0,MONTH(D68),0) -> 9 | B68: =VLOOKUP(A68,[1]Hoja3!$C$3:$D$14,2,FALSE) -> SEPTIEMBRE | C68: 45552 | D68: 45552 | G68: NSK-WARNER MEXICO | H68: NME16070647A | I68: =+B68 -> SEPTIEMBRE | J68: 814.66 | K68: =+J68*0.16 -> 130.3456 | N68: =+J68+K68-L68-M68 -> 945.0056 | O68: 36275 | P68: MORAL | Q68: pago con tarjeta
A69: =IF(D69>0,MONTH(D69),0) -> 9 | B69: =VLOOKUP(A69,[1]Hoja3!$C$3:$D$14,2,FALSE) -> SEPTIEMBRE | C69: 45552 | D69: 45552 | G69: MARIELA OLMOS GAONA | H69: =IF(G69="EFREN ABUNDEZ REYNA","AURE7306187IA",IF(G69="LUIS ALEJANDRO HERNANDEZ REYNA","HERL850705AL2",IF(G69="ANA BEATRIZ ESTRADA ARGOTE","EAAA860701UP2",IF(G69="SERGIO ROMERO DURAN","RODS620908QAA",IF(G69="MARIELA OLMOS GAONA","OOGM010703NX1",IF(G69="LUCIANO MIJAIL ORTEGA MUÑOZ","OEML881105IK2",IF(G69="GUSTAVO HUMBERTO VELAZCO GALVAN","VEGG9211019T1",IF(G69="JESUS AGUSTIN VELAZQUEZ FLORES","VEFJ900303M65",IF(G69="KARLA ESTEFANIA SALAZAR FLORES","SAFK9807277N1",IF(G69="ANGEL TERRAZAS MONROY","TEMA7105035N4")))))))))) -> OOGM010703NX1 | I69: =+B69 -> SEPTIEMBRE | J69: 11980 | K69: =+J69*0.16 -> 1916.8 | N69: =+J69+K69-L69-M69 -> 13896.8 | O69: =IF(G69="EFREN ABUNDEZ REYNA","37295",IF(G69="LUIS ALEJANDRO HERNANDEZ REYNA","HERL850705AL2",IF(G69="ANA BEATRIZ ESTRADA ARGOTE","37530",IF(G69="SERGIO ROMERO DURAN","RODS620908QAA",IF(G69="MARIELA OLMOS GAONA","37675",IF(G69="LUCIANO MIJAIL ORTEGA MUÑOZ","37297",IF(G69="GUSTAVO HUMBERTO VELAZCO GALVAN","VEGG9211019T1",IF(G69="JESUS AGUSTIN VELAZQUEZ FLORES","VEFJ900303M65",IF(G69="KARLA ESTEFANIA SALAZAR FLORES","SAFK9807277N1",IF(G69="ANGEL TERRAZAS MONROY","TEMA7105035N4")))))))))) -> 37675 | P69: =IF(G69="EFREN ABUNDEZ REYNA","PFAEP",IF(G69="LUIS ALEJANDRO HERNANDEZ REYNA","HERL850705AL2",IF(G69="ANA BEATRIZ ESTRADA ARGOTE","RIF",IF(G69="SERGIO ROMERO DURAN","RODS620908QAA",IF(G69="MARIELA OLMOS GAONA","RESICO",IF(G69="LUCIANO MIJAIL ORTEGA MUÑOZ","RIF",IF(G69="GUSTAVO HUMBERTO VELAZCO GALVAN","VEGG9211019T1",IF(G69="JESUS AGUSTIN VELAZQUEZ FLORES","VEFJ900303M65",IF(G69="KARLA ESTEFANIA SALAZAR FLORES","SAFK9807277N1",IF(G69="ANGEL TERRAZAS MONROY","TEMA7105035N4")))))))))) -> RESICO
A70: =IF(D70>0,MONTH(D70),0) -> 9 | B70: =VLOOKUP(A70,[1]Hoja3!$C$3:$D$14,2,FALSE) -> SEPTIEMBRE | C70: 45565 | D70: 45565 | G70: POWERQRO | H70: POW210709HU2 | I70: =+B70 -> SEPTIEMBRE | J70: 250 | K70: =+J70*0.16 -> 40 | N70: =+J70+K70-L70-M70 -> 290 | O70: 76226 | P70: MORAL
A71: =IF(D71>0,MONTH(D71),0) -> 9 | B71: =VLOOKUP(A71,[1]Hoja3!$C$3:$D$14,2,FALSE) -> SEPTIEMBRE | C71: 45565 | D71: 45565 | G71: CHEM-AQUA MEXICO | H71: CAM9612093J2 | I71: =+B71 -> SEPTIEMBRE | J71: 165 | K71: =+J71*0.16 -> 26.4 | N71: =+J71+K71-L71-M71 -> 191.4 | O71: 54750 | P71: MORAL
A72: =IF(D72>0,MONTH(D72),0) -> 9 | B72: =VLOOKUP(A72,[1]Hoja3!$C$3:$D$14,2,FALSE) -> SEPTIEMBRE | C72: 45565 | D72: 45565 | G72: CHEM-AQUA MEXICO | H72: CAM9612093J2 | I72: =+B72 -> SEPTIEMBRE | J72: 95 | K72: =+J72*0.16 -> 15.2 | N72: =+J72+K72-L72-M72 -> 110.2 | O72: =IF(G72="EFREN ABUNDEZ REYNA","37295",IF(G72="LUIS ALEJANDRO HERNANDEZ REYNA","HERL850705AL2",IF(G72="ANA BEATRIZ ESTRADA ARGOTE","37530",IF(G72="SERGIO ROMERO DURAN","RODS620908QAA",IF(G72="MARIELA OLMOS GAONA","37675",IF(G72="LUCIANO MIJAIL ORTEGA MUÑOZ","37297",IF(G72="GUSTAVO HUMBERTO VELAZCO GALVAN","VEGG9211019T1",IF(G72="JESUS AGUSTIN VELAZQUEZ FLORES","VEFJ900303M65",IF(G72="KARLA ESTEFANIA SALAZAR FLORES","SAFK9807277N1",IF(G72="ANGEL TERRAZAS MONROY","TEMA7105035N4")))))))))) -> FALSE | P72: =IF(G72="EFREN ABUNDEZ REYNA","PFAEP",IF(G72="LUIS ALEJANDRO HERNANDEZ REYNA","HERL850705AL2",IF(G72="ANA BEATRIZ ESTRADA ARGOTE","RIF",IF(G72="SERGIO ROMERO DURAN","RODS620908QAA",IF(G72="MARIELA OLMOS GAONA","RESICO",IF(G72="LUCIANO MIJAIL ORTEGA MUÑOZ","RIF",IF(G72="GUSTAVO HUMBERTO VELAZCO GALVAN","VEGG9211019T1",IF(G72="JESUS AGUSTIN VELAZQUEZ FLORES","VEFJ900303M65",IF(G72="KARLA ESTEFANIA SALAZAR FLORES","SAFK9807277N1",IF(G72="ANGEL TERRAZAS MONROY","TEMA7105035N4")))))))))) -> FALSE
A73: =IF(D73>0,MONTH(D73),0) -> 9 | B73: =VLOOKUP(A73,[1]Hoja3!$C$3:$D$14,2,FALSE) -> SEPTIEMBRE | C73: 45565 | D73: 45565 | G73: MARIELA OLMOS GAONA | H73: =IF(G73="EFREN ABUNDEZ REYNA","AURE7306187IA",IF(G73="LUIS ALEJANDRO HERNANDEZ REYNA","HERL850705AL2",IF(G73="ANA BEATRIZ ESTRADA ARGOTE","EAAA860701UP2",IF(G73="SERGIO ROMERO DURAN","RODS620908QAA",IF(G73="MARIELA OLMOS GAONA","OOGM010703NX1",IF(G73="LUCIANO MIJAIL ORTEGA MUÑOZ","OEML881105IK2",IF(G73="GUSTAVO HUMBERTO VELAZCO GALVAN","VEGG9211019T1",IF(G73="JESUS AGUSTIN VELAZQUEZ FLORES","VEFJ900303M65",IF(G73="KARLA ESTEFANIA SALAZAR FLORES","SAFK9807277N1",IF(G73="ANGEL TERRAZAS MONROY","TEMA7105035N4")))))))))) -> OOGM010703NX1 | I73: =+B73 -> SEPTIEMBRE | J73: 9660 | K73: 0 | N73: =+J73+K73-L73-M73 -> 9660 | O73: =IF(G73="EFREN ABUNDEZ REYNA","37295",IF(G73="LUIS ALEJANDRO HERNANDEZ REYNA","HERL850705AL2",IF(G73="ANA BEATRIZ ESTRADA ARGOTE","37530",IF(G73="SERGIO ROMERO DURAN","RODS620908QAA",IF(G73="MARIELA OLMOS GAONA","37675",IF(G73="LUCIANO MIJAIL ORTEGA MUÑOZ","37297",IF(G73="GUSTAVO HUMBERTO VELAZCO GALVAN","VEGG9211019T1",IF(G73="JESUS AGUSTIN VELAZQUEZ FLORES","VEFJ900303M65",IF(G73="KARLA ESTEFANIA SALAZAR FLORES","SAFK9807277N1",IF(G73="ANGEL TERRAZAS MONROY","TEMA7105035N4")))))))))) -> 37675 | P73: =IF(G73="EFREN ABUNDEZ REYNA","PFAEP",IF(G73="LUIS ALEJANDRO HERNANDEZ REYNA","HERL850705AL2",IF(G73="ANA BEATRIZ ESTRADA ARGOTE","RIF",IF(G73="SERGIO ROMERO DURAN","RODS620908QAA",IF(G73="MARIELA OLMOS GAONA","RESICO",IF(G73="LUCIANO MIJAIL ORTEGA MUÑOZ","RIF",IF(G73="GUSTAVO HUMBERTO VELAZCO GALVAN","VEGG9211019T1",IF(G73="JESUS AGUSTIN VELAZQUEZ FLORES","VEFJ900303M65",IF(G73="KARLA ESTEFANIA SALAZAR FLORES","SAFK9807277N1",IF(G73="ANGEL TERRAZAS MONROY","TEMA7105035N4")))))))))) -> RESICO
A74: =IF(D74>0,MONTH(D74),0) -> 9 | B74: =VLOOKUP(A74,[1]Hoja3!$C$3:$D$14,2,FALSE) -> SEPTIEMBRE | C74: 45565 | D74: 45565 | G74: CALIBRACMM DE MEXICO | H74: CME040519990 | I74: =+B74 -> SEPTIEMBRE | J74: 1260 | K74: =+J74*0.16 -> 201.6 | N74: =+J74+K74-L74-M74 -> 1461.6 | O74: 72210 | P74: MORAL | Q74: jesusariz@hotmail.com
A75: =IF(D75>0,MONTH(D75),0) -> 9 | B75: =VLOOKUP(A75,[1]Hoja3!$C$3:$D$14,2,FALSE) -> SEPTIEMBRE | C75: 45565 | D75: 45565 | G75: CALIBRACMM DE MEXICO | H75: CME040519990 | I75: =+B75 -> SEPTIEMBRE | J75: 1535 | K75: =+J75*0.16 -> 245.6 | N75: =+J75+K75-L75-M75 -> 1780.6 | O75: 72210 | P75: MORAL
A76: =IF(D76>0,MONTH(D76),0) -> 10 | B76: =VLOOKUP(A76,[1]Hoja3!$C$3:$D$14,2,FALSE) -> OCTUBRE | C76: 45567 | D76: 45567 | G76: MARIELA OLMOS GAONA | H76: =IF(G76="EFREN ABUNDEZ REYNA","AURE7306187IA",IF(G76="LUIS ALEJANDRO HERNANDEZ REYNA","HERL850705AL2",IF(G76="ANA BEATRIZ ESTRADA ARGOTE","EAAA860701UP2",IF(G76="SERGIO ROMERO DURAN","RODS620908QAA",IF(G76="MARIELA OLMOS GAONA","OOGM010703NX1",IF(G76="LUCIANO MIJAIL ORTEGA MUÑOZ","OEML881105IK2",IF(G76="GUSTAVO HUMBERTO VELAZCO GALVAN","VEGG9211019T1",IF(G76="JESUS AGUSTIN VELAZQUEZ FLORES","VEFJ900303M65",IF(G76="KARLA ESTEFANIA SALAZAR FLORES","SAFK9807277N1",IF(G76="ANGEL TERRAZAS MONROY","TEMA7105035N4")))))))))) -> OOGM010703NX1 | I76: =+B76 -> OCTUBRE | J76: 6955 | K76: 0 | N76: =+J76+K76-L76-M76 -> 6955 | O76: =IF(G76="EFREN ABUNDEZ REYNA","37295",IF(G76="LUIS ALEJANDRO HERNANDEZ REYNA","HERL850705AL2",IF(G76="ANA BEATRIZ ESTRADA ARGOTE","37530",IF(G76="SERGIO ROMERO DURAN","RODS620908QAA",IF(G76="MARIELA OLMOS GAONA","37675",IF(G76="LUCIANO MIJAIL ORTEGA MUÑOZ","37297",IF(G76="GUSTAVO HUMBERTO VELAZCO GALVAN","VEGG9211019T1",IF(G76="JESUS AGUSTIN VELAZQUEZ FLORES","VEFJ900303M65",IF(G76="KARLA ESTEFANIA SALAZAR FLORES","SAFK9807277N1",IF(G76="ANGEL TERRAZAS MONROY","TEMA7105035N4")))))))))) -> 37675 | P76: =IF(G76="EFREN ABUNDEZ REYNA","PFAEP",IF(G76="LUIS ALEJANDRO HERNANDEZ REYNA","HERL850705AL2",IF(G76="ANA BEATRIZ ESTRADA ARGOTE","RIF",IF(G76="SERGIO ROMERO DURAN","RODS620908QAA",IF(G76="MARIELA OLMOS GAONA","RESICO",IF(G76="LUCIANO MIJAIL ORTEGA MUÑOZ","RIF",IF(G76="GUSTAVO HUMBERTO VELAZCO GALVAN","VEGG9211019T1",IF(G76="JESUS AGUSTIN VELAZQUEZ FLORES","VEFJ900303M65",IF(G76="KARLA ESTEFANIA SALAZAR FLORES","SAFK9807277N1",IF(G76="ANGEL TERRAZAS MONROY","TEMA7105035N4")))))))))) -> RESICO
A77: =IF(D77>0,MONTH(D77),0) -> 10 | B77: =VLOOKUP(A77,[1]Hoja3!$C$3:$D$14,2,FALSE) -> OCTUBRE | C77: 45573 | D77: 45573 | G77: OSCAR URIBE CRUZ | H77: UICO7504071PA | I77: =+B77 -> OCTUBRE | J77: 821.55 | K77: =+J77*0.16 -> 131.448 | N77: =+J77+K77-L77-M77 -> 952.998 | O77: 54950 | P77: PFAEP | Q77: CRUZ.URIBE.OSCAR@GMAIL.COM
A78: =IF(D78>0,MONTH(D78),0) -> 10 | B78: =VLOOKUP(A78,[1]Hoja3!$C$3:$D$14,2,FALSE) -> OCTUBRE | C78: 45573 | D78: 45573 | G78: GERARDO RAMOS LOPEZ | H78: RALG850220K25 | I78: =+B78 -> OCTUBRE | J78: 625 | K78: =+J78*0.16 -> 100 | N78: =+J78+K78-L78-M78 -> 725 | O78: 22117 | P78: PFAEP
A79: =IF(D79>0,MONTH(D79),0) -> 10 | B79: =VLOOKUP(A79,[1]Hoja3!$C$3:$D$14,2,FALSE) -> OCTUBRE | C79: 45574 | D79: 45574 | G79: MARIELA OLMOS GAONA | H79: =IF(G79="EFREN ABUNDEZ REYNA","AURE7306187IA",IF(G79="LUIS ALEJANDRO HERNANDEZ REYNA","HERL850705AL2",IF(G79="ANA BEATRIZ ESTRADA ARGOTE","EAAA860701UP2",IF(G79="SERGIO ROMERO DURAN","RODS620908QAA",IF(G79="MARIELA OLMOS GAONA","OOGM010703NX1",IF(G79="LUCIANO MIJAIL ORTEGA MUÑOZ","OEML881105IK2",IF(G79="GUSTAVO HUMBERTO VELAZCO GALVAN","VEGG9211019T1",IF(G79="JESUS AGUSTIN VELAZQUEZ FLORES","VEFJ900303M65",IF(G79="KARLA ESTEFANIA SALAZAR FLORES","SAFK9807277N1",IF(G79="ANGEL TERRAZAS MONROY","TEMA7105035N4")))))))))) -> OOGM010703NX1 | I79: =+B79 -> OCTUBRE | J79: 5354 | K79: 0 | N79: =+J79+K79-L79-M79 -> 5354 | O79: =IF(G79="EFREN ABUNDEZ REYNA","37295",IF(G79="LUIS ALEJANDRO HERNANDEZ REYNA","HERL850705AL2",IF(G79="ANA BEATRIZ ESTRADA ARGOTE","37530",IF(G79="SERGIO ROMERO DURAN","RODS620908QAA",IF(G79="MARIELA OLMOS GAONA","37675",IF(G79="LUCIANO MIJAIL ORTEGA MUÑOZ","37297",IF(G79="GUSTAVO HUMBERTO VELAZCO GALVAN","VEGG9211019T1",IF(G79="JESUS AGUSTIN VELAZQUEZ FLORES","VEFJ900303M65",IF(G79="KARLA ESTEFANIA SALAZAR FLORES","SAFK9807277N1",IF(G79="ANGEL TERRAZAS MONROY","TEMA7105035N4")))))))))) -> 37675 | P79: =IF(G79="EFREN ABUNDEZ REYNA","PFAEP",IF(G79="LUIS ALEJANDRO HERNANDEZ REYNA","HERL850705AL2",IF(G79="ANA BEATRIZ ESTRADA ARGOTE","RIF",IF(G79="SERGIO ROMERO DURAN","RODS620908QAA",IF(G79="MARIELA OLMOS GAONA","RESICO",IF(G79="LUCIANO MIJAIL ORTEGA MUÑOZ","RIF",IF(G79="GUSTAVO HUMBERTO VELAZCO GALVAN","VEGG9211019T1",IF(G79="JESUS AGUSTIN VELAZQUEZ FLORES","VEFJ900303M65",IF(G79="KARLA ESTEFANIA SALAZAR FLORES","SAFK9807277N1",IF(G79="ANGEL TERRAZAS MONROY","TEMA7105035N4")))))))))) -> RESICO
A80: =IF(D80>0,MONTH(D80),0) -> 9 | B80: =VLOOKUP(A80,[1]Hoja3!$C$3:$D$14,2,FALSE) -> SEPTIEMBRE | C80: 45565 | D80: 45565 | G80: PUBLICO EN GENERAL | H80: =IF(G80="EFREN ABUNDEZ REYNA","AURE7306187IA",IF(G80="LUIS ALEJANDRO HERNANDEZ REYNA","HERL850705AL2",IF(G80="ANA BEATRIZ ESTRADA ARGOTE","EAAA860701UP2",IF(G80="SERGIO ROMERO DURAN","RODS620908QAA",IF(G80="MARIELA OLMOS GAONA","OOGM010703NX1",IF(G80="LUCIANO MIJAIL ORTEGA MUÑOZ","OEML881105IK2",IF(G80="GUSTAVO HUMBERTO VELAZCO GALVAN","VEGG9211019T1",IF(G80="JESUS AGUSTIN VELAZQUEZ FLORES","VEFJ900303M65",IF(G80="KARLA ESTEFANIA SALAZAR FLORES","SAFK9807277N1",IF(G80="ANGEL TERRAZAS MONROY","TEMA7105035N4")))))))))) -> FALSE | I80: =+B80 -> SEPTIEMBRE | J80: 288436 | K80: 0 | N80: =+J80+K80-L80-M80 -> 288436 | O80: =IF(G80="EFREN ABUNDEZ REYNA","37295",IF(G80="LUIS ALEJANDRO HERNANDEZ REYNA","HERL850705AL2",IF(G80="ANA BEATRIZ ESTRADA ARGOTE","37530",IF(G80="SERGIO ROMERO DURAN","RODS620908QAA",IF(G80="MARIELA OLMOS GAONA","37675",IF(G80="LUCIANO MIJAIL ORTEGA MUÑOZ","37297",IF(G80="GUSTAVO HUMBERTO VELAZCO GALVAN","VEGG9211019T1",IF(G80="JESUS AGUSTIN VELAZQUEZ FLORES","VEFJ900303M65",IF(G80="KARLA ESTEFANIA SALAZAR FLORES","SAFK9807277N1",IF(G80="ANGEL TERRAZAS MONROY","TEMA7105035N4")))))))))) -> FALSE | P80: =IF(G80="EFREN ABUNDEZ REYNA","PFAEP",IF(G80="LUIS ALEJANDRO HERNANDEZ REYNA","HERL850705AL2",IF(G80="ANA BEATRIZ ESTRADA ARGOTE","RIF",IF(G80="SERGIO ROMERO DURAN","RODS620908QAA",IF(G80="MARIELA OLMOS GAONA","RESICO",IF(G80="LUCIANO MIJAIL ORTEGA MUÑOZ","RIF",IF(G80="GUSTAVO HUMBERTO VELAZCO GALVAN","VEGG9211019T1",IF(G80="JESUS AGUSTIN VELAZQUEZ FLORES","VEFJ900303M65",IF(G80="KARLA ESTEFANIA SALAZAR FLORES","SAFK9807277N1",IF(G80="ANGEL TERRAZAS MONROY","TEMA7105035N4")))))))))) -> FALSE
A81: =IF(D81>0,MONTH(D81),0) -> 10 | B81: =VLOOKUP(A81,[1]Hoja3!$C$3:$D$14,2,FALSE) -> OCTUBRE | C81: 45580 | D81: 45580 | G81: MARIELA OLMOS GAONA | H81: =IF(G81="EFREN ABUNDEZ REYNA","AURE7306187IA",IF(G81="LUIS ALEJANDRO HERNANDEZ REYNA","HERL850705AL2",IF(G81="ANA BEATRIZ ESTRADA ARGOTE","EAAA860701UP2",IF(G81="SERGIO ROMERO DURAN","RODS620908QAA",IF(G81="MARIELA OLMOS GAONA","OOGM010703NX1",IF(G81="LUCIANO MIJAIL ORTEGA MUÑOZ","OEML881105IK2",IF(G81="GUSTAVO HUMBERTO VELAZCO GALVAN","VEGG9211019T1",IF(G81="JESUS AGUSTIN VELAZQUEZ FLORES","VEFJ900303M65",IF(G81="KARLA ESTEFANIA SALAZAR FLORES","SAFK9807277N1",IF(G81="ANGEL TERRAZAS MONROY","TEMA7105035N4")))))))))) -> OOGM010703NX1 | I81: =+B81 -> OCTUBRE | J81: 7070 | K81: 0 | N81: =+J81+K81-L81-M81 -> 7070 | O81: =IF(G81="EFREN ABUNDEZ REYNA","37295",IF(G81="LUIS ALEJANDRO HERNANDEZ REYNA","HERL850705AL2",IF(G81="ANA BEATRIZ ESTRADA ARGOTE","37530",IF(G81="SERGIO ROMERO DURAN","RODS620908QAA",IF(G81="MARIELA OLMOS GAONA","37675",IF(G81="LUCIANO MIJAIL ORTEGA MUÑOZ","37297",IF(G81="GUSTAVO HUMBERTO VELAZCO GALVAN","VEGG9211019T1",IF(G81="JESUS AGUSTIN VELAZQUEZ FLORES","VEFJ900303M65",IF(G81="KARLA ESTEFANIA SALAZAR FLORES","SAFK9807277N1",IF(G81="ANGEL TERRAZAS MONROY","TEMA7105035N4")))))))))) -> 37675 | P81: =IF(G81="EFREN ABUNDEZ REYNA","PFAEP",IF(G81="LUIS ALEJANDRO HERNANDEZ REYNA","HERL850705AL2",IF(G81="ANA BEATRIZ ESTRADA ARGOTE","RIF",IF(G81="SERGIO ROMERO DURAN","RODS620908QAA",IF(G81="MARIELA OLMOS GAONA","RESICO",IF(G81="LUCIANO MIJAIL ORTEGA MUÑOZ","RIF",IF(G81="GUSTAVO HUMBERTO VELAZCO GALVAN","VEGG9211019T1",IF(G81="JESUS AGUSTIN VELAZQUEZ FLORES","VEFJ900303M65",IF(G81="KARLA ESTEFANIA SALAZAR FLORES","SAFK9807277N1",IF(G81="ANGEL TERRAZAS MONROY","TEMA7105035N4")))))))))) -> RESICO
A82: =IF(D82>0,MONTH(D82),0) -> 10 | B82: =VLOOKUP(A82,[1]Hoja3!$C$3:$D$14,2,FALSE) -> OCTUBRE | C82: 45582 | D82: 45582 | G82: OSCAR URIBE CRUZ | H82: UICO7504071PA | I82: =+B82 -> OCTUBRE | J82: 825 | K82: =+J82*0.16 -> 132 | N82: =+J82+K82-L82-M82 -> 957 | O82: 54950 | P82: PFAEP | Q82: CRUZ.URIBE.OSCAR@GMAIL.COM
A83: =IF(D83>0,MONTH(D83),0) -> 10 | B83: =VLOOKUP(A83,[1]Hoja3!$C$3:$D$14,2,FALSE) -> OCTUBRE | C83: 45594 | D83: 45594 | G83: MARIELA OLMOS GAONA | H83: =IF(G83="EFREN ABUNDEZ REYNA","AURE7306187IA",IF(G83="LUIS ALEJANDRO HERNANDEZ REYNA","HERL850705AL2",IF(G83="ANA BEATRIZ ESTRADA ARGOTE","EAAA860701UP2",IF(G83="SERGIO ROMERO DURAN","RODS620908QAA",IF(G83="MARIELA OLMOS GAONA","OOGM010703NX1",IF(G83="LUCIANO MIJAIL ORTEGA MUÑOZ","OEML881105IK2",IF(G83="GUSTAVO HUMBERTO VELAZCO GALVAN","VEGG9211019T1",IF(G83="JESUS AGUSTIN VELAZQUEZ FLORES","VEFJ900303M65",IF(G83="KARLA ESTEFANIA SALAZAR FLORES","SAFK9807277N1",IF(G83="ANGEL TERRAZAS MONROY","TEMA7105035N4")))))))))) -> OOGM010703NX1 | I83: =+B83 -> OCTUBRE | J83: 11071 | K83: 0 | N83: =+J83+K83-L83-M83 -> 11071 | O83: =IF(G83="EFREN ABUNDEZ REYNA","37295",IF(G83="LUIS ALEJANDRO HERNANDEZ REYNA","HERL850705AL2",IF(G83="ANA BEATRIZ ESTRADA ARGOTE","37530",IF(G83="SERGIO ROMERO DURAN","RODS620908QAA",IF(G83="MARIELA OLMOS GAONA","37675",IF(G83="LUCIANO MIJAIL ORTEGA MUÑOZ","37297",IF(G83="GUSTAVO HUMBERTO VELAZCO GALVAN","VEGG9211019T1",IF(G83="JESUS AGUSTIN VELAZQUEZ FLORES","VEFJ900303M65",IF(G83="KARLA ESTEFANIA SALAZAR FLORES","SAFK9807277N1",IF(G83="ANGEL TERRAZAS MONROY","TEMA7105035N4")))))))))) -> 37675 | P83: =IF(G83="EFREN ABUNDEZ REYNA","PFAEP",IF(G83="LUIS ALEJANDRO HERNANDEZ REYNA","HERL850705AL2",IF(G83="ANA BEATRIZ ESTRADA ARGOTE","RIF",IF(G83="SERGIO ROMERO DURAN","RODS620908QAA",IF(G83="MARIELA OLMOS GAONA","RESICO",IF(G83="LUCIANO MIJAIL ORTEGA MUÑOZ","RIF",IF(G83="GUSTAVO HUMBERTO VELAZCO GALVAN","VEGG9211019T1",IF(G83="JESUS AGUSTIN VELAZQUEZ FLORES","VEFJ900303M65",IF(G83="KARLA ESTEFANIA SALAZAR FLORES","SAFK9807277N1",IF(G83="ANGEL TERRAZAS MONROY","TEMA7105035N4")))))))))) -> RESICO
A84: =IF(D84>0,MONTH(D84),0) -> 10 | B84: =VLOOKUP(A84,[1]Hoja3!$C$3:$D$14,2,FALSE) -> OCTUBRE | C84: 45594 | D84: 45594 | G84: MARIELA OLMOS GAONA | H84: =IF(G84="EFREN ABUNDEZ REYNA","AURE7306187IA",IF(G84="LUIS ALEJANDRO HERNANDEZ REYNA","HERL850705AL2",IF(G84="ANA BEATRIZ ESTRADA ARGOTE","EAAA860701UP2",IF(G84="SERGIO ROMERO DURAN","RODS620908QAA",IF(G84="MARIELA OLMOS GAONA","OOGM010703NX1",IF(G84="LUCIANO MIJAIL ORTEGA MUÑOZ","OEML881105IK2",IF(G84="GUSTAVO HUMBERTO VELAZCO GALVAN","VEGG9211019T1",IF(G84="JESUS AGUSTIN VELAZQUEZ FLORES","VEFJ900303M65",IF(G84="KARLA ESTEFANIA SALAZAR FLORES","SAFK9807277N1",IF(G84="ANGEL TERRAZAS MONROY","TEMA7105035N4")))))))))) -> OOGM010703NX1 | I84: =+B84 -> OCTUBRE | J84: 8890 | K84: 0 | N84: =+J84+K84-L84-M84 -> 8890 | O84: =IF(G84="EFREN ABUNDEZ REYNA","37295",IF(G84="LUIS ALEJANDRO HERNANDEZ REYNA","HERL850705AL2",IF(G84="ANA BEATRIZ ESTRADA ARGOTE","37530",IF(G84="SERGIO ROMERO DURAN","RODS620908QAA",IF(G84="MARIELA OLMOS GAONA","37675",IF(G84="LUCIANO MIJAIL ORTEGA MUÑOZ","37297",IF(G84="GUSTAVO HUMBERTO VELAZCO GALVAN","VEGG9211019T1",IF(G84="JESUS AGUSTIN VELAZQUEZ FLORES","VEFJ900303M65",IF(G84="KARLA ESTEFANIA SALAZAR FLORES","SAFK9807277N1",IF(G84="ANGEL TERRAZAS MONROY","TEMA7105035N4")))))))))) -> 37675 | P84: =IF(G84="EFREN ABUNDEZ REYNA","PFAEP",IF(G84="LUIS ALEJANDRO HERNANDEZ REYNA","HERL850705AL2",IF(G84="ANA BEATRIZ ESTRADA ARGOTE","RIF",IF(G84="SERGIO ROMERO DURAN","RODS620908QAA",IF(G84="MARIELA OLMOS GAONA","RESICO",IF(G84="LUCIANO MIJAIL ORTEGA MUÑOZ","RIF",IF(G84="GUSTAVO HUMBERTO VELAZCO GALVAN","VEGG9211019T1",IF(G84="JESUS AGUSTIN VELAZQUEZ FLORES","VEFJ900303M65",IF(G84="KARLA ESTEFANIA SALAZAR FLORES","SAFK9807277N1",IF(G84="ANGEL TERRAZAS MONROY","TEMA7105035N4")))))))))) -> RESICO
A85: =IF(D85>0,MONTH(D85),0) -> 11 | B85: =VLOOKUP(A85,[1]Hoja3!$C$3:$D$14,2,FALSE) -> NOVIEMBRE | C85: 45608 | D85: 45608 | G85: MARIELA OLMOS GAONA | H85: =IF(G85="EFREN ABUNDEZ REYNA","AURE7306187IA",IF(G85="LUIS ALEJANDRO HERNANDEZ REYNA","HERL850705AL2",IF(G85="ANA BEATRIZ ESTRADA ARGOTE","EAAA860701UP2",IF(G85="SERGIO ROMERO DURAN","RODS620908QAA",IF(G85="MARIELA OLMOS GAONA","OOGM010703NX1",IF(G85="LUCIANO MIJAIL ORTEGA MUÑOZ","OEML881105IK2",IF(G85="GUSTAVO HUMBERTO VELAZCO GALVAN","VEGG9211019T1",IF(G85="JESUS AGUSTIN VELAZQUEZ FLORES","VEFJ900303M65",IF(G85="KARLA ESTEFANIA SALAZAR FLORES","SAFK9807277N1",IF(G85="ANGEL TERRAZAS MONROY","TEMA7105035N4")))))))))) -> OOGM010703NX1 | I85: =+B85 -> NOVIEMBRE | J85: 7820 | K85: 0 | N85: =+J85+K85-L85-M85 -> 7820 | O85: =IF(G85="EFREN ABUNDEZ REYNA","37295",IF(G85="LUIS ALEJANDRO HERNANDEZ REYNA","HERL850705AL2",IF(G85="ANA BEATRIZ ESTRADA ARGOTE","37530",IF(G85="SERGIO ROMERO DURAN","RODS620908QAA",IF(G85="MARIELA OLMOS GAONA","37675",IF(G85="LUCIANO MIJAIL ORTEGA MUÑOZ","37297",IF(G85="GUSTAVO HUMBERTO VELAZCO GALVAN","VEGG9211019T1",IF(G85="JESUS AGUSTIN VELAZQUEZ FLORES","VEFJ900303M65",IF(G85="KARLA ESTEFANIA SALAZAR FLORES","SAFK9807277N1",IF(G85="ANGEL TERRAZAS MONROY","TEMA7105035N4")))))))))) -> 37675 | P85: =IF(G85="EFREN ABUNDEZ REYNA","PFAEP",IF(G85="LUIS ALEJANDRO HERNANDEZ REYNA","HERL850705AL2",IF(G85="ANA BEATRIZ ESTRADA ARGOTE","RIF",IF(G85="SERGIO ROMERO DURAN","RODS620908QAA",IF(G85="MARIELA OLMOS GAONA","RESICO",IF(G85="LUCIANO MIJAIL ORTEGA MUÑOZ","RIF",IF(G85="GUSTAVO HUMBERTO VELAZCO GALVAN","VEGG9211019T1",IF(G85="JESUS AGUSTIN VELAZQUEZ FLORES","VEFJ900303M65",IF(G85="KARLA ESTEFANIA SALAZAR FLORES","SAFK9807277N1",IF(G85="ANGEL TERRAZAS MONROY","TEMA7105035N4")))))))))) -> RESICO
A86: =IF(D86>0,MONTH(D86),0) -> 11 | B86: =VLOOKUP(A86,[1]Hoja3!$C$3:$D$14,2,FALSE) -> NOVIEMBRE | C86: 45608 | D86: 45608 | G86: CALIBRACMM DE MEXICO | H86: CME040519990 | I86: =+B86 -> NOVIEMBRE | J86: 1182.7586 | K86: =+J86*0.16 -> 189.24138 | N86: =+J86+K86-L86-M86 -> 1372 | O86: 72210 | P86: MORAL
A87: =IF(D87>0,MONTH(D87),0) -> 11 | B87: =VLOOKUP(A87,[1]Hoja3!$C$3:$D$14,2,FALSE) -> NOVIEMBRE | C87: 45617 | D87: 45617 | G87: OSCAR URIBE CRUZ | H87: UICO7504071PA | I87: =+B87 -> NOVIEMBRE | J87: 380 | K87: =+J87*0.16 -> 60.8 | N87: =+J87+K87-L87-M87 -> 440.8 | O87: 54950 | P87: PFAEP
A88: =IF(D88>0,MONTH(D88),0) -> 11 | B88: =VLOOKUP(A88,[1]Hoja3!$C$3:$D$14,2,FALSE) -> NOVIEMBRE | C88: 45617 | D88: 45617 | G88: ASTUS | H88: AST111025LX3 | I88: =+B88 -> NOVIEMBRE | J88: 450 | K88: =+J88*0.16 -> 72 | N88: =+J88+K88-L88-M88 -> 522 | O88: 53390 | P88: MORAL | Q88: gerardo.gonzalez@directed.com.mx
A89: =IF(D89>0,MONTH(D89),0) -> 11 | B89: =VLOOKUP(A89,[1]Hoja3!$C$3:$D$14,2,FALSE) -> NOVIEMBRE | C89: 45617 | D89: 45617 | G89: MARIELA OLMOS GAONA | H89: =IF(G89="EFREN ABUNDEZ REYNA","AURE7306187IA",IF(G89="LUIS ALEJANDRO HERNANDEZ REYNA","HERL850705AL2",IF(G89="ANA BEATRIZ ESTRADA ARGOTE","EAAA860701UP2",IF(G89="SERGIO ROMERO DURAN","RODS620908QAA",IF(G89="MARIELA OLMOS GAONA","OOGM010703NX1",IF(G89="LUCIANO MIJAIL ORTEGA MUÑOZ","OEML881105IK2",IF(G89="GUSTAVO HUMBERTO VELAZCO GALVAN","VEGG9211019T1",IF(G89="JESUS AGUSTIN VELAZQUEZ FLORES","VEFJ900303M65",IF(G89="KARLA ESTEFANIA SALAZAR FLORES","SAFK9807277N1",IF(G89="ANGEL TERRAZAS MONROY","TEMA7105035N4")))))))))) -> OOGM010703NX1 | I89: =+B89 -> NOVIEMBRE | J89: 6135 | K89: 0 | N89: =+J89+K89-L89-M89 -> 6135 | O89: =IF(G89="EFREN ABUNDEZ REYNA","37295",IF(G89="LUIS ALEJANDRO HERNANDEZ REYNA","HERL850705AL2",IF(G89="ANA BEATRIZ ESTRADA ARGOTE","37530",IF(G89="SERGIO ROMERO DURAN","RODS620908QAA",IF(G89="MARIELA OLMOS GAONA","37675",IF(G89="LUCIANO MIJAIL ORTEGA MUÑOZ","37297",IF(G89="GUSTAVO HUMBERTO VELAZCO GALVAN","VEGG9211019T1",IF(G89="JESUS AGUSTIN VELAZQUEZ FLORES","VEFJ900303M65",IF(G89="KARLA ESTEFANIA SALAZAR FLORES","SAFK9807277N1",IF(G89="ANGEL TERRAZAS MONROY","TEMA7105035N4")))))))))) -> 37675 | P89: =IF(G89="EFREN ABUNDEZ REYNA","PFAEP",IF(G89="LUIS ALEJANDRO HERNANDEZ REYNA","HERL850705AL2",IF(G89="ANA BEATRIZ ESTRADA ARGOTE","RIF",IF(G89="SERGIO ROMERO DURAN","RODS620908QAA",IF(G89="MARIELA OLMOS GAONA","RESICO",IF(G89="LUCIANO MIJAIL ORTEGA MUÑOZ","RIF",IF(G89="GUSTAVO HUMBERTO VELAZCO GALVAN","VEGG9211019T1",IF(G89="JESUS AGUSTIN VELAZQUEZ FLORES","VEFJ900303M65",IF(G89="KARLA ESTEFANIA SALAZAR FLORES","SAFK9807277N1",IF(G89="ANGEL TERRAZAS MONROY","TEMA7105035N4")))))))))) -> RESICO
A90: =IF(D90>0,MONTH(D90),0) -> 11 | B90: =VLOOKUP(A90,[1]Hoja3!$C$3:$D$14,2,FALSE) -> NOVIEMBRE | C90: 45617 | D90: 45617 | G90: ASTUS | H90: AST111025LX3 | I90: =+B90 -> NOVIEMBRE | J90: 960 | K90: =+J90*0.16 -> 153.6 | N90: =+J90+K90-L90-M90 -> 1113.6 | O90: 53390 | P90: MORAL | Q90: gerardo.gonzalez@directed.com.mx
A91: =IF(D91>0,MONTH(D91),0) -> 11 | B91: =VLOOKUP(A91,[1]Hoja3!$C$3:$D$14,2,FALSE) -> NOVIEMBRE | C91: 45621 | D91: 45621 | G91: AUTOSISTEMAS DE TORREON | H91: ATO990618K58 | I91: =+B91 -> NOVIEMBRE | J91: 254.31034 | K91: =+J91*0.16 -> 40.689655 | N91: =+J91+K91-L91-M91 -> 295 | O91: 27297 | P91: MORAL
A92: =IF(D92>0,MONTH(D92),0) -> 11 | B92: =VLOOKUP(A92,[1]Hoja3!$C$3:$D$14,2,FALSE) -> NOVIEMBRE | C92: 45621 | D92: 45621 | G92: EDUARDO FLORES RODRIGUEZ | H92: FORE800801UQ7 | I92: =+B92 -> NOVIEMBRE | J92: 1133.6207 | K92: =+J92*0.16 -> 181.37931 | N92: =+J92+K92-L92-M92 -> 1315 | O92: 50010 | P92: PFAEP
A93: =IF(D93>0,MONTH(D93),0) -> 12 | B93: =VLOOKUP(A93,[1]Hoja3!$C$3:$D$14,2,FALSE) -> DICIEMBRE | C93: 45631 | D93: 45631 | G93: MARIELA OLMOS GAONA | H93: =IF(G93="EFREN ABUNDEZ REYNA","AURE7306187IA",IF(G93="LUIS ALEJANDRO HERNANDEZ REYNA","HERL850705AL2",IF(G93="ANA BEATRIZ ESTRADA ARGOTE","EAAA860701UP2",IF(G93="SERGIO ROMERO DURAN","RODS620908QAA",IF(G93="MARIELA OLMOS GAONA","OOGM010703NX1",IF(G93="LUCIANO MIJAIL ORTEGA MUÑOZ","OEML881105IK2",IF(G93="GUSTAVO HUMBERTO VELAZCO GALVAN","VEGG9211019T1",IF(G93="JESUS AGUSTIN VELAZQUEZ FLORES","VEFJ900303M65",IF(G93="KARLA ESTEFANIA SALAZAR FLORES","SAFK9807277N1",IF(G93="ANGEL TERRAZAS MONROY","TEMA7105035N4")))))))))) -> OOGM010703NX1 | I93: =+B93 -> DICIEMBRE | J93: 6035 | K93: 0 | N93: =+J93+K93-L93-M93 -> 6035 | O93: =IF(G93="EFREN ABUNDEZ REYNA","37295",IF(G93="LUIS ALEJANDRO HERNANDEZ REYNA","HERL850705AL2",IF(G93="ANA BEATRIZ ESTRADA ARGOTE","37530",IF(G93="SERGIO ROMERO DURAN","RODS620908QAA",IF(G93="MARIELA OLMOS GAONA","37675",IF(G93="LUCIANO MIJAIL ORTEGA MUÑOZ","37297",IF(G93="GUSTAVO HUMBERTO VELAZCO GALVAN","VEGG9211019T1",IF(G93="JESUS AGUSTIN VELAZQUEZ FLORES","VEFJ900303M65",IF(G93="KARLA ESTEFANIA SALAZAR FLORES","SAFK9807277N1",IF(G93="ANGEL TERRAZAS MONROY","TEMA7105035N4")))))))))) -> 37675 | P93: =IF(G93="EFREN ABUNDEZ REYNA","PFAEP",IF(G93="LUIS ALEJANDRO HERNANDEZ REYNA","HERL850705AL2",IF(G93="ANA BEATRIZ ESTRADA ARGOTE","RIF",IF(G93="SERGIO ROMERO DURAN","RODS620908QAA",IF(G93="MARIELA OLMOS GAONA","RESICO",IF(G93="LUCIANO MIJAIL ORTEGA MUÑOZ","RIF",IF(G93="GUSTAVO HUMBERTO VELAZCO GALVAN","VEGG9211019T1",IF(G93="JESUS AGUSTIN VELAZQUEZ FLORES","VEFJ900303M65",IF(G93="KARLA ESTEFANIA SALAZAR FLORES","SAFK9807277N1",IF(G93="ANGEL TERRAZAS MONROY","TEMA7105035N4")))))))))) -> RESICO
A94: =IF(D94>0,MONTH(D94),0) -> 12 | B94: =VLOOKUP(A94,[1]Hoja3!$C$3:$D$14,2,FALSE) -> DICIEMBRE | C94: 45631 | D94: 45631 | G94: SINDY JHOANN FLORES CASTELLANOS | H94: FOCS920720Q24 | I94: =+B94 -> DICIEMBRE | J94: 198.28 | K94: =+J94*0.16 -> 31.7248 | N94: =+J94+K94-L94-M94 -> 230.0048 | O94: 76907 | P94: PFAEP
A95: =IF(D95>0,MONTH(D95),0) -> 12 | B95: =VLOOKUP(A95,[1]Hoja3!$C$3:$D$14,2,FALSE) -> DICIEMBRE | C95: 45631 | D95: 45631 | G95: MARIELA OLMOS GAONA | H95: =IF(G95="EFREN ABUNDEZ REYNA","AURE7306187IA",IF(G95="LUIS ALEJANDRO HERNANDEZ REYNA","HERL850705AL2",IF(G95="ANA BEATRIZ ESTRADA ARGOTE","EAAA860701UP2",IF(G95="SERGIO ROMERO DURAN","RODS620908QAA",IF(G95="MARIELA OLMOS GAONA","OOGM010703NX1",IF(G95="LUCIANO MIJAIL ORTEGA MUÑOZ","OEML881105IK2",IF(G95="GUSTAVO HUMBERTO VELAZCO GALVAN","VEGG9211019T1",IF(G95="JESUS AGUSTIN VELAZQUEZ FLORES","VEFJ900303M65",IF(G95="KARLA ESTEFANIA SALAZAR FLORES","SAFK9807277N1",IF(G95="ANGEL TERRAZAS MONROY","TEMA7105035N4")))))))))) -> OOGM010703NX1 | I95: =+B95 -> DICIEMBRE | J95: 4065 | K95: 0 | N95: =+J95+K95-L95-M95 -> 4065 | O95: =IF(G95="EFREN ABUNDEZ REYNA","37295",IF(G95="LUIS ALEJANDRO HERNANDEZ REYNA","HERL850705AL2",IF(G95="ANA BEATRIZ ESTRADA ARGOTE","37530",IF(G95="SERGIO ROMERO DURAN","RODS620908QAA",IF(G95="MARIELA OLMOS GAONA","37675",IF(G95="LUCIANO MIJAIL ORTEGA MUÑOZ","37297",IF(G95="GUSTAVO HUMBERTO VELAZCO GALVAN","VEGG9211019T1",IF(G95="JESUS AGUSTIN VELAZQUEZ FLORES","VEFJ900303M65",IF(G95="KARLA ESTEFANIA SALAZAR FLORES","SAFK9807277N1",IF(G95="ANGEL TERRAZAS MONROY","TEMA7105035N4")))))))))) -> 37675 | P95: =IF(G95="EFREN ABUNDEZ REYNA","PFAEP",IF(G95="LUIS ALEJANDRO HERNANDEZ REYNA","HERL850705AL2",IF(G95="ANA BEATRIZ ESTRADA ARGOTE","RIF",IF(G95="SERGIO ROMERO DURAN","RODS620908QAA",IF(G95="MARIELA OLMOS GAONA","RESICO",IF(G95="LUCIANO MIJAIL ORTEGA MUÑOZ","RIF",IF(G95="GUSTAVO HUMBERTO VELAZCO GALVAN","VEGG9211019T1",IF(G95="JESUS AGUSTIN VELAZQUEZ FLORES","VEFJ900303M65",IF(G95="KARLA ESTEFANIA SALAZAR FLORES","SAFK9807277N1",IF(G95="ANGEL TERRAZAS MONROY","TEMA7105035N4")))))))))) -> RESICO
A96: =IF(D96>0,MONTH(D96),0) -> 12 | B96: =VLOOKUP(A96,[1]Hoja3!$C$3:$D$14,2,FALSE) -> DICIEMBRE | C96: 45631 | D96: 45631 | G96: FARMACIA GUADALAJARA | H96: FGU830930PD3 | I96: =+B96 -> DICIEMBRE | J96: 790 | K96: =+J96*0.16 -> 126.4 | N96: =+J96+K96-L96-M96 -> 916.4 | O96: 44610 | P96: MORAL
A97: =IF(D97>0,MONTH(D97),0) -> 12 | B97: =VLOOKUP(A97,[1]Hoja3!$C$3:$D$14,2,FALSE) -> DICIEMBRE | C97: 45631 | D97: 45631 | G97: TEC&O&SET | H97: TEC2303144V4 | I97: =+B97 -> DICIEMBRE | J97: 320 | K97: =+J97*0.16 -> 51.2 | N97: =+J97+K97-L97-M97 -> 371.2 | O97: 11000 | P97: MORAL
A98: =IF(D98>0,MONTH(D98),0) -> 12 | B98: =VLOOKUP(A98,[1]Hoja3!$C$3:$D$14,2,FALSE) -> DICIEMBRE | C98: 45632 | D98: 45632 | G98: REDPACK | H98: RED940114JX9 | I98: =+B98 -> DICIEMBRE | J98: 172.41 | K98: =+J98*0.16 -> 27.5856 | N98: =+J98+K98-L98-M98 -> 199.9956 | O98: 2120 | P98: MORAL | Q98: h.barrera@redpack.com.mx
A99: =IF(D99>0,MONTH(D99),0) -> 12 | B99: =VLOOKUP(A99,[1]Hoja3!$C$3:$D$14,2,FALSE) -> DICIEMBRE | C99: 45632 | D99: 45632 | G99: REDPACK | H99: RED940114JX9 | I99: =+B99 -> DICIEMBRE | J99: 297.41 | K99: =+J99*0.16 -> 47.5856 | N99: =+J99+K99-L99-M99 -> 344.9956 | O99: 2120 | P99: MORAL | Q99: h.barrera@redpack.com.mx
A100: =IF(D100>0,MONTH(D100),0) -> 12 | B100: =VLOOKUP(A100,[1]Hoja3!$C$3:$D$14,2,FALSE) -> DICIEMBRE | C100: 45632 | D100: 45632 | G100: REDPACK | H100: RED940114JX9 | I100: =+B100 -> DICIEMBRE | J100: 198.28 | K100: =+J100*0.16 -> 31.7248 | N100: =+J100+K100-L100-M100 -> 230.0048 | O100: 2120 | P100: MORAL | Q100: h.barrera@redpack.com.mx
...

Sheet EGR
A1: MES | B1: MES | C1: FECHA | D1: PROVEEDOR | E1: RFC | F1: FACTURA | H1: GASTO TOTAL | J1: IVA | L1: TASA 16% | M1: TASA 0 % | N1: TOTAL | O1: F. D PAGO | P1: monto total | Q1: diferencia
A2: =IF(C2>0,MONTH(C2),0) -> 1 | B2: =VLOOKUP(A2,[1]Hoja3!$C$3:$D$14,2,FALSE) -> ENERO | C2: 45293.768 | D2: BANCO DEL BAJIO | E2: BBA940707IE1 | F2: M | G2: =+B2 -> ENERO | H2: 1164.4 | I2: =+B2 -> ENERO | J2: 186.3 | K2: =+B2 -> ENERO | L2: =+J2/0.16 -> 1164.375 | M2: =+H2-L2 -> 0.025 | N2: =+H2+J2 -> 1350.7 | O2: PUE | P2: =+N2 -> 1350.7 | Q2: =+N2-P2 -> 0
A3: =IF(C3>0,MONTH(C3),0) -> 1 | B3: =VLOOKUP(A3,[1]Hoja3!$C$3:$D$14,2,FALSE) -> ENERO | C3: 45293.998 | D3: HERIBERTO JIMENEZ AVILA | E3: JIAH810501A8A | F3: F696 | G3: =+B3 -> ENERO | H3: 33524 | I3: =+B3 -> ENERO | J3: 0 | K3: =+B3 -> ENERO | L3: =+J3/0.16 -> 0 | M3: =+H3-L3 -> 33524 | N3: =+H3+J3 -> 33524 | O3: PUE | P3: =+N3 -> 33524 | Q3: =+N3-P3 -> 0
A4: =IF(C4>0,MONTH(C4),0) -> 1 | B4: =VLOOKUP(A4,[1]Hoja3!$C$3:$D$14,2,FALSE) -> ENERO | C4: 45294.747 | D4: NOEMI ROSALIA REYES ANDRADE | E4: REAN920904CM3 | F4: A799 | G4: =+B4 -> ENERO | H4: 1928.45 | I4: =+B4 -> ENERO | J4: 308.55 | K4: =+B4 -> ENERO | L4: =+J4/0.16 -> 1928.4375 | M4: =+H4-L4 -> 0.0125 | N4: =+H4+J4 -> 2237 | O4: PUE | P4: =+N4 -> 2237 | Q4: =+N4-P4 -> 0
A5: =IF(C5>0,MONTH(C5),0) -> 1 | B5: =VLOOKUP(A5,[1]Hoja3!$C$3:$D$14,2,FALSE) -> ENERO | C5: 45296.703 | D5: MEGA GASOLINERAS | E5: MGA110810CC3 | F5: PTIN7994 | G5: =+B5 -> ENERO | H5: 432.66 | I5: =+B5 -> ENERO | J5: 67.34 | K5: =+B5 -> ENERO | L5: =+J5/0.16 -> 420.875 | M5: =+H5-L5 -> 11.785 | N5: =+H5+J5 -> 500 | O5: PUE | P5: =+N5 -> 500 | Q5: =+N5-P5 -> 0
A6: =IF(C6>0,MONTH(C6),0) -> 1 | B6: =VLOOKUP(A6,[1]Hoja3!$C$3:$D$14,2,FALSE) -> ENERO | C6: 45299.401 | D6: BANCOPPEL, S.A. INSTITUCION DE BANCA MULTIPLE | E6: BSI061110963 | F6: 202410144717444 | G6: =+B6 -> ENERO | H6: 0.01 | I6: =+B6 -> ENERO | K6: =+B6 -> ENERO | L6: =+J6/0.16 -> 0 | M6: =+H6-L6 -> 0.01 | N6: =+H6+J6 -> 0.01 | O6: PUE | P6: =+N6 -> 0.01 | Q6: =+N6-P6 -> 0
A7: =IF(C7>0,MONTH(C7),0) -> 1 | B7: =VLOOKUP(A7,[1]Hoja3!$C$3:$D$14,2,FALSE) -> ENERO | C7: 45299.964 | D7: HERIBERTO JIMENEZ AVILA | E7: JIAH810501A8A | F7: F697 | G7: =+B7 -> ENERO | H7: 20000 | I7: =+B7 -> ENERO | J7: 0 | K7: =+B7 -> ENERO | L7: =+J7/0.16 -> 0 | M7: =+H7-L7 -> 20000 | N7: =+H7+J7 -> 20000 | O7: PUE | P7: =+N7 -> 20000 | Q7: =+N7-P7 -> 0
A8: =IF(C8>0,MONTH(C8),0) -> 1 | B8: =VLOOKUP(A8,[1]Hoja3!$C$3:$D$14,2,FALSE) -> ENERO | C8: 45300.507 | D8: SAN JORGE Y CIA. | E8: SJC080617R86 | F8: MAD7632 | G8: =+B8 -> ENERO | H8: 11607.22 | I8: =+B8 -> ENERO | J8: 0 | K8: =+B8 -> ENERO | L8: =+J8/0.16 -> 0 | M8: =+H8-L8 -> 11607.22 | N8: =+H8+J8 -> 11607.22 | O8: PUE | P8: =+N8 -> 11607.22 | Q8: =+N8-P8 -> 0
A9: =IF(C9>0,MONTH(C9),0) -> 1 | B9: =VLOOKUP(A9,[1]Hoja3!$C$3:$D$14,2,FALSE) -> ENERO | C9: 45301.471 | D9: MARIA GRICELDA BARAJAS OLIVA | E9: BAOG961112Q60 | F9: 1742 | G9: =+B9 -> ENERO | H9: 45019 | I9: =+B9 -> ENERO | J9: 0 | K9: =+B9 -> ENERO | L9: =+J9/0.16 -> 0 | M9: =+H9-L9 -> 45019 | N9: =+H9+J9 -> 45019 | O9: PUE | P9: =+N9 -> 45019 | Q9: =+N9-P9 -> 0
A10: =IF(C10>0,MONTH(C10),0) -> 1 | B10: =VLOOKUP(A10,[1]Hoja3!$C$3:$D$14,2,FALSE) -> ENERO | C10: 45301.532 | D10: J. SOCORRO ALMANZA CARRILLO | E10: AACJ680307H3A | F10: 7 | G10: =+B10 -> ENERO | H10: 16250 | I10: =+B10 -> ENERO | J10: 0 | K10: =+B10 -> ENERO | L10: =+J10/0.16 -> 0 | M10: =+H10-L10 -> 16250 | N10: =+H10+J10 -> 16250 | O10: PUE | P10: =+N10 -> 16250 | Q10: =+N10-P10 -> 0
A11: =IF(C11>0,MONTH(C11),0) -> 1 | B11: =VLOOKUP(A11,[1]Hoja3!$C$3:$D$14,2,FALSE) -> ENERO | C11: 45301.532 | D11: J. SOCORRO ALMANZA CARRILLO | E11: AACJ680307H3A | F11: 8 | G11: =+B11 -> ENERO | H11: 19000 | I11: =+B11 -> ENERO | J11: 0 | K11: =+B11 -> ENERO | L11: =+J11/0.16 -> 0 | M11: =+H11-L11 -> 19000 | N11: =+H11+J11 -> 19000 | O11: PUE | P11: =+N11 -> 19000 | Q11: =+N11-P11 -> 0
A12: =IF(C12>0,MONTH(C12),0) -> 1 | B12: =VLOOKUP(A12,[1]Hoja3!$C$3:$D$14,2,FALSE) -> ENERO | C12: 45303.517 | D12: MINIBODEGAS Y ALMACENAMIENTO MEXICO | E12: MAL1511111U9 | F12: C1057 | G12: =+B12 -> ENERO | H12: 2155.17 | I12: =+B12 -> ENERO | J12: 344.8272 | K12: =+B12 -> ENERO | L12: =+J12/0.16 -> 2155.17 | M12: =+H12-L12 -> 0 | N12: =+H12+J12 -> 2499.9972 | O12: PUE | P12: =+N12 -> 2499.9972 | Q12: =+N12-P12 -> 0
A13: =IF(C13>0,MONTH(C13),0) -> 1 | B13: =VLOOKUP(A13,[1]Hoja3!$C$3:$D$14,2,FALSE) -> ENERO | C13: 45303.52 | D13: MINIBODEGAS Y ALMACENAMIENTO MEXICO | E13: MAL1511111U9 | F13: C1058 | G13: =+B13 -> ENERO | H13: 2500 | I13: =+B13 -> ENERO | J13: 400 | K13: =+B13 -> ENERO | L13: =+J13/0.16 -> 2500 | M13: =+H13-L13 -> 0 | N13: =+H13+J13 -> 2900 | O13: PUE | P13: =+N13 -> 2900 | Q13: =+N13-P13 -> 0
A14: =IF(C14>0,MONTH(C14),0) -> 1 | B14: =VLOOKUP(A14,[1]Hoja3!$C$3:$D$14,2,FALSE) -> ENERO | C14: 45306.481 | D14: DOS MIL GAS | E14: DMG9212301D0 | F14: COFCO0334326 | G14: =+B14 -> ENERO | H14: 465.26 | I14: =+B14 -> ENERO | J14: 74.44 | K14: =+B14 -> ENERO | L14: =+J14/0.16 -> 465.25 | M14: =+H14-L14 -> 0.01 | N14: =+H14+J14 -> 539.7 | O14: PUE | P14: =+N14 -> 539.7 | Q14: =+N14-P14 -> 0
A15: =IF(C15>0,MONTH(C15),0) -> 1 | B15: =VLOOKUP(A15,[1]Hoja3!$C$3:$D$14,2,FALSE) -> ENERO | C15: 45307.531 | D15: MEGA GASOLINERAS | E15: MGA110810CC3 | F15: EMS53007 | G15: =+B15 -> ENERO | H15: 259.6 | I15: =+B15 -> ENERO | J15: 40.4 | K15: =+B15 -> ENERO | L15: =+J15/0.16 -> 252.5 | M15: =+H15-L15 -> 7.1 | N15: =+H15+J15 -> 300 | O15: PUE | P15: =+N15 -> 300 | Q15: =+N15-P15 -> 0
A16: =IF(C16>0,MONTH(C16),0) -> 1 | B16: =VLOOKUP(A16,[1]Hoja3!$C$3:$D$14,2,FALSE) -> ENERO | C16: 45307.533 | D16: MEGA GASOLINERAS | E16: MGA110810CC3 | F16: EMS53008 | G16: =+B16 -> ENERO | H16: 432.67 | I16: =+B16 -> ENERO | J16: 67.33 | K16: =+B16 -> ENERO | L16: =+J16/0.16 -> 420.8125 | M16: =+H16-L16 -> 11.8575 | N16: =+H16+J16 -> 500 | O16: PUE | P16: =+N16 -> 500 | Q16: =+N16-P16 -> 0
A17: =IF(C17>0,MONTH(C17),0) -> 1 | B17: =VLOOKUP(A17,[1]Hoja3!$C$3:$D$14,2,FALSE) -> ENERO | C17: 45307.84 | D17: MEGA GASOLINERAS | E17: MGA110810CC3 | F17: LIB374820 | G17: =+B17 -> ENERO | H17: 1048.19 | I17: =+B17 -> ENERO | J17: 163.11 | K17: =+B17 -> ENERO | L17: =+J17/0.16 -> 1019.4375 | M17: =+H17-L17 -> 28.7525 | N17: =+H17+J17 -> 1211.3 | O17: PUE | P17: =+N17 -> 1211.3 | Q17: =+N17-P17 -> 0
A18: =IF(C18>0,MONTH(C18),0) -> 1 | B18: =VLOOKUP(A18,[1]Hoja3!$C$3:$D$14,2,FALSE) -> ENERO | C18: 45309.418 | D18: SOCIEDAD COOPERATIVA DE PRODUCCION PESQUERA 21 DE MARZO | E18: SCP680430MF0 | F18: 14247 | G18: =+B18 -> ENERO | H18: 1800 | I18: =+B18 -> ENERO | J18: 0 | K18: =+B18 -> ENERO | L18: =+J18/0.16 -> 0 | M18: =+H18-L18 -> 1800 | N18: =+H18+J18 -> 1800 | O18: PUE | P18: =+N18 -> 1800 | Q18: =+N18-P18 -> 0
A19: =IF(C19>0,MONTH(C19),0) -> 1 | B19: =VLOOKUP(A19,[1]Hoja3!$C$3:$D$14,2,FALSE) -> ENERO | C19: 45309.428 | D19: RADIOMOVIL DIPSA | E19: RDI841003QJ4 | F19: PF0059735866 | G19: =+B19 -> ENERO | H19: 0 | I19: =+B19 -> ENERO | K19: =+B19 -> ENERO | L19: =+J19/0.16 -> 0 | M19: =+H19-L19 -> 0 | N19: =+H19+J19 -> 0 | P19: =+N19 -> 0 | Q19: =+N19-P19 -> 0
A20: =IF(C20>0,MONTH(C20),0) -> 1 | B20: =VLOOKUP(A20,[1]Hoja3!$C$3:$D$14,2,FALSE) -> ENERO | C20: 45309.628 | D20: PESCADERIA BUENA OLA | E20: PBO200626IW3 | F20: BO4814 | G20: =+B20 -> ENERO | H20: 37512.5 | I20: =+B20 -> ENERO | J20: 0 | K20: =+B20 -> ENERO | L20: =+J20/0.16 -> 0 | M20: =+H20-L20 -> 37512.5 | N20: =+H20+J20 -> 37512.5 | O20: PUE | P20: =+N20 -> 37512.5 | Q20: =+N20-P20 -> 0
A21: =IF(C21>0,MONTH(C21),0) -> 1 | B21: =VLOOKUP(A21,[1]Hoja3!$C$3:$D$14,2,FALSE) -> ENERO | C21: 45309.987 | D21: HERIBERTO JIMENEZ AVILA | E21: JIAH810501A8A | F21: F699 | G21: =+B21 -> ENERO | H21: 23191 | I21: =+B21 -> ENERO | J21: 0 | K21: =+B21 -> ENERO | L21: =+J21/0.16 -> 0 | M21: =+H21-L21 -> 23191 | N21: =+H21+J21 -> 23191 | O21: PUE | P21: =+N21 -> 23191 | Q21: =+N21-P21 -> 0
A22: =IF(C22>0,MONTH(C22),0) -> 1 | B22: =VLOOKUP(A22,[1]Hoja3!$C$3:$D$14,2,FALSE) -> ENERO | C22: 45312.367 | D22: TOTAL PLAY TELECOMUNICACIONES | E22: TPT890516JP5 | F22: TP347305631453697353P1-332231403T1-0 | G22: =+B22 -> ENERO | H22: 0 | I22: =+B22 -> ENERO | K22: =+B22 -> ENERO | L22: =+J22/0.16 -> 0 | M22: =+H22-L22 -> 0 | N22: =+H22+J22 -> 0 | P22: =+N22 -> 0 | Q22: =+N22-P22 -> 0
A23: =IF(C23>0,MONTH(C23),0) -> 1 | B23: =VLOOKUP(A23,[1]Hoja3!$C$3:$D$14,2,FALSE) -> ENERO | C23: 45312.367 | D23: TOTAL BOX | E23: TBO140305DH0 | F23: TP347305631453696841P1-332231403T1-4 | G23: =+B23 -> ENERO | H23: 0 | I23: =+B23 -> ENERO | K23: =+B23 -> ENERO | L23: =+J23/0.16 -> 0 | M23: =+H23-L23 -> 0 | N23: =+H23+J23 -> 0 | P23: =+N23 -> 0 | Q23: =+N23-P23 -> 0
A24: =IF(C24>0,MONTH(C24),0) -> 1 | B24: =VLOOKUP(A24,[1]Hoja3!$C$3:$D$14,2,FALSE) -> ENERO | C24: 45312.86 | D24: MEGA GASOLINERAS | E24: MGA110810CC3 | F24: LIB375119 | G24: =+B24 -> ENERO | H24: 1127.68 | I24: =+B24 -> ENERO | J24: 175.49 | K24: =+B24 -> ENERO | L24: =+J24/0.16 -> 1096.8125 | M24: =+H24-L24 -> 30.8675 | N24: =+H24+J24 -> 1303.17 | O24: PUE | P24: =+N24 -> 1303.17 | Q24: =+N24-P24 -> 0
A25: =IF(C25>0,MONTH(C25),0) -> 1 | B25: =VLOOKUP(A25,[1]Hoja3!$C$3:$D$14,2,FALSE) -> ENERO | C25: 45314.716 | D25: SAN JORGE Y CIA. | E25: SJC080617R86 | F25: MAD7691 | G25: =+B25 -> ENERO | H25: 1994.16 | I25: =+B25 -> ENERO | J25: 0 | K25: =+B25 -> ENERO | L25: =+J25/0.16 -> 0 | M25: =+H25-L25 -> 1994.16 | N25: =+H25+J25 -> 1994.16 | O25: PUE | P25: =+N25 -> 1994.16 | Q25: =+N25-P25 -> 0
A26: =IF(C26>0,MONTH(C26),0) -> 1 | B26: =VLOOKUP(A26,[1]Hoja3!$C$3:$D$14,2,FALSE) -> ENERO | C26: 45314.716 | D26: SAN JORGE Y CIA. | E26: SJC080617R86 | F26: MAD7692 | G26: =+B26 -> ENERO | H26: 1942.68 | I26: =+B26 -> ENERO | J26: 0 | K26: =+B26 -> ENERO | L26: =+J26/0.16 -> 0 | M26: =+H26-L26 -> 1942.68 | N26: =+H26+J26 -> 1942.68 | O26: PUE | P26: =+N26 -> 1942.68 | Q26: =+N26-P26 -> 0
A27: =IF(C27>0,MONTH(C27),0) -> 1 | B27: =VLOOKUP(A27,[1]Hoja3!$C$3:$D$14,2,FALSE) -> ENERO | C27: 45314.717 | D27: SAN JORGE Y CIA. | E27: SJC080617R86 | F27: MAD7693 | G27: =+B27 -> ENERO | H27: 1837.28 | I27: =+B27 -> ENERO | J27: 0 | K27: =+B27 -> ENERO | L27: =+J27/0.16 -> 0 | M27: =+H27-L27 -> 1837.28 | N27: =+H27+J27 -> 1837.28 | O27: PUE | P27: =+N27 -> 1837.28 | Q27: =+N27-P27 -> 0
A28: =IF(C28>0,MONTH(C28),0) -> 1 | B28: =VLOOKUP(A28,[1]Hoja3!$C$3:$D$14,2,FALSE) -> ENERO | C28: 45314.717 | D28: SAN JORGE Y CIA. | E28: SJC080617R86 | F28: MAD7694 | G28: =+B28 -> ENERO | H28: 1998.48 | I28: =+B28 -> ENERO | J28: 0 | K28: =+B28 -> ENERO | L28: =+J28/0.16 -> 0 | M28: =+H28-L28 -> 1998.48 | N28: =+H28+J28 -> 1998.48 | O28: PUE | P28: =+N28 -> 1998.48 | Q28: =+N28-P28 -> 0
A29: =IF(C29>0,MONTH(C29),0) -> 1 | B29: =VLOOKUP(A29,[1]Hoja3!$C$3:$D$14,2,FALSE) -> ENERO | C29: 45314.717 | D29: SAN JORGE Y CIA. | E29: SJC080617R86 | F29: MAD7695 | G29: =+B29 -> ENERO | H29: 929.04 | I29: =+B29 -> ENERO | J29: 0 | K29: =+B29 -> ENERO | L29: =+J29/0.16 -> 0 | M29: =+H29-L29 -> 929.04 | N29: =+H29+J29 -> 929.04 | O29: PUE | P29: =+N29 -> 929.04 | Q29: =+N29-P29 -> 0
A30: =IF(C30>0,MONTH(C30),0) -> 1 | B30: =VLOOKUP(A30,[1]Hoja3!$C$3:$D$14,2,FALSE) -> ENERO | C30: 45315.005 | D30: HERIBERTO JIMENEZ AVILA | E30: JIAH810501A8A | F30: F704 | G30: =+B30 -> ENERO | H30: 20000 | I30: =+B30 -> ENERO | J30: 0 | K30: =+B30 -> ENERO | L30: =+J30/0.16 -> 0 | M30: =+H30-L30 -> 20000 | N30: =+H30+J30 -> 20000 | O30: PUE | P30: =+N30 -> 20000 | Q30: =+N30-P30 -> 0
A31: =IF(C31>0,MONTH(C31),0) -> 1 | B31: =VLOOKUP(A31,[1]Hoja3!$C$3:$D$14,2,FALSE) -> ENERO | C31: 45316.847 | D31: MEGA GASOLINERAS | E31: MGA110810CC3 | F31: DEL22567 | G31: =+B31 -> ENERO | H31: 984.34 | I31: =+B31 -> ENERO | J31: 153.18 | K31: =+B31 -> ENERO | L31: =+J31/0.16 -> 957.375 | M31: =+H31-L31 -> 26.965 | N31: =+H31+J31 -> 1137.52 | O31: PUE | P31: =+N31 -> 1137.52 | Q31: =+N31-P31 -> 0
A32: =IF(C32>0,MONTH(C32),0) -> 1 | B32: =VLOOKUP(A32,[1]Hoja3!$C$3:$D$14,2,FALSE) -> ENERO | C32: 45317.973 | D32: MARIA GRICELDA BARAJAS OLIVA | E32: BAOG961112Q60 | F32: 1808 | G32: =+B32 -> ENERO | H32: 11620 | I32: =+B32 -> ENERO | J32: 0 | K32: =+B32 -> ENERO | L32: =+J32/0.16 -> 0 | M32: =+H32-L32 -> 11620 | N32: =+H32+J32 -> 11620 | O32: PUE | P32: =+N32 -> 11620 | Q32: =+N32-P32 -> 0
A33: =IF(C33>0,MONTH(C33),0) -> 1 | B33: =VLOOKUP(A33,[1]Hoja3!$C$3:$D$14,2,FALSE) -> ENERO | C33: 45319.549 | D33: BANCOPPEL, S.A. INSTITUCION DE BANCA MULTIPLE | E33: BSI061110963 | F33: 202410052174142 | G33: =+B33 -> ENERO | H33: 0.01 | I33: =+B33 -> ENERO | K33: =+B33 -> ENERO | L33: =+J33/0.16 -> 0 | M33: =+H33-L33 -> 0.01 | N33: =+H33+J33 -> 0.01 | O33: PUE | P33: =+N33 -> 0.01 | Q33: =+N33-P33 -> 0
A34: =IF(C34>0,MONTH(C34),0) -> 1 | B34: =VLOOKUP(A34,[1]Hoja3!$C$3:$D$14,2,FALSE) -> ENERO | C34: 45322.405 | D34: GUSTAVO HUMBERTO VELASCO GALVEZ | E34: VEGG9211019T1 | F34: A213 | G34: =+B34 -> ENERO | H34: 8500 | I34: =+B34 -> ENERO | J34: 0 | K34: =+B34 -> ENERO | L34: =+J34/0.16 -> 0 | M34: =+H34-L34 -> 8500 | N34: =+H34+J34 -> 8500 | O34: PUE | P34: =+N34 -> 8500 | Q34: =+N34-P34 -> 0
A35: =IF(C35>0,MONTH(C35),0) -> 1 | B35: =VLOOKUP(A35,[1]Hoja3!$C$3:$D$14,2,FALSE) -> ENERO | C35: 45322.406 | D35: GUSTAVO HUMBERTO VELASCO GALVEZ | E35: VEGG9211019T1 | F35: A214 | G35: =+B35 -> ENERO | H35: 1880 | I35: =+B35 -> ENERO | J35: 0 | K35: =+B35 -> ENERO | L35: =+J35/0.16 -> 0 | M35: =+H35-L35 -> 1880 | N35: =+H35+J35 -> 1880 | O35: PUE | P35: =+N35 -> 1880 | Q35: =+N35-P35 -> 0
A36: =IF(C36>0,MONTH(C36),0) -> 1 | B36: =VLOOKUP(A36,[1]Hoja3!$C$3:$D$14,2,FALSE) -> ENERO | C36: 45322.807 | D36: JULIO ANTONIO AMEZQUITA MARTINEZ | E36: AEMJ850627FFA | G36: =+B36 -> ENERO | H36: 1980 | I36: =+B36 -> ENERO | J36: 0 | K36: =+B36 -> ENERO | L36: =+J36/0.16 -> 0 | M36: =+H36-L36 -> 1980 | N36: =+H36+J36 -> 1980 | O36: PUE | P36: =+N36 -> 1980 | Q36: =+N36-P36 -> 0
A37: =IF(C37>0,MONTH(C37),0) -> 1 | B37: =VLOOKUP(A37,[1]Hoja3!$C$3:$D$14,2,FALSE) -> ENERO | C37: 45322.809 | D37: JULIO ANTONIO AMEZQUITA MARTINEZ | E37: AEMJ850627FFA | G37: =+B37 -> ENERO | H37: 1980 | I37: =+B37 -> ENERO | J37: 0 | K37: =+B37 -> ENERO | L37: =+J37/0.16 -> 0 | M37: =+H37-L37 -> 1980 | N37: =+H37+J37 -> 1980 | O37: PUE | P37: =+N37 -> 1980 | Q37: =+N37-P37 -> 0
A38: =IF(C38>0,MONTH(C38),0) -> 1 | B38: =VLOOKUP(A38,[1]Hoja3!$C$3:$D$14,2,FALSE) -> ENERO | C38: 45322.81 | D38: JULIO ANTONIO AMEZQUITA MARTINEZ | E38: AEMJ850627FFA | G38: =+B38 -> ENERO | H38: 1980 | I38: =+B38 -> ENERO | J38: 0 | K38: =+B38 -> ENERO | L38: =+J38/0.16 -> 0 | M38: =+H38-L38 -> 1980 | N38: =+H38+J38 -> 1980 | O38: PUE | P38: =+N38 -> 1980 | Q38: =+N38-P38 -> 0
A39: =IF(C39>0,MONTH(C39),0) -> 1 | B39: =VLOOKUP(A39,[1]Hoja3!$C$3:$D$14,2,FALSE) -> ENERO | C39: 45322.812 | D39: JULIO ANTONIO AMEZQUITA MARTINEZ | E39: AEMJ850627FFA | G39: =+B39 -> ENERO | H39: 660 | I39: =+B39 -> ENERO | J39: 0 | K39: =+B39 -> ENERO | L39: =+J39/0.16 -> 0 | M39: =+H39-L39 -> 660 | N39: =+H39+J39 -> 660 | O39: PUE | P39: =+N39 -> 660 | Q39: =+N39-P39 -> 0
A40: =IF(C40>0,MONTH(C40),0) -> 1 | B40: =VLOOKUP(A40,[1]Hoja3!$C$3:$D$14,2,FALSE) -> ENERO | C40: 45322.814 | D40: MEGA GASOLINERAS | E40: MGA110810CC3 | F40: DEL22668 | G40: =+B40 -> ENERO | H40: 982.49 | I40: =+B40 -> ENERO | J40: 152.91 | K40: =+B40 -> ENERO | L40: =+J40/0.16 -> 955.6875 | M40: =+H40-L40 -> 26.8025 | N40: =+H40+J40 -> 1135.4 | O40: PUE | P40: =+N40 -> 1135.4 | Q40: =+N40-P40 -> 0
A41: =IF(C41>0,MONTH(C41),0) -> 1 | B41: =VLOOKUP(A41,[1]Hoja3!$C$3:$D$14,2,FALSE) -> ENERO | C41: 45322.96 | D41: MARIA GRICELDA BARAJAS OLIVA | E41: BAOG961112Q60 | F41: 1834 | G41: =+B41 -> ENERO | H41: 25000 | I41: =+B41 -> ENERO | J41: 0 | K41: =+B41 -> ENERO | L41: =+J41/0.16 -> 0 | M41: =+H41-L41 -> 25000 | N41: =+H41+J41 -> 25000 | O41: PUE | P41: =+N41 -> 25000 | Q41: =+N41-P41 -> 0
A42: =IF(C42>0,MONTH(C42),0) -> 2 | B42: =VLOOKUP(A42,[1]Hoja3!$C$3:$D$14,2,FALSE) -> FEBRERO | C42: 45323.573 | D42: MA. DEL ROSARIO CASTILLO GONZALEZ | E42: CAGM570916DJ2 | F42: 407 | H42: 3712 | I42: =+B42 -> FEBRERO | J42: =+H42*0.16 -> 593.92 | K42: =+B42 -> FEBRERO | L42: =+J42/0.16 -> 3712 | M42: =+H42-L42 -> 0 | N42: =+H42+J42 -> 4305.92 | O42: PUE | P42: =+N42 -> 4305.92 | Q42: =+N42-P42 -> 0
A43: =IF(C43>0,MONTH(C43),0) -> 2 | B43: =VLOOKUP(A43,[1]Hoja3!$C$3:$D$14,2,FALSE) -> FEBRERO | C43: 45323.828 | D43: BANCO DEL BAJIO | E43: BBA940707IE1 | F43: M | H43: 629.82 | I43: =+B43 -> FEBRERO | J43: =+H43*0.16 -> 100.7712 | K43: =+B43 -> FEBRERO | L43: =+J43/0.16 -> 629.82 | M43: =+H43-L43 -> 0 | N43: =+H43+J43 -> 730.5912 | O43: PUE | P43: =+N43 -> 730.5912 | Q43: =+N43-P43 -> 0
A44: =IF(C44>0,MONTH(C44),0) -> 2 | B44: =VLOOKUP(A44,[1]Hoja3!$C$3:$D$14,2,FALSE) -> FEBRERO | C44: 45328.59 | D44: SAN JORGE Y CIA. | E44: SJC080617R86 | F44: MAD7757 | G44: =+B44 -> FEBRERO | H44: 7671.47 | I44: =+B44 -> FEBRERO | J44: =+H44*0.16 -> 1227.4352 | K44: =+B44 -> FEBRERO | L44: =+J44/0.16 -> 7671.47 | M44: =+H44-L44 -> 0 | N44: =+H44+J44 -> 8898.9052 | O44: PUE | P44: =+N44 -> 8898.9052 | Q44: =+N44-P44 -> 0
A45: =IF(C45>0,MONTH(C45),0) -> 2 | B45: =VLOOKUP(A45,[1]Hoja3!$C$3:$D$14,2,FALSE) -> FEBRERO | C45: 45328.644 | D45: JOSE ELIAS MOJICA MUÑOZ | E45: MOME7010105K2 | F45: AC7330 | G45: =+B45 -> FEBRERO | H45: 985.77 | I45: =+B45 -> FEBRERO | J45: =+H45*0.16 -> 157.7232 | K45: =+B45 -> FEBRERO | L45: =+J45/0.16 -> 985.77 | M45: =+H45-L45 -> 0 | N45: =+H45+J45 -> 1143.4932 | O45: PUE | P45: =+N45 -> 1143.4932 | Q45: =+N45-P45 -> 0
A46: =IF(C46>0,MONTH(C46),0) -> 2 | B46: =VLOOKUP(A46,[1]Hoja3!$C$3:$D$14,2,FALSE) -> FEBRERO | C46: 45329.506 | D46: SOCIEDAD COOPERATIVA DE PRODUCCION PESQUERA 21 DE MARZO | E46: SCP680430MF0 | F46: 14336 | G46: =+B46 -> FEBRERO | H46: 3960 | I46: =+B46 -> FEBRERO | J46: =+H46*0.16 -> 633.6 | K46: =+B46 -> FEBRERO | L46: =+J46/0.16 -> 3960 | M46: =+H46-L46 -> 0 | N46: =+H46+J46 -> 4593.6 | O46: PUE | P46: =+N46 -> 4593.6 | Q46: =+N46-P46 -> 0
A47: =IF(C47>0,MONTH(C47),0) -> 2 | B47: =VLOOKUP(A47,[1]Hoja3!$C$3:$D$14,2,FALSE) -> FEBRERO | C47: 45329.751 | D47: PESCADERIA BUENA OLA | E47: PBO200626IW3 | F47: BO4991 | G47: =+B47 -> FEBRERO | H47: 36844.76 | I47: =+B47 -> FEBRERO | J47: =+H47*0.16 -> 5895.1616 | K47: =+B47 -> FEBRERO | L47: =+J47/0.16 -> 36844.76 | M47: =+H47-L47 -> 0 | N47: =+H47+J47 -> 42739.922 | O47: PUE | P47: =+N47 -> 42739.922 | Q47: =+N47-P47 -> 0
A48: =IF(C48>0,MONTH(C48),0) -> 2 | B48: =VLOOKUP(A48,[1]Hoja3!$C$3:$D$14,2,FALSE) -> FEBRERO | C48: 45330.351 | D48: TOTAL PLAY TELECOMUNICACIONES | E48: TPT890516JP5 | F48: TP347639885658514269_1_A1-456311908 | G48: =+B48 -> FEBRERO | H48: 42.95 | I48: =+B48 -> FEBRERO | J48: =+H48*0.16 -> 6.872 | K48: =+B48 -> FEBRERO | L48: =+J48/0.16 -> 42.95 | M48: =+H48-L48 -> 0 | N48: =+H48+J48 -> 49.822 | O48: PUE | P48: =+N48 -> 49.822 | Q48: =+N48-P48 -> 0
A49: =IF(C49>0,MONTH(C49),0) -> 2 | B49: =VLOOKUP(A49,[1]Hoja3!$C$3:$D$14,2,FALSE) -> FEBRERO | C49: 45330.351 | D49: TOTAL PLAY TELECOMUNICACIONES | E49: TPT890516JP5 | F49: TP347639885658471424_0_A1-456311909 | G49: =+B49 -> FEBRERO | H49: 0.15 | I49: =+B49 -> FEBRERO | J49: =+H49*0.16 -> 0.024 | K49: =+B49 -> FEBRERO | L49: =+J49/0.16 -> 0.15 | M49: =+H49-L49 -> 0 | N49: =+H49+J49 -> 0.174 | O49: PUE | P49: =+N49 -> 0.174 | Q49: =+N49-P49 -> 0
A50: =IF(C50>0,MONTH(C50),0) -> 2 | B50: =VLOOKUP(A50,[1]Hoja3!$C$3:$D$14,2,FALSE) -> FEBRERO | C50: 45330.407 | D50: BANCOPPEL, S.A. INSTITUCION DE BANCA MULTIPLE | E50: BSI061110963 | F50: 202410144717444 | G50: =+B50 -> FEBRERO | H50: 0.01 | I50: =+B50 -> FEBRERO | J50: =+H50*0.16 -> 0.0016 | K50: =+B50 -> FEBRERO | L50: =+J50/0.16 -> 0.01 | M50: =+H50-L50 -> 0 | N50: =+H50+J50 -> 0.0116 | O50: PUE | P50: =+N50 -> 0.0116 | Q50: =+N50-P50 -> 0
A51: =IF(C51>0,MONTH(C51),0) -> 2 | B51: =VLOOKUP(A51,[1]Hoja3!$C$3:$D$14,2,FALSE) -> FEBRERO | C51: 45333.658 | D51: MARIA GRICELDA BARAJAS OLIVA | E51: BAOG961112Q60 | F51: 1864 | G51: =+B51 -> FEBRERO | H51: 30000 | I51: =+B51 -> FEBRERO | J51: =+H51*0.16 -> 4800 | K51: =+B51 -> FEBRERO | L51: =+J51/0.16 -> 30000 | M51: =+H51-L51 -> 0 | N51: =+H51+J51 -> 34800 | O51: PUE | P51: =+N51 -> 34800 | Q51: =+N51-P51 -> 0
A52: =IF(C52>0,MONTH(C52),0) -> 2 | B52: =VLOOKUP(A52,[1]Hoja3!$C$3:$D$14,2,FALSE) -> FEBRERO | C52: 45333.833 | D52: TOTAL BOX | E52: TBO140305DH0 | F52: TP347692662647703490P1-337460186T1-4 | G52: =+B52 -> FEBRERO | H52: 0 | I52: =+B52 -> FEBRERO | J52: =+H52*0.16 -> 0 | K52: =+B52 -> FEBRERO | L52: =+J52/0.16 -> 0 | M52: =+H52-L52 -> 0 | N52: =+H52+J52 -> 0 | P52: =+N52 -> 0 | Q52: =+N52-P52 -> 0
A53: =IF(C53>0,MONTH(C53),0) -> 2 | B53: =VLOOKUP(A53,[1]Hoja3!$C$3:$D$14,2,FALSE) -> FEBRERO | C53: 45333.833 | D53: TOTAL PLAY TELECOMUNICACIONES | E53: TPT890516JP5 | F53: TP347692662647702466P1-337460186T1-0 | G53: =+B53 -> FEBRERO | H53: 0 | I53: =+B53 -> FEBRERO | J53: =+H53*0.16 -> 0 | K53: =+B53 -> FEBRERO | L53: =+J53/0.16 -> 0 | M53: =+H53-L53 -> 0 | N53: =+H53+J53 -> 0 | P53: =+N53 -> 0 | Q53: =+N53-P53 -> 0
A54: =IF(C54>0,MONTH(C54),0) -> 2 | B54: =VLOOKUP(A54,[1]Hoja3!$C$3:$D$14,2,FALSE) -> FEBRERO | C54: 45334.638 | D54: CAJA POPULAR MEXICANA | E54: CPM960127M3A | G54: =+B54 -> FEBRERO | H54: 3127.21 | I54: =+B54 -> FEBRERO | J54: =+H54*0.16 -> 500.3536 | K54: =+B54 -> FEBRERO | L54: =+J54/0.16 -> 3127.21 | M54: =+H54-L54 -> 0 | N54: =+H54+J54 -> 3627.5636 | O54: PUE | P54: =+N54 -> 3627.5636 | Q54: =+N54-P54 -> 0
A55: =IF(C55>0,MONTH(C55),0) -> 2 | B55: =VLOOKUP(A55,[1]Hoja3!$C$3:$D$14,2,FALSE) -> FEBRERO | C55: 45335.541 | D55: MEGA GASOLINERAS | E55: MGA110810CC3 | F55: LIB376784 | G55: =+B55 -> FEBRERO | H55: 519.19 | I55: =+B55 -> FEBRERO | J55: =+H55*0.16 -> 83.0704 | K55: =+B55 -> FEBRERO | L55: =+J55/0.16 -> 519.19 | M55: =+H55-L55 -> 0 | N55: =+H55+J55 -> 602.2604 | O55: PUE | P55: =+N55 -> 602.2604 | Q55: =+N55-P55 -> 0
A56: =IF(C56>0,MONTH(C56),0) -> 2 | B56: =VLOOKUP(A56,[1]Hoja3!$C$3:$D$14,2,FALSE) -> FEBRERO | C56: 45335.639 | D56: PRODUCTOS ROLINJERS | E56: PRO1502249T4 | F56: F1875 | G56: =+B56 -> FEBRERO | H56: 3690 | I56: =+B56 -> FEBRERO | J56: =+H56*0.16 -> 590.4 | K56: =+B56 -> FEBRERO | L56: =+J56/0.16 -> 3690 | M56: =+H56-L56 -> 0 | N56: =+H56+J56 -> 4280.4 | O56: PUE | P56: =+N56 -> 4280.4 | Q56: =+N56-P56 -> 0
A57: =IF(C57>0,MONTH(C57),0) -> 2 | B57: =VLOOKUP(A57,[1]Hoja3!$C$3:$D$14,2,FALSE) -> FEBRERO | C57: 45336.999 | D57: HERIBERTO JIMENEZ AVILA | E57: JIAH810501A8A | F57: F716 | G57: =+B57 -> FEBRERO | H57: 31180 | I57: =+B57 -> FEBRERO | J57: =+H57*0.16 -> 4988.8 | K57: =+B57 -> FEBRERO | L57: =+J57/0.16 -> 31180 | M57: =+H57-L57 -> 0 | N57: =+H57+J57 -> 36168.8 | O57: PUE | P57: =+N57 -> 36168.8 | Q57: =+N57-P57 -> 0
A58: =IF(C58>0,MONTH(C58),0) -> 2 | B58: =VLOOKUP(A58,[1]Hoja3!$C$3:$D$14,2,FALSE) -> FEBRERO | C58: 45337.043 | D58: MINIBODEGAS Y ALMACENAMIENTO MEXICO | E58: MAL1511111U9 | F58: F120 | G58: =+B58 -> FEBRERO | H58: 2327.59 | I58: =+B58 -> FEBRERO | J58: =+H58*0.16 -> 372.4144 | K58: =+B58 -> FEBRERO | L58: =+J58/0.16 -> 2327.59 | M58: =+H58-L58 -> 0 | N58: =+H58+J58 -> 2700.0044 | O58: PUE | P58: =+N58 -> 2700.0044 | Q58: =+N58-P58 -> 0
A59: =IF(C59>0,MONTH(C59),0) -> 2 | B59: =VLOOKUP(A59,[1]Hoja3!$C$3:$D$14,2,FALSE) -> FEBRERO | C59: 45337.429 | D59: RADIOMOVIL DIPSA | E59: RDI841003QJ4 | F59: PF0060805448 | G59: =+B59 -> FEBRERO | H59: 0 | I59: =+B59 -> FEBRERO | J59: =+H59*0.16 -> 0 | K59: =+B59 -> FEBRERO | L59: =+J59/0.16 -> 0 | M59: =+H59-L59 -> 0 | N59: =+H59+J59 -> 0 | P59: =+N59 -> 0 | Q59: =+N59-P59 -> 0
A60: =IF(C60>0,MONTH(C60),0) -> 2 | B60: =VLOOKUP(A60,[1]Hoja3!$C$3:$D$14,2,FALSE) -> FEBRERO | C60: 45337.561 | D60: J. SOCORRO ALMANZA CARRILLO | E60: AACJ680307H3A | F60: 9 | G60: =+B60 -> FEBRERO | H60: 13000 | I60: =+B60 -> FEBRERO | J60: =+H60*0.16 -> 2080 | K60: =+B60 -> FEBRERO | L60: =+J60/0.16 -> 13000 | M60: =+H60-L60 -> 0 | N60: =+H60+J60 -> 15080 | O60: PUE | P60: =+N60 -> 15080 | Q60: =+N60-P60 -> 0
A61: =IF(C61>0,MONTH(C61),0) -> 2 | B61: =VLOOKUP(A61,[1]Hoja3!$C$3:$D$14,2,FALSE) -> FEBRERO | C61: 45339.857 | D61: MEGA GASOLINERAS | E61: MGA110810CC3 | F61: LIB377083 | G61: =+B61 -> FEBRERO | H61: 1105.69 | I61: =+B61 -> FEBRERO | J61: =+H61*0.16 -> 176.9104 | K61: =+B61 -> FEBRERO | L61: =+J61/0.16 -> 1105.69 | M61: =+H61-L61 -> 0 | N61: =+H61+J61 -> 1282.6004 | O61: PUE | P61: =+N61 -> 1282.6004 | Q61: =+N61-P61 -> 0
A62: =IF(C62>0,MONTH(C62),0) -> 2 | B62: =VLOOKUP(A62,[1]Hoja3!$C$3:$D$14,2,FALSE) -> FEBRERO | C62: 45342.597 | D62: SAN JORGE Y CIA. | E62: SJC080617R86 | F62: DTE5114 | G62: =+B62 -> FEBRERO | H62: 1704.72 | I62: =+B62 -> FEBRERO | J62: =+H62*0.16 -> 272.7552 | K62: =+B62 -> FEBRERO | L62: =+J62/0.16 -> 1704.72 | M62: =+H62-L62 -> 0 | N62: =+H62+J62 -> 1977.4752 | O62: PUE | P62: =+N62 -> 1977.4752 | Q62: =+N62-P62 -> 0
A63: =IF(C63>0,MONTH(C63),0) -> 2 | B63: =VLOOKUP(A63,[1]Hoja3!$C$3:$D$14,2,FALSE) -> FEBRERO | C63: 45342.597 | D63: SAN JORGE Y CIA. | E63: SJC080617R86 | F63: DTE5115 | G63: =+B63 -> FEBRERO | H63: 1201.6 | I63: =+B63 -> FEBRERO | J63: =+H63*0.16 -> 192.256 | K63: =+B63 -> FEBRERO | L63: =+J63/0.16 -> 1201.6 | M63: =+H63-L63 -> 0 | N63: =+H63+J63 -> 1393.856 | O63: PUE | P63: =+N63 -> 1393.856 | Q63: =+N63-P63 -> 0
A64: =IF(C64>0,MONTH(C64),0) -> 2 | B64: =VLOOKUP(A64,[1]Hoja3!$C$3:$D$14,2,FALSE) -> FEBRERO | C64: 45342.597 | D64: SAN JORGE Y CIA. | E64: SJC080617R86 | F64: DTE5116 | G64: =+B64 -> FEBRERO | H64: 1916.34 | I64: =+B64 -> FEBRERO | J64: =+H64*0.16 -> 306.6144 | K64: =+B64 -> FEBRERO | L64: =+J64/0.16 -> 1916.34 | M64: =+H64-L64 -> 0 | N64: =+H64+J64 -> 2222.9544 | O64: PUE | P64: =+N64 -> 2222.9544 | Q64: =+N64-P64 -> 0
A65: =IF(C65>0,MONTH(C65),0) -> 2 | B65: =VLOOKUP(A65,[1]Hoja3!$C$3:$D$14,2,FALSE) -> FEBRERO | C65: 45343.522 | D65: SOCIEDAD COOPERATIVA DE PRODUCCION PESQUERA 21 DE MARZO | E65: SCP680430MF0 | F65: 14388 | G65: =+B65 -> FEBRERO | H65: 5640 | I65: =+B65 -> FEBRERO | J65: =+H65*0.16 -> 902.4 | K65: =+B65 -> FEBRERO | L65: =+J65/0.16 -> 5640 | M65: =+H65-L65 -> 0 | N65: =+H65+J65 -> 6542.4 | O65: PUE | P65: =+N65 -> 6542.4 | Q65: =+N65-P65 -> 0
A66: =IF(C66>0,MONTH(C66),0) -> 2 | B66: =VLOOKUP(A66,[1]Hoja3!$C$3:$D$14,2,FALSE) -> FEBRERO | C66: 45343.662 | D66: SOCIEDAD COOPERATIVA DE PRODUCCION PESQUERA 21 DE MARZO | E66: SCP680430MF0 | F66: 14393 | G66: =+B66 -> FEBRERO | H66: 1980 | I66: =+B66 -> FEBRERO | J66: =+H66*0.16 -> 316.8 | K66: =+B66 -> FEBRERO | L66: =+J66/0.16 -> 1980 | M66: =+H66-L66 -> 0 | N66: =+H66+J66 -> 2296.8 | O66: PUE | P66: =+N66 -> 2296.8 | Q66: =+N66-P66 -> 0
A67: =IF(C67>0,MONTH(C67),0) -> 2 | B67: =VLOOKUP(A67,[1]Hoja3!$C$3:$D$14,2,FALSE) -> FEBRERO | C67: 45344.601 | D67: MEGA GASOLINERAS | E67: MGA110810CC3 | F67: EMS54436 | G67: =+B67 -> FEBRERO | H67: 519.19 | I67: =+B67 -> FEBRERO | J67: =+H67*0.16 -> 83.0704 | K67: =+B67 -> FEBRERO | L67: =+J67/0.16 -> 519.19 | M67: =+H67-L67 -> 0 | N67: =+H67+J67 -> 602.2604 | O67: PUE | P67: =+N67 -> 602.2604 | Q67: =+N67-P67 -> 0
A68: =IF(C68>0,MONTH(C68),0) -> 2 | B68: =VLOOKUP(A68,[1]Hoja3!$C$3:$D$14,2,FALSE) -> FEBRERO | C68: 45344.623 | D68: SAN JORGE Y CIA. | E68: SJC080617R86 | F68: DTE5120 | G68: =+B68 -> FEBRERO | H68: 2682.56 | I68: =+B68 -> FEBRERO | J68: =+H68*0.16 -> 429.2096 | K68: =+B68 -> FEBRERO | L68: =+J68/0.16 -> 2682.56 | M68: =+H68-L68 -> 0 | N68: =+H68+J68 -> 3111.7696 | O68: PUE | P68: =+N68 -> 3111.7696 | Q68: =+N68-P68 -> 0
A69: =IF(C69>0,MONTH(C69),0) -> 2 | B69: =VLOOKUP(A69,[1]Hoja3!$C$3:$D$14,2,FALSE) -> FEBRERO | C69: 45344.658 | D69: MARIA GRICELDA BARAJAS OLIVA | E69: BAOG961112Q60 | F69: 1896 | G69: =+B69 -> FEBRERO | H69: 12085 | I69: =+B69 -> FEBRERO | J69: =+H69*0.16 -> 1933.6 | K69: =+B69 -> FEBRERO | L69: =+J69/0.16 -> 12085 | M69: =+H69-L69 -> 0 | N69: =+H69+J69 -> 14018.6 | O69: PUE | P69: =+N69 -> 14018.6 | Q69: =+N69-P69 -> 0
A70: =IF(C70>0,MONTH(C70),0) -> 2 | B70: =VLOOKUP(A70,[1]Hoja3!$C$3:$D$14,2,FALSE) -> FEBRERO | C70: 45344.66 | D70: MARIA GRICELDA BARAJAS OLIVA | E70: BAOG961112Q60 | F70: 1897 | G70: =+B70 -> FEBRERO | H70: 2970 | I70: =+B70 -> FEBRERO | J70: =+H70*0.16 -> 475.2 | K70: =+B70 -> FEBRERO | L70: =+J70/0.16 -> 2970 | M70: =+H70-L70 -> 0 | N70: =+H70+J70 -> 3445.2 | O70: PUE | P70: =+N70 -> 3445.2 | Q70: =+N70-P70 -> 0
A71: =IF(C71>0,MONTH(C71),0) -> 2 | B71: =VLOOKUP(A71,[1]Hoja3!$C$3:$D$14,2,FALSE) -> FEBRERO | C71: 45344.774 | D71: SAN JORGE Y CIA. | E71: SJC080617R86 | F71: MAD7842 | G71: =+B71 -> FEBRERO | H71: 2865.93 | I71: =+B71 -> FEBRERO | J71: =+H71*0.16 -> 458.5488 | K71: =+B71 -> FEBRERO | L71: =+J71/0.16 -> 2865.93 | M71: =+H71-L71 -> 0 | N71: =+H71+J71 -> 3324.4788 | O71: PUE | P71: =+N71 -> 3324.4788 | Q71: =+N71-P71 -> 0
P72: =+N72 -> 0 | Q72: =+N72-P72 -> 0
A73: =IF(C73>0,MONTH(C73),0) -> 2 | B73: =VLOOKUP(A73,[1]Hoja3!$C$3:$D$14,2,FALSE) -> FEBRERO | C73: 45346.509 | D73: HERIBERTO JIMENEZ AVILA | E73: JIAH810501A8A | F73: F722 | G73: =+B73 -> FEBRERO | H73: 18300 | I73: =+B73 -> FEBRERO | J73: =+H73*0.16 -> 2928 | K73: =+B73 -> FEBRERO | L73: =+J73/0.16 -> 18300 | M73: =+H73-L73 -> 0 | N73: =+H73+J73 -> 21228 | O73: PUE | P73: =+N73 -> 21228 | Q73: =+N73-P73 -> 0
A74: =IF(C74>0,MONTH(C74),0) -> 2 | B74: =VLOOKUP(A74,[1]Hoja3!$C$3:$D$14,2,FALSE) -> FEBRERO | C74: 45347.407 | D74: MEGA GASOLINERAS | E74: MGA110810CC3 | F74: LIB377637 | G74: =+B74 -> FEBRERO | H74: 1122.55 | I74: =+B74 -> FEBRERO | J74: =+H74*0.16 -> 179.608 | K74: =+B74 -> FEBRERO | L74: =+J74/0.16 -> 1122.55 | M74: =+H74-L74 -> 0 | N74: =+H74+J74 -> 1302.158 | O74: PUE | P74: =+N74 -> 1302.158 | Q74: =+N74-P74 -> 0
A75: =IF(C75>0,MONTH(C75),0) -> 2 | B75: =VLOOKUP(A75,[1]Hoja3!$C$3:$D$14,2,FALSE) -> FEBRERO | C75: 45347.489 | D75: SAN JORGE Y CIA. | E75: SJC080617R86 | F75: MAD7857 | G75: =+B75 -> FEBRERO | H75: 9158.52 | I75: =+B75 -> FEBRERO | J75: =+H75*0.16 -> 1465.3632 | K75: =+B75 -> FEBRERO | L75: =+J75/0.16 -> 9158.52 | M75: =+H75-L75 -> 0 | N75: =+H75+J75 -> 10623.883 | O75: PUE | P75: =+N75 -> 10623.883 | Q75: =+N75-P75 -> 0
A76: =IF(C76>0,MONTH(C76),0) -> 2 | B76: =VLOOKUP(A76,[1]Hoja3!$C$3:$D$14,2,FALSE) -> FEBRERO | C76: 45348.464 | D76: SOCIEDAD COOPERATIVA DE PRODUCCION PESQUERA 21 DE MARZO | E76: SCP680430MF0 | F76: 14411 | G76: =+B76 -> FEBRERO | H76: 2640 | I76: =+B76 -> FEBRERO | J76: =+H76*0.16 -> 422.4 | K76: =+B76 -> FEBRERO | L76: =+J76/0.16 -> 2640 | M76: =+H76-L76 -> 0 | N76: =+H76+J76 -> 3062.4 | O76: PUE | P76: =+N76 -> 3062.4 | Q76: =+N76-P76 -> 0
A77: =IF(C77>0,MONTH(C77),0) -> 2 | B77: =VLOOKUP(A77,[1]Hoja3!$C$3:$D$14,2,FALSE) -> FEBRERO | C77: 45350.4 | D77: BANCOPPEL, S.A. INSTITUCION DE BANCA MULTIPLE | E77: BSI061110963 | F77: 202410052174142 | G77: =+B77 -> FEBRERO | H77: 0.01 | I77: =+B77 -> FEBRERO | J77: =+H77*0.16 -> 0.0016 | K77: =+B77 -> FEBRERO | L77: =+J77/0.16 -> 0.01 | M77: =+H77-L77 -> 0 | N77: =+H77+J77 -> 0.0116 | O77: PUE | P77: =+N77 -> 0.0116 | Q77: =+N77-P77 -> 0
P78: =+N78 -> 0 | Q78: =+N78-P78 -> 0
P79: =+N79 -> 0 | Q79: =+N79-P79 -> 0
P80: =+N80 -> 0 | Q80: =+N80-P80 -> 0
A81: =IF(C81>0,MONTH(C81),0) -> 2 | B81: =VLOOKUP(A81,[1]Hoja3!$C$3:$D$14,2,FALSE) -> FEBRERO | C81: 45350.602 | D81: PESCADERIA BUENA OLA | E81: PBO200626IW3 | F81: BO5185 | G81: =+B81 -> FEBRERO | H81: 18000 | I81: =+B81 -> FEBRERO | J81: =+H81*0.16 -> 2880 | K81: =+B81 -> FEBRERO | L81: =+J81/0.16 -> 18000 | M81: =+H81-L81 -> 0 | N81: =+H81+J81 -> 20880 | O81: PUE | P81: =+N81 -> 20880 | Q81: =+N81-P81 -> 0
A82: =IF(C82>0,MONTH(C82),0) -> 2 | B82: =VLOOKUP(A82,[1]Hoja3!$C$3:$D$14,2,FALSE) -> FEBRERO | C82: 45351.433 | D82: SAN JORGE Y CIA. | E82: SJC080617R86 | F82: DTE5131 | G82: =+B82 -> FEBRERO | H82: 1385.56 | I82: =+B82 -> FEBRERO | J82: =+H82*0.16 -> 221.6896 | K82: =+B82 -> FEBRERO | L82: =+J82/0.16 -> 1385.56 | M82: =+H82-L82 -> 0 | N82: =+H82+J82 -> 1607.2496 | O82: PUE | P82: =+N82 -> 1607.2496 | Q82: =+N82-P82 -> 0
A83: =IF(C83>0,MONTH(C83),0) -> 2 | B83: =VLOOKUP(A83,[1]Hoja3!$C$3:$D$14,2,FALSE) -> FEBRERO | C83: 45351.468 | D83: SAN JORGE Y CIA. | E83: SJC080617R86 | F83: DEL7758 | G83: =+B83 -> FEBRERO | H83: 1927.17 | I83: =+B83 -> FEBRERO | J83: =+H83*0.16 -> 308.3472 | K83: =+B83 -> FEBRERO | L83: =+J83/0.16 -> 1927.17 | M83: =+H83-L83 -> 0 | N83: =+H83+J83 -> 2235.5172 | O83: PUE | P83: =+N83 -> 2235.5172 | Q83: =+N83-P83 -> 0
A84: =IF(C84>0,MONTH(C84),0) -> 2 | B84: =VLOOKUP(A84,[1]Hoja3!$C$3:$D$14,2,FALSE) -> FEBRERO | C84: 45351.573 | D84: MA. DEL ROSARIO CASTILLO GONZALEZ | E84: CAGM570916DJ2 | F84: 413 | G84: =+B84 -> FEBRERO | H84: 3712 | I84: =+B84 -> FEBRERO | J84: =+H84*0.16 -> 593.92 | K84: =+B84 -> FEBRERO | L84: =+J84/0.16 -> 3712 | M84: =+H84-L84 -> 0 | N84: =+H84+J84 -> 4305.92 | O84: PUE | P84: =+N84 -> 4305.92 | Q84: =+N84-P84 -> 0
A85: =IF(C85>0,MONTH(C85),0) -> 3 | B85: =VLOOKUP(A85,[1]Hoja3!$C$3:$D$14,2,FALSE) -> MARZO | C85: 45352.409 | D85: MINIBODEGAS Y ALMACENAMIENTO MEXICO | E85: MAL1511111U9 | F85: F126 | G85: =+B85 -> MARZO | H85: 2327.59 | I85: =+B85 -> MARZO | J85: 372.4144 | K85: =+B85 -> MARZO | L85: =+J85/0.16 -> 2327.59 | M85: =+H85-L85 -> 0 | N85: =+H85+J85 -> 2700.0044 | O85: PUE | P85: 2700 | Q85: =+N85-P85 -> 0.0044
A86: =IF(C86>0,MONTH(C86),0) -> 3 | B86: =VLOOKUP(A86,[1]Hoja3!$C$3:$D$14,2,FALSE) -> MARZO | C86: 45352.76 | D86: BANCO DEL BAJIO | E86: BBA940707IE1 | F86: M | G86: =+B86 -> MARZO | H86: 687.05 | I86: =+B86 -> MARZO | J86: 109.93 | K86: =+B86 -> MARZO | L86: =+J86/0.16 -> 687.0625 | M86: =+H86-L86 -> -0.0125 | N86: =+H86+J86 -> 796.98 | O86: PUE | P86: 796.98 | Q86: =+N86-P86 -> 0
A87: =IF(C87>0,MONTH(C87),0) -> 3 | B87: =VLOOKUP(A87,[1]Hoja3!$C$3:$D$14,2,FALSE) -> MARZO | C87: 45352.882 | D87: MEGA GASOLINERAS | E87: MGA110810CC3 | F87: EMS54915 | G87: =+B87 -> MARZO | H87: 519.19 | I87: =+B87 -> MARZO | J87: 80.81 | K87: =+B87 -> MARZO | L87: =+J87/0.16 -> 505.0625 | M87: =+H87-L87 -> 14.1275 | N87: =+H87+J87 -> 600 | O87: PUE | P87: 600 | Q87: =+N87-P87 -> 0
A88: =IF(C88>0,MONTH(C88),0) -> 3 | B88: =VLOOKUP(A88,[1]Hoja3!$C$3:$D$14,2,FALSE) -> MARZO | C88: 45355.449 | D88: AGROALIMENTOS FRESH HARVEST | E88: AFH200612548 | F88: AG-12672 | G88: =+B88 -> MARZO | H88: 2850 | I88: =+B88 -> MARZO | J88: 0 | K88: =+B88 -> MARZO | L88: =+J88/0.16 -> 0 | M88: =+H88-L88 -> 2850 | N88: =+H88+J88 -> 2850 | O88: PUE | P88: 2850 | Q88: =+N88-P88 -> 0
A89: =IF(C89>0,MONTH(C89),0) -> 3 | B89: =VLOOKUP(A89,[1]Hoja3!$C$3:$D$14,2,FALSE) -> MARZO | C89: 45355.598 | D89: SOCIEDAD COOPERATIVA DE PRODUCCION PESQUERA 21 DE MARZO | E89: SCP680430MF0 | F89: 14447 | G89: =+B89 -> MARZO | H89: 3980 | I89: =+B89 -> MARZO | J89: 0 | K89: =+B89 -> MARZO | L89: =+J89/0.16 -> 0 | M89: =+H89-L89 -> 3980 | N89: =+H89+J89 -> 3980 | O89: PUE | P89: 3980 | Q89: =+N89-P89 -> 0
A90: =IF(C90>0,MONTH(C90),0) -> 3 | B90: =VLOOKUP(A90,[1]Hoja3!$C$3:$D$14,2,FALSE) -> MARZO | C90: 45356.323 | D90: MEGA GASOLINERAS | E90: MGA110810CC3 | F90: LIB378428 | G90: =+B90 -> MARZO | H90: 975.21 | I90: =+B90 -> MARZO | J90: 151.8 | K90: =+B90 -> MARZO | L90: =+J90/0.16 -> 948.75 | M90: =+H90-L90 -> 26.46 | N90: =+H90+J90 -> 1127.01 | O90: PUE | P90: 1127.01 | Q90: =+N90-P90 -> 0
A91: =IF(C91>0,MONTH(C91),0) -> 3 | B91: =VLOOKUP(A91,[1]Hoja3!$C$3:$D$14,2,FALSE) -> MARZO | C91: 45356.522 | D91: PESCADERIA BUENA OLA | E91: PBO200626IW3 | F91: BO5227 | G91: =+B91 -> MARZO | H91: 32432.2 | I91: =+B91 -> MARZO | J91: 0 | K91: =+B91 -> MARZO | L91: =+J91/0.16 -> 0 | M91: =+H91-L91 -> 32432.2 | N91: =+H91+J91 -> 32432.2 | O91: PUE | P91: 32432.2 | Q91: =+N91-P91 -> 0
A92: =IF(C92>0,MONTH(C92),0) -> 3 | B92: =VLOOKUP(A92,[1]Hoja3!$C$3:$D$14,2,FALSE) -> MARZO | C92: 45359.285 | D92: BANCOPPEL, S.A. INSTITUCION DE BANCA MULTIPLE | E92: BSI061110963 | F92: 202410144717444 | G92: =+B92 -> MARZO | H92: 0.01 | I92: =+B92 -> MARZO | K92: =+B92 -> MARZO | L92: =+J92/0.16 -> 0 | M92: =+H92-L92 -> 0.01 | N92: =+H92+J92 -> 0.01 | O92: PUE | P92: 0 | Q92: =+N92-P92 -> 0.01
A93: =IF(C93>0,MONTH(C93),0) -> 3 | B93: =VLOOKUP(A93,[1]Hoja3!$C$3:$D$14,2,FALSE) -> MARZO | C93: 45360.724 | D93: SAN JORGE Y CIA. | E93: SJC080617R86 | F93: MAD7931 | G93: =+B93 -> MARZO | H93: 1924.48 | I93: =+B93 -> MARZO | J93: 0 | K93: =+B93 -> MARZO | L93: =+J93/0.16 -> 0 | M93: =+H93-L93 -> 1924.48 | N93: =+H93+J93 -> 1924.48 | O93: PUE | P93: 1924.48 | Q93: =+N93-P93 -> 0
A94: =IF(C94>0,MONTH(C94),0) -> 3 | B94: =VLOOKUP(A94,[1]Hoja3!$C$3:$D$14,2,FALSE) -> MARZO | C94: 45360.724 | D94: SAN JORGE Y CIA. | E94: SJC080617R86 | F94: MAD7932 | G94: =+B94 -> MARZO | H94: 1972.15 | I94: =+B94 -> MARZO | J94: 0 | K94: =+B94 -> MARZO | L94: =+J94/0.16 -> 0 | M94: =+H94-L94 -> 1972.15 | N94: =+H94+J94 -> 1972.15 | O94: PUE | P94: 1972.15 | Q94: =+N94-P94 -> 0
A95: =IF(C95>0,MONTH(C95),0) -> 3 | B95: =VLOOKUP(A95,[1]Hoja3!$C$3:$D$14,2,FALSE) -> MARZO | C95: 45360.724 | D95: SAN JORGE Y CIA. | E95: SJC080617R86 | F95: MAD7933 | G95: =+B95 -> MARZO | H95: 1875.02 | I95: =+B95 -> MARZO | J95: 0 | K95: =+B95 -> MARZO | L95: =+J95/0.16 -> 0 | M95: =+H95-L95 -> 1875.02 | N95: =+H95+J95 -> 1875.02 | O95: PUE | P95: 1875.02 | Q95: =+N95-P95 -> 0
A96: =IF(C96>0,MONTH(C96),0) -> 3 | B96: =VLOOKUP(A96,[1]Hoja3!$C$3:$D$14,2,FALSE) -> MARZO | C96: 45360.725 | D96: SAN JORGE Y CIA. | E96: SJC080617R86 | F96: MAD7934 | G96: =+B96 -> MARZO | H96: 928.92 | I96: =+B96 -> MARZO | J96: 0 | K96: =+B96 -> MARZO | L96: =+J96/0.16 -> 0 | M96: =+H96-L96 -> 928.92 | N96: =+H96+J96 -> 928.92 | O96: PUE | P96: 928.92 | Q96: =+N96-P96 -> 0
A97: =IF(C97>0,MONTH(C97),0) -> 3 | B97: =VLOOKUP(A97,[1]Hoja3!$C$3:$D$14,2,FALSE) -> MARZO | C97: 45360.725 | D97: SAN JORGE Y CIA. | E97: SJC080617R86 | F97: MAD7935 | G97: =+B97 -> MARZO | H97: 1971.27 | I97: =+B97 -> MARZO | J97: 0 | K97: =+B97 -> MARZO | L97: =+J97/0.16 -> 0 | M97: =+H97-L97 -> 1971.27 | N97: =+H97+J97 -> 1971.27 | O97: PUE | P97: 1971.27 | Q97: =+N97-P97 -> 0
A98: =IF(C98>0,MONTH(C98),0) -> 3 | B98: =VLOOKUP(A98,[1]Hoja3!$C$3:$D$14,2,FALSE) -> MARZO | C98: 45362.609 | D98: SOCIEDAD COOPERATIVA DE PRODUCCION PESQUERA 21 DE MARZO | E98: SCP680430MF0 | F98: 14477 | G98: =+B98 -> MARZO | H98: 4640 | I98: =+B98 -> MARZO | J98: 0 | K98: =+B98 -> MARZO | L98: =+J98/0.16 -> 0 | M98: =+H98-L98 -> 4640 | N98: =+H98+J98 -> 4640 | O98: PUE | P98: 4640 | Q98: =+N98-P98 -> 0
A99: =IF(C99>0,MONTH(C99),0) -> 3 | B99: =VLOOKUP(A99,[1]Hoja3!$C$3:$D$14,2,FALSE) -> MARZO | C99: 45363.505 | D99: MEGA GASOLINERAS | E99: MGA110810CC3 | F99: EMS55220 | G99: =+B99 -> MARZO | H99: 1106.09 | I99: =+B99 -> MARZO | J99: 172.15 | K99: =+B99 -> MARZO | L99: =+J99/0.16 -> 1075.9375 | M99: =+H99-L99 -> 30.1525 | N99: =+H99+J99 -> 1278.24 | O99: PUE | P99: 1278.24 | Q99: =+N99-P99 -> 0
A100: =IF(C100>0,MONTH(C100),0) -> 3 | B100: =VLOOKUP(A100,[1]Hoja3!$C$3:$D$14,2,FALSE) -> MARZO | C100: 45364.035 | D100: HERIBERTO JIMENEZ AVILA | E100: JIAH810501A8A | F100: F792 | G100: =+B100 -> MARZO | H100: 17800 | I100: =+B100 -> MARZO | J100: 0 | K100: =+B100 -> MARZO | L100: =+J100/0.16 -> 0 | M100: =+H100-L100 -> 17800 | N100: =+H100+J100 -> 17800 | O100: PUE | P100: 17800 | Q100: =+N100-P100 -> 0
...

Sheet ISR ANUAL
B2: DECLARACION ANUAL ACTIVIDAD EMPRESARIAL Y PROFESIONAL
F4: IMPORTES
B5: INGRESOS ANUALES ACTIVIDAD EMPRESARIAL | F5: =+'P.F.A.E.'!Q8 -> 3946716.8
B6: INGRESOS OTRO CAPITULO SUELDOS Y SALARIOS | F6: 0
A8: (-) | B8: INGRESOS EXENTOS | F8: 0
A10: (-) | B10: DEDUCCIONES AUTORIZADAS | F10: =+'P.F.A.E.'!Q14 -> 3886661.3
F11: =F5-F10 -> 60055.477
A12: (-) | B12: DEDUCCIONES PERSONALES | F12: ='[2]D.P.A'!J33 -> 0
A13: = | B13: TOTAL DEDUCCIONES | F13: =F10+F12 -> 3886661.3
A14: ISR TARIFA ANUAL ARTICULO 152 LISR
A16: (=) | B16: BASE GRAVABLE | F16: =F5-+F6-F8-F10-F12 -> 60055.477 | G16: =F5-F10-F12 -> 60055.477
A17: (-) | B17: LIMITE INFERIOR | F17: =VLOOKUP(F16,'T ISR'!A121:D131,1,1) -> 8952.5
A18: (=) | B18: EXCEDENTE SOBRE LI | F18: =F16-F17 -> 51102.977
A19: (X) | B19: % Mg. | F19: =VLOOKUP(F16,'T ISR'!A121:D131,4,1) -> 0.064
A20: (=) | B20: IMPUESTO MARGINAL | F20: =F18*F19 -> 3270.5905
A21: (+) | B21: CUOTA FIJA | F21: =VLOOKUP(F16,'T ISR'!A121:D131,3,1) -> 171.88
A22: (=) | B22: TOTAL ISR | F22: =F20+F21 -> 3442.4705
A23: (-) | B23: SUBSIDIO AL EMPLEO
A24: (=) | B24: ISR BRUTO | F24: =F22-F23 -> 3442.4705 | G24: ISR CALCULO ANUAL
A26: (-) | B26: RETENCIONES ISR
A27: (-) | B27: ISR SALARIOS | F27: =+'P.F.A.E.'!Q34 -> 0
A28: (-) | B28: PAGOS PROVISIONALES ACT | F28: =+'P.F.A.E.'!Q36 -> 3443.4705
F29: =F26+F27+F28 -> 3443.4705
A30: (=) | B30: =IF(F29>F24," ISR ANUAL A FAVOR", "ISR ANUAL A CARGO") -> ISR ANUAL A FAVOR | F30: =F24-F26-F27-F28 -> -1 | G30: =F24-F26-F28 -> -1

Sheet D.A.M
D4: REQUISITO DE LAS DEDUCCIONES ARTICULO 27 LISR | J4: REQUISITOS DE LAS DEDUCCIONES ARTICULO 147 LISR
C6: FRACCION I. | D6: GASTOS ESTRICTAMENTE INDISPENSABLE PARA EL DESEMPEÑO DE MI ACTIVIDAD ECONOMICA | J6: III. QUE SE RESTEN UNA SOLA VEZ, AUN CUANDO ESTEN RELACIONADAS CON LA OBTENCION DE DIVERSOS INGRESOS | Q6: ACTIVIDAD PROFESIONAL ABOGADO | S6: ABOGADO | T6: GASOLINA
Q7: ACT. EMP. ING. PLATAFORMAS | S7: UBER | T7: GASOLINA
C10: FRACCION III. | D10: ESTAR AMPARADOS CON UN CFDI. Y QUE LOS PAGOS CUYO MONTO EXCEDA DE $2,000.00 SE EFECTUEN MEDIANTE TRANSFERENCIA ELECTRONICA DE FONDOS Y MEDIANTE MONEDEROS ELECTRONICOS AUTORIZADOS POR EL SAT | J10: VIII. PLAZO PARA REUNIR REQUISITOS DE LAS DEDUCCIONES: QUE AL REALIZAR LAS OPERACIONES CORRESPONDIENTES O A MAS TARDAR EL ULTIMO DIA DEL EJERCICIO, SE REUNAN LOS REQUISITOS QUE PARA CADA DEDUCCION EN LO PARTICULAR ESTABLECE ESTA LEY. QUE TRATANDOSE DE CFDI, SE OBTENGA A MAS TARDAR EL DIA EN QUE EL CONTRIBUYENTE DEBA DE PRESENTAR SE DECLARACION DEL EJERCICIO
C16: COMBUSTIBLES | D16: LA FORMA DE PAGO DE COMBUSTIBLES PARA VEHÍCULOS MARITIMOS, AEREOS Y TERRESTRES LA FORMA DE PAGO DEBERA EFECTUARSE MEDIANTE TRANSFERENCIA ELECTRONICA DE FONDOS, CHEQUE NOMINATIVO, TARJETA DE CREDITO, DEBITO O MONEDEROS ELECTRONICOS AUTORIZADOS POR EL SAT
K19: 0
C22: PAGO INCLUYE IVA | D22: EL LIMITE DEL MONTO DE LOS $2,000.00 INCLUYEN IVA
C25: ACTIVO FIJO | L25: INGRESOS | M25: 100 MIL INGRESOS MES
C26: DEDUCE VIA DEPRECIACION | L26: FACTURADO | M26: 125 MIL PESOS
C28: 150000 | D28: =C28*25% -> 37500 | E28: =D28/12 -> 3125
C29: 0.25 | D29: 12
C30: 0.25 | D30: 12
C31: 0.25 | D31: 12
C32: 0.25 | D32: 12
D33: =SUM(D29:D32) -> 48
C34: ENERO
C35: 150000 | D35: 5000 | E35: 5000
C36: =C35*0.16 -> 24000 | D36: =D35*0.16 -> 800
C43: llantas 4 $10 mil pesos | G43: 2 mil pesos en efectivo
C44: cajas carton | G44: 8 mil pesos tc /td/ transf
C45: renta local
C46: luz
C47: gas
C48: mantto.
C49: adqui materia prima

Sheet D.P.A
B11: DEDUCCIONES PERSONALES AUTORIZADAS ART. 151 LISR
H14: INGRESO ACUMULABLE
H15: INGRESO GRAVADO | J15: APORTACIONES ANUALES
B17: USO CFDI | C17: FORMA DE PAGO | D17: TIPO DE DECCION ANUAL | E17: RAZON SOCIAL | F17: RFC | G17: % | H17: TOPE DEDUCCION | J17: SUB TOTAL | K17: IVA | L17: TOTAL | M17: MONTO NO DEDUCIBLE | N17: MONTO DEDUCIBLE
B18: D01 | C18: TARJETA | D18: HONORARIOS MEDICOS, DENTALES Y GASTOS HOSPITALARIOS | E18: HOSPITAL ANGELEZ DEL SUR | F18: HADS874521K47 | G18: 0.15
B19: D02 | C19: TARJETA | D19: GASTOS MEDICOS POR INCAPACIDAD
B20: D03 | C20: EFECTIVO Y TARJETA | D20: GASTOS FUNERARIOS | E20: JARDIN GUADALUPANO | F20: GDLP547854K47 | G20: 0.15
B21: D04 | C21: EFECTIVO Y TARJETA | D21: DONATIVOS | E21: ALBERGUE OAXAQUEÑOS | F21: ALBOAX5478K47 | G21: 7%,4%
B22: D05 | C22: EFECTIVO Y TARJETA | D22: INTERES REAL CREDITO INFONAVIT | E22: INFONAVIT VIVIENDA XXI | F22: INFT14525K4757 | G22: 0.15
B23: D06 | C23: EFECTIVO Y TARJETA | D23: APORTACIONES COMPLEMENTARIAS AFORE | E23: AFORE SIGLO XXI | F23: AFRGT854785K47 | G23: 0.1
B24: D07 | C24: TARJETA | D24: PRIMAS POR SEGUROS DE GASTOS MEDICOS | E24: SERVICIO MEDICO CDMX SA | F24: SMDN4587K4725 | G24: 0.15
B25: D08 | C25: TARJETA | D25: TRANSPORTACION ESCOLAR | E25: SERVICO ESCOLAR DE TRANSPORTE | F25: GHSTFVD5874DL | G25: 0.15
B26: D09 | C26: TARJETA | D26: DEPOSITOS EN CUENTA PARA EL AHORRO, PLANES DE PENSIONES
B27: D10 | C27: TARJETA | D27: COLEGIATURAS | E27: GRADO ESCOLAR
E28: PREESCOLAR | H28: 14200
E29: PRIMARIA | H29: 12900
E30: SECUNDARIA | H30: 19900
E31: PROFESIONAL TECNICO | H31: 17100
E32: BACHILLER | H32: 24500
B33: TOTALES | J33: =SUM(J18:J32) -> 0 | K33: =SUM(K18:K32) -> 0 | L33: =SUM(L18:L32) -> 0 | M33: =SUM(M18:M32) -> 0 | N33: =SUM(N18:N32) -> 0

Sheet control p.y g.
B1: TABLA DE UTILIDAD NETA | I1: BASE IVA ACREDITABLE | J1: IVA ACREDITABLE | M1: FACTURA PUBLICO EN GENERAL
B2: MES | C2: TOTAL EGRESOS F. | D2: TOTAL INGRESOS F. | E2: INGRESOS GENERAL | F2: GASTOS GENERAL | G2: UTILIDAD MENSUAL
B3: enero | C3: 303686.29 | D3: =SUMIF(ING!$E2:M$600,"*"&B43&"*",ING!$F2:N$600) -> 310579 | E3: =+ganancia!M313 -> 362050 | F3: =+GASTO!M344 -> 113772 | G3: =+D3+E3-C3-F3-M3 -> -4974.29 | I3: 303686.29 | J3: =+I3*0.16 -> 48589.806 | K3: =+D3-C3 -> 6892.71 | M3: 260145
B4: febrero | C4: =SUMIF(EGR!$E1:H$986,"*"&B4&"*",EGR!$F1:O$986) -> 224265.94 | D4: =SUMIF(ING!$E2:M$600,"*"&B4&"*",ING!$F2:N$600) -> 230572.03 | E4: =+ganancia!M607 -> 498010 | F4: =+GASTO!M656 -> 189819 | G4: =+D4+E4-C4-F4-M4 -> 119263.09 | I4: =SUMIF(EGR!$K1:T$982,"*"&B4&"*",EGR!$L1:U$982) -> 228607.76 | J4: =+I4*0.16 -> 36577.242 | K4: =+D4-C4 -> 6306.0945 | M4: 195234
B5: marzo | C5: =SUMIF(EGR!$E2:N$982,"*"&B5&"*",EGR!$F2:O$982) -> 236808.89 | D5: =SUMIF(ING!$E2:M$600,"*"&B5&"*",ING!$F2:N$600) -> 240808.89 | E5: =+ganancia!M922 -> 772929 | F5: =+GASTO!M1001 -> 158781 | G5: =+D5+E5-C5-F5-M5 -> 457390.39 | I5: =SUMIF(EGR!$K2:T$982,"*"&B5&"*",EGR!$L2:U$982) -> 12764.778 | J5: =+I5*0.16 -> 2042.3644 | K5: =+D5-C5 -> 3999.9933 | M5: 160757.6
B6: abril | C6: =SUMIF(EGR!$E3:N$982,"*"&B6&"*",EGR!$F3:O$982) -> 354090.89 | D6: =SUMIF(ING!$E3:M$600,"*"&B6&"*",ING!$F3:N$600) -> 357091.76 | E6: =+ganancia!M1226 -> 364997 | F6: =+GASTO!M1336 -> 238987 | G6: =+D6+E6-C6-F6-M6 -> -227223.13 | I6: =SUMIF(EGR!$K3:T$982,"*"&B6&"*",EGR!$L3:U$982) -> 7445.7775 | J6: =+I6*0.16 -> 1191.3244 | K6: =+D6-C6 -> 3000.8667 | M6: 356234
B7: mayo | C7: =SUMIF(EGR!$E4:N$982,"*"&B7&"*",EGR!$F4:O$982) -> 359428.77 | D7: =SUMIF(ING!$E4:M$600,"*"&B7&"*",ING!$F4:N$600) -> 362431.69 | E7: =+ganancia!M1540 -> 216881 | F7: =+GASTO!M1681 -> 92523 | G7: =+D7+E7-C7-F7-M7 -> -177462.08 | I7: =SUMIF(EGR!$K4:T$982,"*"&B7&"*",EGR!$L4:U$982) -> 10422.32 | J7: =+I7*0.16 -> 1667.5712 | K7: =+D7-C7 -> 3002.9185 | M7: 304823
B8: junio | C8: =SUMIF(EGR!$E5:N$982,"*"&B8&"*",EGR!$F5:O$982) -> 426702.99 | D8: =SUMIF(ING!$E5:M$600,"*"&B8&"*",ING!$F5:N$600) -> 424706 | E8: =+ganancia!M1844 -> 277597 | F8: =+GASTO!M2015 -> 78962 | G8: =+D8+E8-C8-F8-M8 -> -203950.99 | I8: =SUMIF(EGR!$K5:T$982,"*"&B8&"*",EGR!$L5:U$982) -> 159173 | J8: =+I8*0.16 -> 25467.68 | K8: =+D8-C8 -> -1996.99 | M8: 400589
B9: julio | C9: =SUMIF(EGR!$E6:N$982,"*"&B9&"*",EGR!$F6:O$982) -> 260003.44 | D9: =SUMIF(ING!$E6:M$600,"*"&B9&"*",ING!$F6:N$600) -> 272396.1 | E9: =+ganancia!M2157 -> 334562 | F9: =+GASTO!M2360 -> 91811 | G9: =+D9+E9-C9-F9-M9 -> 41489.664 | I9: =SUMIF(EGR!$K6:T$982,"*"&B9&"*",EGR!$L6:U$982) -> 15790.578 | J9: =+I9*0.16 -> 2526.4924 | K9: =+D9-C9 -> 12392.664 | M9: 213654
B10: agosto | C10: =SUMIF(EGR!$E7:N$982,"*"&B10&"*",EGR!$F7:O$982) -> 240167.35 | D10: =SUMIF(ING!$E7:M$600,"*"&B10&"*",ING!$F7:N$600) -> 247594.93 | E10: =+ganancia!M2470 -> 335589 | F10: =+GASTO!M2704 -> 120482 | G10: =+D10+E10-C10-F10-M10 -> 17967.585 | I10: =SUMIF(EGR!$K7:T$982,"*"&B10&"*",EGR!$L7:U$982) -> 20983.1 | J10: =+I10*0.16 -> 3357.296 | K10: =+D10-C10 -> 7427.585 | M10: 204567
B11: septiembre | C11: =SUMIF(EGR!$E8:N$982,"*"&B11&"*",EGR!$F8:O$982) -> 329447.37 | D11: =SUMIF(ING!$E8:M$600,"*"&B11&"*",ING!$F8:N$600) -> 336307.21 | E11: =+ganancia!M2775 -> 433121 | F11: =+GASTO!M3039 -> 81667 | G11: =+D11+E11-C11-F11-M11 -> 69877.836 | I11: =SUMIF(EGR!$K8:T$982,"*"&B11&"*",EGR!$L8:U$982) -> 19558.553 | J11: =+I11*0.16 -> 3129.3684 | K11: =+D11-C11 -> 6859.8363 | M11: 288436
B12: octubre | C12: =SUMIF(EGR!$E9:N$982,"*"&B12&"*",EGR!$F9:O$982) -> 355882.93 | D12: =SUMIF(ING!$E9:M$600,"*"&B12&"*",ING!$F9:N$600) -> 359882.55 | E12: =+ganancia!M3088 -> 221078 | F12: =+GASTO!M3384 -> 80391 | G12: =+D12+E12-C12-F12-M12 -> 144686.62 | I12: =SUMIF(EGR!$K9:T$982,"*"&B12&"*",EGR!$L9:U$982) -> 25572.574 | J12: =+I12*0.16 -> 4091.6118 | K12: =+D12-C12 -> 3999.6241
B13: noviembre | C13: =SUMIF(EGR!$E10:N$982,"*"&B13&"*",EGR!$F10:O$982) -> 275458.4 | D13: =SUMIF(ING!$E10:M$600,"*"&B13&"*",ING!$F10:N$600) -> 279550.69 | E13: =+ganancia!M3391 -> 0 | F13: =+GASTO!M3718 -> 0 | G13: =+D13+E13-C13-F13-M13 -> 4092.292 | I13: =SUMIF(EGR!$K10:T$982,"*"&B13&"*",EGR!$L10:U$982) -> 18207.446 | J13: =+I13*0.16 -> 2913.1914 | K13: =+D13-C13 -> 4092.292
B14: diciembre | C14: =SUMIF(EGR!$E11:N$982,"*"&B14&"*",EGR!$F11:O$982) -> 520718.05 | D14: =SUMIF(ING!$E11:M$600,"*"&B14&"*",ING!$F11:N$600) -> 524795.93 | E14: =+ganancia!M3704 -> 0 | F14: =+GASTO!M4063 -> 0 | G14: =+D14+E14-C14-F14-M14 -> 4077.883 | I14: =SUMIF(EGR!$K11:T$982,"*"&B14&"*",EGR!$L11:U$982) -> 19375.174 | J14: =+I14*0.16 -> 3100.0278 | K14: =+D14-C14 -> 4077.883
A15: TOTAL ANUAL | C15: =SUM(C3:C14) -> 3886661.3 | D15: =SUM(D3:D14) -> 3946716.8 | E15: =SUM(E3:E14) -> 3816814 | F15: =SUM(F3:F14) -> 1247195 | G15: =SUM(G3:G14) -> 245234.88 | H15: =+D15+E15-C15-F15 -> 2629674.5
A16: UTILIDAD ANUAL
B43: ENERO

Sheet ganancia
A1: LOCAL MEDINA | G1: LOCAL SAN PEDRO
A2: 45292 | G2: 45292
A3: Concepto | B3: Efectivo | C3: Transferencia | D3: Credito | E3: P. tarjeta | G3: Concepto | H3: Efectivo | I3: Transferencia | J3: Credito | K3: P. tarjeta
A4: V. LOCAL | G4: V. LOCAL
A5: P. CLIENTES
A9: TOTAL | B9: =SUM(B4:B8) -> 0 | C9: =SUM(C4:C8) -> 0 | D9: =SUM(D4:D8) -> 0 | E9: =SUM(E4:E8) -> 0 | G9: TOTAL | H9: =SUM(H4:H8) -> 0 | I9: =SUM(I4:I8) -> 0 | J9: =SUM(J4:J8) -> 0 | K9: =SUM(K4:K8) -> 0
A10: TOTAL GRAL. | B10: =+B9+C9+D9+E9 -> 0 | G10: TOTAL GRAL. | H10: =+H9+I9+J9+K9 -> 0
A11: LOCAL MEDINA | G11: LOCAL SAN PEDRO
A12: 45293 | G12: 45293
A13: Concepto | B13: Efectivo | C13: Transferencia | D13: Credito | E13: P. tarjeta | G13: Concepto | H13: Efectivo | I13: Transferencia | J13: Credito | K13: P. tarjeta
A14: V. LOCAL | B14: 180 | G14: V. LOCAL
A15: P. CLIENTES | B15: 37214
A19: TOTAL | B19: =SUM(B14:B18) -> 37394 | C19: =SUM(C14:C18) -> 0 | D19: =SUM(D14:D18) -> 0 | E19: =SUM(E14:E18) -> 0 | G19: TOTAL | H19: =SUM(H14:H18) -> 0 | I19: =SUM(I14:I18) -> 0 | J19: =SUM(J14:J18) -> 0 | K19: =SUM(K14:K18) -> 0
A20: TOTAL GRAL. | B20: =+B19+C19+D19+E19 -> 37394 | G20: TOTAL GRAL. | H20: =+H19+I19+J19+K19 -> 0
A21: LOCAL MEDINA | G21: LOCAL SAN PEDRO
A22: 45294 | G22: 45294
A23: Concepto | B23: Efectivo | C23: Transferencia | D23: Credito | E23: P. tarjeta | G23: Concepto | H23: Efectivo | I23: Transferencia | J23: Credito | K23: P. tarjeta
A24: V. LOCAL | B24: 3933 | G24: V. LOCAL
A25: P. CLIENTES
A29: TOTAL | B29: =SUM(B24:B28) -> 3933 | C29: =SUM(C24:C28) -> 0 | D29: =SUM(D24:D28) -> 0 | E29: =SUM(E24:E28) -> 0 | G29: TOTAL | H29: =SUM(H24:H28) -> 0 | I29: =SUM(I24:I28) -> 0 | J29: =SUM(J24:J28) -> 0 | K29: =SUM(K24:K28) -> 0
A30: TOTAL GRAL. | B30: =+B29+C29+D29+E29 -> 3933 | G30: TOTAL GRAL. | H30: =+H29+I29+J29+K29 -> 0
A31: LOCAL MEDINA | G31: LOCAL SAN PEDRO
A32: 45295 | G32: 45295
A33: Concepto | B33: Efectivo | C33: Transferencia | D33: Credito | E33: P. tarjeta | G33: Concepto | H33: Efectivo | I33: Transferencia | J33: Credito | K33: P. tarjeta
A34: V. LOCAL | G34: V. LOCAL
A35: P. CLIENTES
